[1,["ecpdLyjvZBwrvm+cedCcQy","a6LVbNoupIirIDrApqMG8A","72FBGT1tRNg4Ptm82ALNi3","ccBMhAU1RGpbuCVq29NdXy","89CucvXeRG4o5AEufVPmKb","d6iceZ35lJVoiudennZUiH","a2MjXRFdtLlYQ5ouAFv/+R","3ae7efMv1CLq2ilvUY/tQi","67qn38sKlF47fhCbPgplpm","dflqV91PpDlpbD59nVCC5g","30vTa39I1ANbxNo4mbm2AV","a6Q4bPvBtM5YUQU0sml8pM","332/Ypp/NGk4YUzVKUjwjp","8eGhrgW/JBdqF+V7UhGCGK"],["node","_spriteFrame","_parent","checkMark","_N$target","_N$background","_N$placeholderLabel","_N$textLabel","_normalMaterial","_textureSetter","root","data","_grayMaterial"],[["cc.Node",["_name","_opacity","_active","_prefab","_contentSize","_parent","_components","_trs","_children","_color","_anchorPoint"],0,4,5,1,9,7,2,5,5],["cc.Sprite",["_sizeMode","_isTrimmedMode","_type","_enabled","node","_materials","_spriteFrame"],-1,1,3,6],["cc.Label",["_fontSize","_lineHeight","_styleFlags","_N$verticalAlign","_string","_N$overflow","_N$horizontalAlign","_enableWrapText","_isSystemFontUsed","node","_materials"],-6,1,3],["cc.Widget",["_alignFlags","alignMode","_originalWidth","_originalHeight","_top","_left","node"],-3,1],["cc.Node",["_name","_objFlags","_active","_parent","_components","_prefab","_contentSize","_anchorPoint","_trs","_color"],0,1,12,4,5,5,7,5],["cc.Layout",["_resize","_N$layoutType","_N$paddingTop","_N$paddingBottom","_N$spacingX","_N$spacingY","_N$paddingLeft","node","_layoutSize"],-4,1,5],["cc.Button",["zoomScale","node","_normalMaterial","_grayMaterial"],2,1,6,6],["cc.Toggle",["zoomScale","_N$isChecked","node","_N$normalColor","_N$target","checkMark","_normalMaterial"],1,1,5,1,1,6],["cc.Node",["_name","_active","_parent","_components","_prefab","_contentSize","_trs"],1,1,2,4,5,7],["cc.PrefabInfo",["fileId","root"],2,1],["a326a9m5/1JeIcXBdJXIiLl",["_dataID","_enabled","node"],1,1],["cc.LabelOutline",["_width","_enabled","node","_color"],1,1,5],"cc.SpriteFrame",["cc.Prefab",["_name"],2],["cc.Node",["_name","_children","_components","_prefab","_contentSize","_trs"],2,12,9,4,5,7],["c08ba1vtWhIcafT71zOjQu1",["node"],3,1],["cc.BlockInputEvents",["node"],3,1],["cc.ToggleContainer",["node"],3,1],["9316bR6sttHFor6RlXYt0Wm",["node"],3,1],["5dd73pYLsRJi6ZDnBguO11Y",["_costPos","node"],2,1],["cc.EditBox",["_N$inputMode","node","_N$textLabel","_N$placeholderLabel","_N$background"],2,1,1,1,1]],[[9,0,1,2],[0,0,5,8,6,3,4,7,2],[1,2,0,4,5,6,3],[0,0,5,6,3,9,4,10,7,2],[0,0,5,6,3,4,2],[2,4,0,1,2,3,5,9,10,7],[0,0,5,6,3,4,7,2],[1,2,0,1,4,5,6,4],[8,0,1,2,3,4,5,6,3],[2,4,0,1,2,6,3,9,10,7],[0,0,8,6,3,4,7,2],[3,1,0,5,2,3,6,6],[1,0,1,4,3],[7,0,1,2,3,4,5,3],[0,0,8,6,3,4,2],[0,0,5,6,3,9,4,7,2],[3,1,0,2,3,6,5],[3,0,4,6,3],[1,2,0,4,5,3],[6,0,1,2],[2,4,0,1,2,3,9,10,6],[0,0,5,8,6,3,4,10,7,2],[0,0,5,8,3,4,7,2],[4,0,1,3,4,5,6,3],[4,0,1,2,3,4,5,6,7,8,4],[4,0,1,3,4,5,9,6,7,8,3],[1,0,1,4,5,3],[5,0,1,2,3,5,7,8,6],[6,1,1],[20,0,1,2,3,4,2],[2,4,0,1,2,6,3,5,9,10,8],[2,0,1,7,2,3,5,9,10,7],[2,4,0,1,7,2,3,5,9,10,8],[10,0,2,2],[10,1,0,2,3],[11,0,2,3,2],[11,1,0,2,3,3],[13,0,2],[0,0,5,8,6,3,4,2],[0,0,1,5,6,3,9,4,3],[0,0,5,3,2],[0,0,5,6,3,9,4,2],[0,0,5,8,3,4,2],[0,0,2,5,6,3,4,7,3],[14,0,1,2,3,4,5,2],[8,0,2,3,4,5,6,2],[3,1,0,6,3],[15,0,1],[9,1,1],[1,3,0,4,5,6,3],[1,0,4,5,6,2],[1,0,1,4,5,6,3],[1,4,5,6,1],[16,0,1],[17,0,1],[5,0,1,6,2,3,4,5,7,8,8],[5,0,1,4,7,8,4],[6,0,1,2,3,2],[7,0,2,3,4,5,2],[7,0,1,2,3,4,5,6,3],[18,0,1],[19,0,1,2],[2,4,0,1,8,2,6,3,9,10,8]],[[[{"name":"role_btn1_2","rect":[0,0,30,22],"offset":[-0.5,0],"originalSize":[31,22],"capInsets":[0,0,0,0]}],[12],0,[0],[9],[5]],[[[37,"GuildInactiveMemberMgrUI"],[10,"GuildInactiveMemberMgrUI",[-4,-5],[[46,2,45,-2],[47,-3]],[48,-1],[5,750,1334],[375,667,0,0,0,0,1,1,1,1]],[38,"windowbg",1,[-8,-9,-10,-11,-12,-13,-14,-15],[[2,1,0,-6,[72],73],[53,-7]],[0,"f4Uw8BVsZHCqtiXzVNPk2j",1],[5,699,780]],[14,"node_hours",[-18,-19,-20,-21,-22,-23],[[54,-16],[55,1,3,20,10,10,170,20,-17,[5,600,120]]],[0,"45lMzNXe1NBqyQK7qPuK7u",1],[5,600,120]],[10,"btn_public",[-26,-27,-28,-29],[[2,1,0,-24,[16],17],[19,0.98,-25]],[0,"99dL2HAxtJ/oXSGKP5PQCP",1],[5,150,45],[215.625,0,0,0,0,0,1,1,1,0]],[1,"toggle1",3,[-33,-34,-35],[[58,0.98,-32,[4,4292269782],-31,-30]],[0,"65J5TaXglKnpjxc+9RpfD8",1],[5,40,40],[-260,30,0,0,0,0,1,1,1,0]],[1,"toggle2",3,[-39,-40,-41],[[59,0.98,false,-38,[4,4292269782],-37,-36,28]],[0,"c3LwMMAqtArYBD0KAgMnbW",1],[5,40,40],[-50,30,0,0,0,0,1,1,1,0]],[1,"toggle3",3,[-45,-46,-47],[[13,0.98,false,-44,[4,4292269782],-43,-42]],[0,"0agrLWhF1AjIaZRKMB/C3O",1],[5,40,40],[160,30,0,0,0,0,1,1,1,0]],[1,"toggle4",3,[-51,-52,-53],[[13,0.98,false,-50,[4,4292269782],-49,-48]],[0,"76dDUlQ7ZCiaUi/Tw3zWSv",1],[5,40,40],[-260,-30,0,0,0,0,1,1,1,0]],[1,"toggle5",3,[-57,-58,-59],[[13,0.98,false,-56,[4,4292269782],-55,-54]],[0,"7dNeEVEs1MFLq4CZ5Fe9LF",1],[5,40,40],[-50,-30,0,0,0,0,1,1,1,0]],[1,"toggle6",3,[-63,-64,-65],[[13,0.98,false,-62,[4,4292269782],-61,-60]],[0,"cfi6w4SwFHM6ky3ogII0rL",1],[5,40,40],[160,-30,0,0,0,0,1,1,1,0]],[1,"common_box1_img4 copy",2,[-68,-69,-70],[[2,1,0,-66,[68],69],[27,1,2,5,5,5,-67,[5,622,170]]],[0,"b9OPThRxNGeYesLLQtBpkr",1],[5,622,170],[0,54.934,0,0,0,0,1,1,1,1]],[10,"btn_class",[-73,-74,-75],[[60,-71],[28,-72]],[0,"84K/+62CVG04+wNp3ntJME",1],[5,222,55],[0,-1.0390000000000015,0,0,0,0,1,1,1,1]],[1,"btn_save",2,[-79],[[18,1,0,-76,[6]],[57,0.93,-77,7,8],[61,"outter",-78]],[0,"60owJYUTBO9LhDnOt3qnEN",1],[5,250,108],[0,-301.497,0,0,0,0,1,1,1,0]],[14,"editbox_power",[-84,-85,-86],[[29,2,-83,-82,-81,-80]],[0,"29TeFCwl1ER50BUlq/1wi4",1],[5,230,40]],[14,"editbox_playerlevel",[-91,-92,-93],[[29,2,-90,-89,-88,-87]],[0,"a1FU/tzEpJxpqnbqMgfant",1],[5,230,40]],[10,"btn_filter",[-96,-97],[[49,false,0,-94,[62],63],[19,0.93,-95]],[0,"ad71Q2EehERLR66wRmrz6R",1],[5,150,40],[0,-25,0,0,0,0,1,1,1,0]],[39,"btn_close",200,1,[[50,0,-98,[0],1],[16,2,45,100,100,-99],[28,-100]],[0,"31YMb2rBFDnpY8b0vw7M6P",1],[4,4278190080],[5,750,1334]],[15,"lbl_title",2,[[30,"不活跃管理",32,50,1,1,1,2,-101,[2]],[17,17,1.7639999999999816,-102],[33,900601974,-103]],[0,"36Euj5tv5P8avRVk6+w1jS",1],[4,4288862715],[5,400,67],[0,354.736,0,0,0,0,1,1,1,1]],[15,"-",2,[[9,"满足条件的成员会被清理出联盟",20,24,1,1,1,-104,[3]],[17,17,212.346,-105],[34,false,900601968,-106]],[0,"d0WxRsI3FDSJi9pRy3wCuV",1],[4,4286019451],[5,280,30.24],[0,162.534,0,0,0,0,1,1,1,1]],[15,"- copy",2,[[9,"自动清理不上线时间",20,24,1,1,1,-107,[4]],[17,17,439.66700000000003,-108],[34,false,900601968,-109]],[0,"d9TCKgRkpNwq8lcMP2o7ln",1],[4,4286019451],[5,180,30.24],[0,-64.78700000000003,0,0,0,0,1,1,1,1]],[1,"common_box1_img4",2,[-111,4],[[2,1,0,-110,[18],19]],[0,"412zWGw9ZF5qj5TjeVtkB1",1],[5,622,83],[0,239.262,0,0,0,0,1,1,1,1]],[44,"common_box1_img6",[[[40,"New Node",-113,[0,"1axWw7UKlGmofOTr0vHGTv",1]],12],4,1],[[2,1,0,-112,[66],67]],[0,"8bj/LI3rZAbpQczsxfloeP",1],[5,249,49],[59.335,0,0,0,0,0,1,1,1,1]],[21,"node_panel",12,[16],[[27,1,2,5,8,5,-114,[5,249,53]],[2,1,0,-115,[64],65]],[0,"f91Jw8KkJG46JcGaZfxjVD",1],[5,249,53],[0,0.5,1],[0,-21.019,0,0,0,0,1,1,1,1]],[41,"-",13,[[9,"确定",36,32,1,1,1,-116,[5]],[33,900600024,-117]],[0,"d6YL1sHAxEhpda5bXagSr+",1],[4,4278333345],[5,72,40.32]],[6,"New Label",4,[[9,"开",24,24,1,1,1,-118,[14]],[35,3,-119,[4,4278190080]]],[0,"b1LpGCbC5JeYgG6/gER0WN",1],[5,30,36.239999999999995],[-37.235,0,0,0,0,0,1,1,1,1]],[6,"New Label copy",4,[[9,"关",24,24,1,1,1,-120,[15]],[35,3,-121,[4,4278190080]]],[0,"dddMDlO3lDBpQhtTQiSiGr",1],[5,30,36.239999999999995],[36.349,0,0,0,0,0,1,1,1,1]],[1,"common_box1_img4 copy",2,[3],[[2,1,0,-122,[41],42]],[0,"a7V0rvvixJQ7y3yDUCwoFq",1],[5,622,133],[0,-157.193,0,0,0,0,1,1,1,1]],[22,"New Node",11,[-123,-124],[0,"e0+2UCuwhHRLCp8ir9zgfl",1],[5,400,50],[0,55,0,0,0,0,1,1,1,1]],[1,"common_box1_img6",28,[14],[[2,1,0,-125,[47],48]],[0,"bcNStOn2xPfaEFeRKMER7M",1],[5,249,49],[59.335,0,0,0,0,0,1,1,1,1]],[23,"BACKGROUND_SPRITE",512,14,[[-126,[16,0,45,160,40,-127]],1,4],[0,"cbTKDqAO5HzolsCNGfsTNO",1],[5,230,40]],[24,"TEXT_LABEL",512,false,14,[[-128,[11,0,45,2,158,40,-129]],1,4],[0,"7a22J4M5lOgqEY5pSYefsj",1],[5,228,40],[0,0,1],[-113,20,0,0,0,0,1,1,1,1]],[25,"PLACEHOLDER_LABEL",512,14,[[-130,[11,0,45,2,158,40,-131]],1,4],[0,"501AQAkDJJbp5eCAFHryP9",1],[4,4290493371],[5,228,40],[0,0,1],[-113,20,0,0,0,0,1,1,1,1]],[42,"New Node copy",11,[-132,-133],[0,"f1KypJ5NFNf6/6xa6Ugpi/",1],[5,400,50]],[1,"common_box1_img6",33,[15],[[2,1,0,-134,[53],54]],[0,"dcKv7S+YVG/41758ADPQ6f",1],[5,249,49],[59.335,0,0,0,0,0,1,1,1,1]],[23,"BACKGROUND_SPRITE",512,15,[[-135,[16,0,45,160,40,-136]],1,4],[0,"68eToE73BIWK3DXI40rfjd",1],[5,230,40]],[24,"TEXT_LABEL",512,false,15,[[-137,[11,0,45,2,158,40,-138]],1,4],[0,"62OoE1J6NDjZxjkGuYBWMI",1],[5,228,40],[0,0,1],[-113,20,0,0,0,0,1,1,1,1]],[25,"PLACEHOLDER_LABEL",512,15,[[-139,[11,0,45,2,158,40,-140]],1,4],[0,"d6MphRNk5HbYBp04jUdAUr",1],[4,4290493371],[5,228,40],[0,0,1],[-113,20,0,0,0,0,1,1,1,1]],[22,"New Node copy",11,[-141,22],[0,"dbZ5fcncdPy5i7hTMma+Om",1],[5,400,50],[0,-55,0,0,0,0,1,1,1,1]],[21,"New Node",12,[-143],[[56,1,1,80,-142,[5,40,40]]],[0,"d0BxIUjX1Ah6QCAQGo/7+d",1],[5,40,40],[0,0,0.5],[-112.376,0,0,0,0,0,1,1,1,1]],[6,"lbl_sort_name",39,[[62,"全部",20,25,false,1,1,1,-144,[58]],[36,false,2,-145,[4,4278190080]]],[0,"11f8BF76tGQbSnPQjzPDZG",1],[5,40,31.5],[20,1.273,0,0,0,0,1,1,1,1]],[4,"New Label",16,[[30,"全部",18,20,1,1,1,2,-146,[61]],[36,false,2,-147,[4,4278190080]]],[0,"fayITpUUFKv7ZhLmwZ6amC",1],[5,150,25]],[6,"btn_close",2,[[51,2,false,-148,[70],71],[19,0.95,-149]],[0,"7fkJYqgudMDJXCDDGgd0De",1],[5,92,88],[-263.489,-430.271,0,0,0,0,1,1,1,0]],[3,"New Label",21,[[5,"自动清理不活跃成员",24,28,1,1,3,-150,[9]]],[0,"23oER5AYxHUouN9ZbvERjs",1],[4,4284369740],[5,400,35.28],[0,0,0.5],[-292.244,0,0,0,0,0,1,1,1,1]],[6,"open",4,[[2,1,0,-151,[10],11]],[0,"cc6yk11SBMNY/r46YKs16i",1],[5,75,45],[-36.041,0,0,0,0,0,1,1,1,0]],[43,"close",false,4,[[2,1,0,-152,[12],13]],[0,"7dgXuvmuJEd5Gm2d5lc5xc",1],[5,75,45],[35.554,0,0,0,0,0,1,1,1,0]],[4,"Background",5,[[7,1,0,false,-153,[20],21]],[0,"6dINoiNTBLtJqtKLDctXLB",1],[5,39,39]],[45,"checkmark",5,[-154],[0,"bdml0CMo1INK/zFc+KbX1c",1],[5,67,57],[0,0,0,0,0,0,1,0.61,0.61,0.61]],[26,2,false,47,[22]],[3,"New Label",5,[[5,"3小时",24,24,1,1,2,-155,[23]]],[0,"14IpoxBk9DyLHz9WHpEhl3",1],[4,4284369740],[5,150,37.8],[0,0,0.5],[25.358,0,0,0,0,0,1,1,1,1]],[4,"Background",6,[[7,1,0,false,-156,[24],25]],[0,"aawaI/WSZMro0k5NkTV2vj",1],[5,39,39]],[8,"checkmark",false,6,[-157],[0,"6dN01LrslC4LQom3JVpnAz",1],[5,67,57],[0,0,0,0,0,0,1,0.61,0.61,0.61]],[26,2,false,51,[26]],[3,"New Label",6,[[5,"6小时",24,24,1,1,2,-158,[27]]],[0,"34yUaTsnNEdKxXJ4MVoGFi",1],[4,4284369740],[5,150,37.8],[0,0,0.5],[25.358,0,0,0,0,0,1,1,1,1]],[4,"Background",7,[[7,1,0,false,-159,[29],30]],[0,"2b4PSBzD9BW7jTyGPkdSSw",1],[5,39,39]],[8,"checkmark",false,7,[-160],[0,"31/BLvZ4lIaodejXdWrqeE",1],[5,67,57],[0,0,0,0,0,0,1,0.61,0.61,0.61]],[12,2,false,55],[3,"New Label",7,[[5,"12小时",24,24,1,1,2,-161,[31]]],[0,"ecEAyFTkJCH4UdinMekKNV",1],[4,4284369740],[5,150,37.8],[0,0,0.5],[25.358,0,0,0,0,0,1,1,1,1]],[4,"Background",8,[[7,1,0,false,-162,[32],33]],[0,"dcvfofFNBPaJSO/G9kbW5i",1],[5,39,39]],[8,"checkmark",false,8,[-163],[0,"2aqUBYR9JMt4AC9kHpR/5U",1],[5,67,57],[0,0,0,0,0,0,1,0.61,0.61,0.61]],[12,2,false,59],[3,"New Label",8,[[5,"24小时",24,24,1,1,2,-164,[34]]],[0,"afF+j7bM1Gy7QLuOPVvMQa",1],[4,4284369740],[5,150,37.8],[0,0,0.5],[25.358,0,0,0,0,0,1,1,1,1]],[4,"Background",9,[[7,1,0,false,-165,[35],36]],[0,"69X6PWfBlOsbwLr6PvhS4g",1],[5,39,39]],[8,"checkmark",false,9,[-166],[0,"63p7WooQVMN4hYHZ5dKI/n",1],[5,67,57],[0,0,0,0,0,0,1,0.61,0.61,0.61]],[12,2,false,63],[3,"New Label",9,[[5,"48小时",24,24,1,1,2,-167,[37]]],[0,"40I2kc791CcpD8wAW3tvKb",1],[4,4284369740],[5,150,37.8],[0,0,0.5],[25.358,0,0,0,0,0,1,1,1,1]],[4,"Background",10,[[7,1,0,false,-168,[38],39]],[0,"9boT3bG/dDJIukvWhBcTqP",1],[5,39,39]],[8,"checkmark",false,10,[-169],[0,"570icGj2xGt4WHU1sZ0pfy",1],[5,67,57],[0,0,0,0,0,0,1,0.61,0.61,0.61]],[12,2,false,67],[3,"New Label",10,[[5,"72小时",24,24,1,1,2,-170,[40]]],[0,"803vHfxCpJ36WuYaO6SOCH",1],[4,4284369740],[5,150,37.8],[0,0,0.5],[25.358,0,0,0,0,0,1,1,1,1]],[3,"New Label",28,[[20,"战力≤",24,28,1,1,-171,[43]]],[0,"c9qoP1EXRMzZHALa2SAYH1",1],[4,4284369740],[5,61.17,35.28],[0,1,0.5],[-81.097,0,0,0,0,0,1,1,1,1]],[18,1,0,30,[44]],[31,20,25,false,1,1,1,31,[45]],[32,"输入战力",20,25,false,1,1,1,32,[46]],[3,"New Label",33,[[20,"玩家等级≤",24,28,1,1,-172,[49]]],[0,"e0ZcgMt/BNsqUse2rmfJmp",1],[4,4284369740],[5,109.17,35.28],[0,1,0.5],[-81.097,0,0,0,0,0,1,1,1,1]],[18,1,0,35,[50]],[31,20,25,false,1,1,1,36,[51]],[32,"输入玩家等级",20,25,false,1,1,1,37,[52]],[3,"New Label",38,[[20,"阶段≤",24,28,1,1,-173,[55]]],[0,"4cA7BzDW1FIYw2Ay5EIK89",1],[4,4284369740],[5,61.17,35.28],[0,1,0.5],[-81.097,0,0,0,0,0,1,1,1,1]],[6,"role_btn1_2",12,[[52,-174,[56],57]],[0,"c41nfpzIVMHLw9EdrvtNdI",1],[5,30,22],[79.763,0,0,0,0,0,1,0.7,0.7,0.7]],[4,"yellow_small",16,[[2,1,0,-175,[59],60]],[0,"bbvRvgY3ZHUpoUZ/SLEtDf",1],[5,229,51]]],0,[0,10,1,0,0,1,0,0,1,0,-1,17,0,-2,2,0,0,2,0,0,2,0,-1,18,0,-2,19,0,-3,20,0,-4,13,0,-5,21,0,-6,27,0,-7,11,0,-8,42,0,0,3,0,0,3,0,-1,5,0,-2,6,0,-3,7,0,-4,8,0,-5,9,0,-6,10,0,0,4,0,0,4,0,-1,44,0,-2,45,0,-3,25,0,-4,26,0,3,48,0,4,5,0,0,5,0,-1,46,0,-2,47,0,-3,49,0,3,52,0,4,6,0,0,6,0,-1,50,0,-2,51,0,-3,53,0,3,56,0,4,7,0,0,7,0,-1,54,0,-2,55,0,-3,57,0,3,60,0,4,8,0,0,8,0,-1,58,0,-2,59,0,-3,61,0,3,64,0,4,9,0,0,9,0,-1,62,0,-2,63,0,-3,65,0,3,68,0,4,10,0,0,10,0,-1,66,0,-2,67,0,-3,69,0,0,11,0,0,11,0,-1,28,0,-2,33,0,-3,38,0,0,12,0,0,12,0,-1,79,0,-2,39,0,-3,23,0,0,13,0,0,13,0,0,13,0,-1,24,0,5,71,0,6,73,0,7,72,0,0,14,0,-1,30,0,-2,31,0,-3,32,0,5,75,0,6,77,0,7,76,0,0,15,0,-1,35,0,-2,36,0,-3,37,0,0,16,0,0,16,0,-1,80,0,-2,41,0,0,17,0,0,17,0,0,17,0,0,18,0,0,18,0,0,18,0,0,19,0,0,19,0,0,19,0,0,20,0,0,20,0,0,20,0,0,21,0,-1,43,0,0,22,0,2,22,0,0,23,0,0,23,0,0,24,0,0,24,0,0,25,0,0,25,0,0,26,0,0,26,0,0,27,0,-1,70,0,-2,29,0,0,29,0,-1,71,0,0,30,0,-1,72,0,0,31,0,-1,73,0,0,32,0,-1,74,0,-2,34,0,0,34,0,-1,75,0,0,35,0,-1,76,0,0,36,0,-1,77,0,0,37,0,-1,78,0,0,39,0,-1,40,0,0,40,0,0,40,0,0,41,0,0,41,0,0,42,0,0,42,0,0,43,0,0,44,0,0,45,0,0,46,0,-1,48,0,0,49,0,0,50,0,-1,52,0,0,53,0,0,54,0,-1,56,0,0,57,0,0,58,0,-1,60,0,0,61,0,0,62,0,-1,64,0,0,65,0,0,66,0,-1,68,0,0,69,0,0,70,0,0,74,0,0,78,0,0,79,0,0,80,0,11,1,3,2,27,4,2,21,12,2,22,14,2,29,15,2,34,16,2,23,22,2,38,175],[0,0,0,0,0,0,0,0,0,0,0,0,0,0,0,0,0,0,0,0,0,0,0,0,0,0,0,0,0,0,0,0,0,0,0,0,0,0,0,0,0,0,0,0,0,0,0,0,0,0,0,0,0,0,0,0,0,0,0,0,0,0,0,0,0,0,0,0,0,0,0,0,0,0,48,52,56,60,64,68],[-1,1,-1,-1,-1,-1,-1,8,12,-1,-1,1,-1,1,-1,-1,-1,1,-1,1,-1,1,-1,-1,-1,1,-1,-1,8,-1,1,-1,-1,1,-1,-1,1,-1,-1,1,-1,-1,1,-1,-1,-1,-1,-1,1,-1,-1,-1,-1,-1,1,-1,-1,1,-1,-1,1,-1,-1,1,-1,1,-1,1,-1,1,-1,1,-1,1,1,1,1,1,1,1],[0,6,0,0,0,0,0,0,7,0,0,8,0,9,0,0,0,3,0,4,0,1,0,0,0,1,0,0,0,0,1,0,0,1,0,0,1,0,0,1,0,0,4,0,0,0,0,0,3,0,0,0,0,0,3,0,0,10,0,0,4,0,0,11,0,3,0,3,0,4,0,12,0,13,2,2,2,2,2,2]]]]