[1,["34VkNs+J9DPrmS3xaH8MTM","7078EJKapAhIJxbHaedNMc","8fX7po2ORAMqIhHvcs3KFk"],["_textureSetter","theme1_water1_4","theme1_water1_4_70efc109-29aa-4084-8271-6c769e74d31c"],["cc.SpriteFrame",["cc.SpriteAtlas",["_name","_spriteFrames"],2,11]],[[1,0,1,2]],[[[[0,"theme1_water1_4.plist",[{},"theme1_water1_4",6,0,"theme1_water1_4_70efc109-29aa-4084-8271-6c769e74d31c",6,1]]],0,0,[0,0],[1,2],[1,2]],[[{"name":"theme1_water1_4","rect":[0,0,128,128],"offset":[0,0],"originalSize":[128,128],"capInsets":[0,0,0,0]}],[0],0,[0],[0],[0]],[[{"name":"theme1_water1_4_70efc109-29aa-4084-8271-6c769e74d31c","rect":[0,0,128,128],"offset":[0,0],"originalSize":[128,128],"capInsets":[0,0,0,0]}],[0],0,[0],[0],[0]]]]