[1,["6b5+cZXnVPzq5pgVVasNNf"],0,[["sp.SkeletonData",["_name","_atlasText","textureNames","_skeletonJson","textures"],-1,3]],[[0,0,1,2,3,4,5]],[[0,"demon_wizard_death","\r\ndemon_wizard_death.png\r\nsize: 427,427\r\nformat: RGBA8888\r\nfilter: Linear,Linear\r\nrepeat: none\r\nTou2\r\n  rotate: false\r\n  xy: 220, 206\r\n  size: 152, 91\r\n  orig: 152, 101\r\n  offset: 0, 10\r\n  index: -1\r\nYoudabi\r\n  rotate: false\r\n  xy: 344, 140\r\n  size: 76, 64\r\n  orig: 76, 64\r\n  offset: 0, 0\r\n  index: -1\r\nYoutui\r\n  rotate: false\r\n  xy: 280, 316\r\n  size: 22, 45\r\n  orig: 22, 46\r\n  offset: 0, 0\r\n  index: -1\r\nYouxiaobi\r\n  rotate: false\r\n  xy: 382, 21\r\n  size: 38, 34\r\n  orig: 38, 34\r\n  offset: 0, 0\r\n  index: -1\r\nZuodabi\r\n  rotate: false\r\n  xy: 376, 305\r\n  size: 39, 41\r\n  orig: 39, 41\r\n  offset: 0, 0\r\n  index: -1\r\nZuojiao\r\n  rotate: false\r\n  xy: 367, 57\r\n  size: 20, 14\r\n  orig: 20, 14\r\n  offset: 0, 0\r\n  index: -1\r\nZuotui\r\n  rotate: true\r\n  xy: 374, 211\r\n  size: 23, 45\r\n  orig: 23, 46\r\n  offset: 0, 0\r\n  index: -1\r\nZuoxiaobi\r\n  rotate: false\r\n  xy: 220, 300\r\n  size: 58, 64\r\n  orig: 58, 64\r\n  offset: 0, 0\r\n  index: -1\r\ndangbu\r\n  rotate: false\r\n  xy: 374, 236\r\n  size: 46, 61\r\n  orig: 46, 61\r\n  offset: 0, 0\r\n  index: -1\r\neffect/g2_0\r\n  rotate: true\r\n  xy: 2, 2\r\n  size: 200, 205\r\n  orig: 280, 280\r\n  offset: 45, 43\r\n  index: -1\r\neffect/g_0\r\n  rotate: false\r\n  xy: 2, 204\r\n  size: 216, 221\r\n  orig: 280, 280\r\n  offset: 36, 30\r\n  index: -1\r\nqunbaiYou\r\n  rotate: false\r\n  xy: 344, 363\r\n  size: 32, 62\r\n  orig: 32, 62\r\n  offset: 0, 0\r\n  index: -1\r\nqunbaihou\r\n  rotate: false\r\n  xy: 209, 5\r\n  size: 82, 49\r\n  orig: 82, 50\r\n  offset: 0, 0\r\n  index: -1\r\nqunbaoZuo\r\n  rotate: false\r\n  xy: 285, 363\r\n  size: 56, 62\r\n  orig: 56, 62\r\n  offset: 0, 0\r\n  index: -1\r\nshenti\r\n  rotate: false\r\n  xy: 220, 366\r\n  size: 63, 59\r\n  orig: 70, 59\r\n  offset: 7, 0\r\n  index: -1\r\nshuijiqiu\r\n  rotate: false\r\n  xy: 344, 73\r\n  size: 66, 65\r\n  orig: 66, 65\r\n  offset: 0, 0\r\n  index: -1\r\ntou1\r\n  rotate: true\r\n  xy: 209, 56\r\n  size: 146, 133\r\n  orig: 146, 133\r\n  offset: 0, 0\r\n  index: -1\r\ntoufa1\r\n  rotate: false\r\n  xy: 382, 348\r\n  size: 31, 77\r\n  orig: 31, 78\r\n  offset: 0, 0\r\n  index: -1\r\ntoufa2\r\n  rotate: true\r\n  xy: 293, 15\r\n  size: 39, 87\r\n  orig: 39, 87\r\n  offset: 0, 0\r\n  index: -1\r\nyaodai\r\n  rotate: true\r\n  xy: 344, 299\r\n  size: 62, 30\r\n  orig: 62, 30\r\n  offset: 0, 0\r\n  index: -1\r\nyoujiao\r\n  rotate: false\r\n  xy: 344, 57\r\n  size: 21, 14\r\n  orig: 21, 14\r\n  offset: 0, 0\r\n  index: -1\r\n",["demon_wizard_death.png"],{"skeleton":{"hash":"JOp3HGCwaRYGOLqDdhNfD5Tzj44","spine":"3.8.99","x":-121.7,"y":-4.21,"width":408.67,"height":384.58,"images":"./images/","audio":"D:/1罗羽工作/202505/新增怪/4-艾瑞达死亡巫师"},"bones":[{"name":"root"},{"name":"all","parent":"root"},{"name":"all2","parent":"all","x":-3.18,"y":70.25},{"name":"yaodai","parent":"all2","length":15.63,"rotation":90.91,"x":17.7,"y":2.53},{"name":"shenti","parent":"all2","length":26.78,"rotation":90,"x":-0.41,"y":0.05},{"name":"shenti2","parent":"shenti","length":26.78,"x":26.78},{"name":"tou1","parent":"shenti2","length":36.7,"rotation":0.39,"x":37.7,"y":-0.5},{"name":"toufa1","parent":"tou1","length":18.69,"rotation":179.98,"x":30.05,"y":48.45},{"name":"toufa2","parent":"tou1","length":22.91,"rotation":-166.16,"x":45.73,"y":-32.48},{"name":"toufa2b","parent":"toufa2","length":22.91,"rotation":-6.81,"x":22.91},{"name":"toufa2c","parent":"toufa2b","length":22.91,"rotation":-6.81,"x":22.91},{"name":"toufa2d","parent":"toufa2c","length":22.91,"rotation":-6.81,"x":22.91},{"name":"toufa1b","parent":"toufa1","length":18.69,"rotation":8.62,"x":18.69},{"name":"toufa1c","parent":"toufa1b","length":18.69,"rotation":8.62,"x":18.69},{"name":"toufa1d","parent":"toufa1c","length":18.69,"rotation":8.62,"x":18.69},{"name":"tou2","parent":"tou1","x":3.15,"y":84.92},{"name":"tou3","parent":"tou1","x":16.02,"y":-62.96},{"name":"tou4","parent":"tou1","x":-20.79,"y":-9.32},{"name":"Zuodabi","parent":"shenti2","length":34.51,"rotation":145.2,"x":25.21,"y":38.64},{"name":"Zuoxiaobi","parent":"Zuodabi","length":44.38,"rotation":5.22,"x":34.84,"y":0.23},{"name":"Youxiaobi","parent":"shenti2","length":31.26,"rotation":-101.43,"x":13.92,"y":-17.16},{"name":"Youdabi","parent":"Youxiaobi","length":53.39,"rotation":39.87,"x":31.07,"y":0.96},{"name":"Youdabi2","parent":"Youdabi","length":35.84,"rotation":2.79,"x":53.39},{"name":"Zuotui","parent":"all2","length":36.51,"rotation":-93.42,"x":-14.84,"y":-12.06},{"name":"target1","parent":"all","x":-20.21,"y":21.75,"color":"ff3f00ff"},{"name":"Zuotui2","parent":"target1","length":23.12,"rotation":-89.35},{"name":"Youtui","parent":"all2","length":39.18,"rotation":-91.19,"x":27.32,"y":-10.15},{"name":"target2","parent":"all","x":23.27,"y":20.97,"color":"ff3f00ff"},{"name":"Youtui2","parent":"target2","length":21.76,"rotation":-90.07,"y":-0.04},{"name":"qunbaoZuo","parent":"all2","length":19.08,"rotation":-116.02,"x":-20.55,"y":-1.79},{"name":"qunbaiYou","parent":"all2","length":17.58,"rotation":-73.07,"x":32.75,"y":-0.81},{"name":"dangbu","parent":"all2","length":17.38,"rotation":-84.64,"x":13.58,"y":3.41},{"name":"dangbu2","parent":"dangbu","length":17.38,"x":17.38},{"name":"dangbu3","parent":"dangbu2","length":17.38,"x":17.38},{"name":"dangbu4","parent":"dangbu3","length":17.38,"x":17.38},{"name":"qunbaoZuo2","parent":"qunbaoZuo","length":19.08,"x":19.08},{"name":"qunbaoZuo3","parent":"qunbaoZuo2","length":19.08,"x":19.08},{"name":"qunbaoZuo4","parent":"qunbaoZuo3","length":19.08,"x":19.08},{"name":"qunbaiYou2","parent":"qunbaiYou","length":17.58,"x":17.58},{"name":"qunbaiYou3","parent":"qunbaiYou2","length":17.58,"x":17.58},{"name":"qunbaiYou4","parent":"qunbaiYou3","length":17.58,"x":17.58},{"name":"shuijiqiu","parent":"root","x":117.21,"y":203.67},{"name":"effect/g_0","parent":"shuijiqiu","x":1.27,"y":0.69},{"name":"effect/g2_0","parent":"shuijiqiu","x":0.3,"y":-1.85},{"name":"effect/g_1","parent":"shuijiqiu","x":1.27,"y":0.69}],"slots":[{"name":"Youxiaobi","bone":"Youxiaobi","attachment":"Youxiaobi"},{"name":"Youdabi","bone":"Youdabi","attachment":"Youdabi"},{"name":"qunbaihou","bone":"all2","attachment":"qunbaihou"},{"name":"Youtui","bone":"Youtui","attachment":"Youtui"},{"name":"youjiao","bone":"Youtui2","attachment":"youjiao"},{"name":"Zuotui","bone":"Zuotui","attachment":"Zuotui"},{"name":"Zuojiao","bone":"Zuotui2","attachment":"Zuojiao"},{"name":"shenti","bone":"shenti","attachment":"shenti"},{"name":"qunbaiYou","bone":"qunbaiYou","attachment":"qunbaiYou"},{"name":"qunbaoZuo","bone":"qunbaoZuo","attachment":"qunbaoZuo"},{"name":"dangbu","bone":"dangbu","attachment":"dangbu"},{"name":"yaodai","bone":"yaodai","attachment":"yaodai"},{"name":"Zuodabi","bone":"Zuodabi","attachment":"Zuodabi"},{"name":"Zuoxiaobi","bone":"Zuoxiaobi","attachment":"Zuoxiaobi"},{"name":"Tou2","bone":"tou1","attachment":"Tou2"},{"name":"toufa2","bone":"toufa2","attachment":"toufa2"},{"name":"tou1","bone":"tou1","attachment":"tou1"},{"name":"toufa1","bone":"toufa1","attachment":"toufa1"},{"name":"shuijiqiu","bone":"shuijiqiu","attachment":"shuijiqiu"},{"name":"effect/g2_0","bone":"effect/g2_0","attachment":"effect/g2_0","blend":"additive"},{"name":"effect/g_0","bone":"effect/g_0","attachment":"effect/g_0"},{"name":"effect/g_1","bone":"effect/g_1","attachment":"effect/g_0"}],"ik":[{"name":"target1","target":"target1","compress":true,"stretch":true,"bones":["Zuotui"]},{"name":"target2","order":1,"target":"target2","compress":true,"stretch":true,"bones":["Youtui"]}],"skins":[{"name":"default","attachments":{"Tou2":{"Tou2":{"type":"mesh","hull":21,"width":190,"height":126,"uvs":[0.8714,0.00469,0.94277,0.184,0.99487,0.44131,0.9948,0.56256,0.9266,0.71939,0.85174,0.84129,0.72952,0.89832,0.5419,0.89648,0.39687,0.86642,0.34408,0.85733,0.12409,0.76693,0.00825,0.59256,0.00068,0.5205,0.0069,0.47998,0.22115,0.45945,0.23006,0.46323,0.38139,0.20737,0.53073,0.11225,0.72312,0.08452,0.77997,0.08711,0.82943,0.00882,0.13839,0.54838,0.21597,0.65686,0.32458,0.73981,0.47268,0.81213,0.62643,0.82063,0.71106,0.81425,0.84929,0.76533,0.91276,0.59305,0.94521,0.4399,0.90148,0.27613,0.85634,0.13362,0.93251,0.38248,0.85634,0.26549,0.78582,0.21019,0.81967,0.38035,0.79287,0.50159,0.87327,0.44203,0.81826,0.60581,0.7703,0.68238,0.65041,0.66536,0.53474,0.65048,0.47409,0.68238,0.40357,0.66962,0.25828,0.56965,0.20186,0.52498,0.32599,0.50159,0.33868,0.66536,0.57001,0.76108,0.69413,0.7313,0.74773,0.61006],"triangles":[36,34,35,35,34,33,1,30,31,34,31,33,34,19,31,19,20,31,11,12,21,21,45,22,45,44,22,44,15,46,48,24,42,24,8,43,8,9,23,43,8,23,43,23,47,42,41,48,24,43,42,48,41,40,41,42,46,46,42,43,43,47,46,46,16,41,16,17,41,17,36,40,41,17,40,36,17,34,34,18,19,18,34,17,46,15,16,15,45,14,44,46,47,44,45,15,45,21,14,14,21,13,12,13,21,31,20,0,31,0,1,30,33,31,32,30,1,5,27,4,39,38,27,4,38,28,4,27,38,4,28,3,39,50,38,50,40,36,50,36,38,28,38,37,38,36,37,28,29,3,28,37,29,3,29,2,36,35,37,37,35,30,37,32,29,37,30,32,30,35,33,29,32,2,1,2,32,7,25,6,25,26,6,6,26,5,8,24,7,7,24,48,7,48,25,26,27,5,25,49,26,25,40,49,25,48,40,26,39,27,26,49,39,49,50,39,49,40,50,9,10,23,10,22,23,10,21,22,10,11,21,23,22,47,22,44,47],"vertices":[1,6,76.3,-56.47,1,1,6,53.61,-69.88,1,2,16,5.11,-16.6,0.99671,6,21.13,-79.56,0.00329,2,17,26.64,-70.13,0.02989,16,-10.17,-16.48,0.97011,3,17,6.96,-57.03,0.27039,16,-29.84,-3.39,0.7296,6,-13.82,-66.35,0.00001,2,17,-8.3,-42.71,0.55779,16,-45.11,10.94,0.44221,2,17,-15.33,-19.44,0.8515,16,-52.14,34.21,0.1485,3,15,-38.8,-78.03,0.05317,17,-14.85,16.21,0.76566,6,-35.64,6.89,0.18117,3,15,-34.82,-50.5,0.30451,17,-10.88,43.74,0.25268,6,-31.67,34.42,0.44281,3,15,-33.61,-40.48,0.43111,17,-9.67,53.76,0.1578,6,-30.46,44.44,0.41109,3,15,-21.94,1.24,0.95775,17,2,95.48,0.00693,6,-18.78,86.16,0.03531,2,15,0.18,23.1,0.36841,6,3.34,108.02,0.63159,1,6,12.42,109.4,1,1,6,17.52,108.18,1,1,6,19.83,67.46,1,1,6,19.34,65.77,1,1,6,51.39,36.8,1,1,6,63.18,8.34,1,1,6,66.43,-28.23,1,1,6,66.03,-39.03,1,1,6,75.83,-48.5,1,3,15,5.58,-1.66,0.3381,17,29.52,92.58,0.00004,6,8.73,83.26,0.66186,3,15,-8.19,-16.31,0.79416,17,15.76,77.93,0.01614,6,-5.03,68.61,0.1897,3,15,-18.78,-36.88,0.50726,17,5.16,57.36,0.09352,6,-15.62,48.05,0.39922,3,15,-28.08,-64.95,0.15243,17,-4.14,29.29,0.4193,6,-24.93,19.97,0.42827,3,15,-29.35,-94.16,0.00205,17,-5.41,0.08,0.99325,16,-42.22,53.73,0.0047,3,17,-4.71,-16,0.85395,16,-41.52,37.64,0.13409,6,-25.5,-25.32,0.01197,3,17,1.27,-42.31,0.4805,16,-35.53,11.34,0.51209,6,-19.51,-51.63,0.00741,3,17,22.9,-54.51,0.11217,16,-13.91,-0.87,0.88247,6,2.11,-63.83,0.00536,2,16,5.35,-7.16,0.99122,6,21.37,-70.13,0.00878,2,16,26.04,1,0.52286,6,42.06,-61.96,0.47714,1,6,60.07,-53.5,1,2,16,12.6,-4.8,0.952,6,28.62,-67.76,0.048,2,16,27.44,9.57,0.3781,6,43.46,-53.39,0.6219,3,17,71.3,-30.72,0,16,34.49,22.92,0.01715,6,50.51,-40.04,0.98285,3,17,49.82,-37.01,0.01261,16,13.01,16.64,0.60493,6,29.03,-46.33,0.38245,3,17,34.58,-31.81,0.1167,16,-2.23,21.83,0.60371,6,13.79,-41.13,0.27959,3,17,41.98,-47.14,0.01056,16,5.17,6.51,0.89081,6,21.19,-56.46,0.09863,3,17,21.41,-36.55,0.26373,16,-15.39,17.1,0.62072,6,0.63,-45.87,0.11555,3,17,11.83,-27.37,0.49506,16,-24.98,26.27,0.38323,6,-8.96,-36.69,0.12171,3,17,14.13,-4.61,0.48678,16,-22.68,49.04,0.07043,6,-6.66,-13.92,0.44279,3,15,-7.79,-76.88,0.04039,17,16.15,17.36,0.11909,6,-4.64,8.04,0.84052,3,15,-11.73,-65.33,0.13992,17,12.21,28.91,0.1735,6,-8.58,19.59,0.68658,3,15,-10.04,-51.94,0.29294,17,13.91,42.3,0.10467,6,-6.88,32.98,0.60238,3,15,2.75,-24.43,0.21828,17,26.69,69.81,0.00385,6,5.9,60.5,0.77786,1,6,11.6,71.18,1,1,6,14.39,47.58,1,3,15,-9.42,-39.62,0.46512,17,14.53,54.62,0.06557,6,-6.26,45.3,0.46931,3,15,-21.77,-83.49,0.02444,17,2.17,10.75,0.67688,6,-18.62,1.43,0.29868,3,17,5.76,-12.86,0.7481,16,-31.05,40.79,0.13191,6,-15.03,-22.18,0.11998,3,17,20.97,-23.14,0.34785,16,-15.84,30.5,0.37133,6,0.18,-32.46,0.28082],"edges":[0,40,0,2,2,4,4,6,6,8,12,14,16,18,18,20,20,22,22,24,24,26,26,28,28,30,30,32,32,34,34,36,36,38,38,40,8,10,12,10,16,14]}},"Youdabi":{"Youdabi":{"type":"mesh","hull":17,"width":95,"height":80,"uvs":[0.64601,0,0.88588,0.10094,0.98968,0.22458,0.99038,0.27377,0.86285,0.49447,0.79347,0.56328,0.76141,0.78764,0.75314,0.84547,0.65705,0.8872,0.48699,0.96106,0.0327,0.99307,0.00937,0.9084,0.00904,0.51221,0.22947,0.2782,0.43048,0.14067,0.49022,0.0998,0.63608,0,0.52733,0.40796,0.59418,0.61434,0.38028,0.34129,0.40434,0.57306,0.49792,0.76991],"triangles":[9,10,21,20,11,19,13,19,12,10,11,21,9,21,8,20,21,11,19,11,12,7,8,6,18,6,8,8,21,18,21,20,18,20,17,18,18,17,5,20,19,17,19,14,17,19,13,14,6,18,5,4,5,17,0,15,16,1,4,17,3,1,2,3,4,1,1,17,0,14,15,17,0,17,15],"vertices":[2,22,23.44,24.18,0.99817,21,75.63,25.29,0.00183,1,22,38.74,5.46,1,1,22,42.04,-8.11,1,1,22,40.06,-11.51,1,2,22,20.55,-20.33,0.97905,21,74.9,-19.3,0.02095,2,22,12.06,-21.62,0.84047,21,66.48,-21.01,0.15953,2,22,0.15,-35.39,0.40227,21,55.26,-35.34,0.59773,2,22,-2.92,-38.93,0.3615,21,52.36,-39.03,0.6385,2,22,-12.46,-37.06,0.25565,21,42.74,-37.62,0.74435,2,22,-29.34,-33.73,0.06549,21,25.73,-35.12,0.93451,1,21,-13.44,-16.82,1,1,21,-12.17,-9.8,1,1,21,2.9,18.08,1,2,22,-21.93,25.67,0.07574,21,30.23,24.57,0.92426,2,22,0.1,25.17,0.63462,21,52.26,25.15,0.36538,2,22,6.65,25.02,0.83042,21,58.81,25.32,0.16958,2,22,22.64,24.67,0.99759,21,74.8,25.74,0.00241,2,22,-3.12,2.12,0.04752,21,50.17,1.96,0.95248,2,22,-6.25,-15.29,0.31972,21,47.89,-15.58,0.68028,2,22,-12.3,13.92,0.16641,21,40.43,13.31,0.83359,2,22,-19.96,-3.12,0.00011,21,33.6,-4.09,0.99989,2,22,-20.52,-21.19,0.09139,21,33.92,-22.17,0.90861],"edges":[0,32,0,2,2,4,4,6,6,8,8,10,18,20,20,22,22,24,24,26,30,32,30,34,34,36,10,12,12,14,36,12,26,28,28,30,28,38,38,40,40,42,14,16,16,18,42,16]}},"Youtui":{"Youtui":{"type":"mesh","hull":12,"width":28,"height":57,"uvs":[0.9192,0.01695,0.9956,0.3022,0.93159,0.51181,0.90095,0.61212,0.88437,0.66642,0.78777,0.98272,0.0332,0.98497,0.03402,0.64737,0.03419,0.58025,0.03441,0.48817,0.03526,0.1379,0.28284,0.01702,0.24551,0.48816,0.58301,0.49211,0.25087,0.58158,0.54016,0.58553,0.25623,0.66448,0.56694,0.66448],"triangles":[10,13,12,11,0,1,11,13,10,9,10,12,11,1,13,2,13,1,15,14,12,8,9,12,14,8,12,13,15,12,3,13,2,15,13,3,7,8,14,16,14,15,7,14,16,17,15,3,16,15,17,4,17,3,5,17,4,6,7,16,5,6,16,5,16,17],"vertices":[1,26,6.75,13.04,1,2,28,-15.89,15.85,0.00205,26,22.96,15.52,0.99795,2,28,-3.94,14.06,0.22873,26,34.94,13.98,0.77127,2,28,1.77,13.2,0.58575,26,40.67,13.24,0.41425,2,28,4.87,12.74,0.77492,26,43.78,12.84,0.22508,1,28,22.9,10.04,1,1,28,23.03,-11.09,1,2,28,3.78,-11.07,0.84574,26,43.19,-10.99,0.15426,2,28,-0.04,-11.06,0.60591,26,39.36,-11.06,0.39409,2,28,-5.29,-11.06,0.24307,26,34.12,-11.17,0.75693,1,26,14.16,-11.56,1,1,26,7.12,-4.77,1,2,28,-5.29,-5.15,0.15273,26,33.99,-5.26,0.84727,2,28,-5.07,4.3,0.04417,26,34.02,4.2,0.95583,2,28,0.03,-5,0.61441,26,39.31,-5,0.38559,2,28,0.26,3.1,0.56577,26,39.37,3.11,0.43423,2,28,4.76,-4.85,0.9498,26,44.03,-4.75,0.0502,2,28,4.76,3.85,0.95999,26,43.85,3.95,0.04001],"edges":[0,22,0,2,10,12,20,22,18,20,18,24,24,26,2,4,26,4,16,18,16,28,28,30,4,6,30,6,12,14,14,16,14,32,32,34,6,8,8,10,34,8]}},"Youxiaobi":{"Youxiaobi":{"x":13.56,"y":-2.83,"rotation":11.43,"width":48,"height":43}},"Zuodabi":{"Zuodabi":{"x":20.9,"y":-2.49,"rotation":124.8,"width":49,"height":51}},"Zuojiao":{"Zuojiao":{"x":15.71,"y":0.81,"rotation":89.33,"width":25,"height":18}},"Zuotui":{"Zuotui":{"type":"mesh","hull":13,"width":29,"height":57,"uvs":[0.7833,0.01752,1,0.20473,1,0.38921,0.95435,0.5025,0.92518,0.5749,0.90206,0.63225,0.76008,0.9846,0.03339,0.98508,0.03365,0.61222,0.03369,0.54447,0.03374,0.48369,0.03398,0.122,0.29511,0.01626,0.3738,0.50106,0.68104,0.50627,0.36356,0.56706,0.62983,0.57574,0.29187,0.62784,0.56497,0.62958],"triangles":[1,12,0,1,13,12,1,14,13,11,12,13,10,11,13,1,2,14,3,14,2,9,10,13,15,9,13,4,14,3,16,13,14,16,14,4,15,13,16,5,16,4,17,8,9,15,17,9,18,15,16,17,15,18,18,16,5,6,18,5,7,8,17,6,7,17,6,17,18],"vertices":[1,23,4.72,7.33,1,1,23,14.99,14.24,1,2,25,-9.93,15.62,0.0087,23,25.49,14.87,0.9913,2,25,-3.49,14.22,0.12404,23,32.02,13.93,0.87596,2,25,0.63,13.32,0.32371,23,36.19,13.33,0.67629,2,25,3.89,12.61,0.53935,23,39.49,12.86,0.46065,1,25,23.92,8.26,1,1,25,23.7,-12.81,1,2,25,2.45,-12.56,0.67767,23,39.85,-12.35,0.32233,2,25,-1.41,-12.51,0.40832,23,36,-12.58,0.59168,2,25,-4.88,-12.47,0.19652,23,32.54,-12.78,0.80348,1,23,11.96,-14,1,1,23,5.49,-6.8,1,2,25,-3.77,-2.62,0.03161,23,32.94,-2.88,0.96839,2,25,-3.37,6.29,0.10943,23,32.7,6.03,0.89057,2,25,-0.01,-2.96,0.5234,23,36.71,-2.95,0.4766,2,25,0.57,4.76,0.41098,23,36.74,4.79,0.58902,2,25,3.43,-5.08,0.8614,23,40.29,-4.82,0.1386,2,25,3.62,2.84,0.86968,23,39.92,3.09,0.13032],"edges":[0,24,0,2,2,4,12,14,22,24,20,22,20,26,26,28,4,6,28,6,18,20,18,30,30,32,6,8,32,8,14,16,16,18,16,34,34,36,8,10,10,12,36,10]}},"Zuoxiaobi":{"Zuoxiaobi":{"type":"mesh","hull":19,"width":73,"height":80,"uvs":[0.40711,0.04319,0.48807,0,0.49263,0,0.7581,0.07974,0.92773,0.23267,0.99716,0.29527,0.95594,0.4257,0.90574,0.58455,0.87191,0.6916,0.83463,0.80957,0.49336,0.98795,0.25124,0.98794,0.05548,0.95968,0.05323,0.65898,0,0.51287,0,0.43702,0.02639,0.3644,0.13837,0.24942,0.26576,0.1186],"triangles":[18,0,3,3,0,2,0,1,2,7,18,3,8,9,10,11,13,10,13,8,10,17,8,13,8,17,18,11,12,13,7,8,18,13,14,17,17,14,16,6,3,4,6,7,3,14,15,16,6,4,5],"vertices":[2,19,1.28,-24.63,0.14165,18,38.36,-24.18,0.85835,2,19,-4.64,-21.2,0.03688,18,32.15,-21.3,0.96312,2,19,-4.81,-20.91,0.03593,18,31.96,-21.03,0.96407,2,19,-8.83,-0.9,0.00037,18,26.14,-1.47,0.99963,2,19,-4.3,15.9,0.96776,18,29.12,15.68,0.03224,2,19,-2.45,22.78,0.99939,18,30.34,22.7,0.00061,1,19,8.11,25.32,1,1,19,20.97,28.41,1,1,19,29.64,30.49,1,1,19,39.19,32.78,1,1,19,63.9,18.16,1,1,19,72.63,2.79,1,1,19,77.71,-10.76,1,2,19,56.88,-22.77,0.97542,18,93.56,-17.28,0.02458,2,19,48.63,-31.92,0.92083,18,86.17,-27.14,0.07917,2,19,43.35,-34.92,0.89113,18,81.19,-30.6,0.10887,2,19,37.35,-36.11,0.85466,18,75.32,-32.34,0.14534,2,19,25.31,-33.55,0.71141,18,63.1,-30.88,0.28859,2,19,11.62,-30.63,0.42096,18,49.2,-29.21,0.57904],"edges":[2,4,4,6,18,20,20,22,22,24,24,26,26,28,28,30,30,32,10,12,12,14,14,16,16,18,32,34,34,36,6,8,8,10,2,0,0,36]}},"dangbu":{"dangbu":{"type":"mesh","hull":30,"width":57,"height":76,"uvs":[0.97092,0.0129,0.94013,0.01778,0.94461,0.07811,0.9509,0.16276,0.95825,0.26174,0.96512,0.35419,0.97234,0.45144,0.9789,0.53974,0.98538,0.62699,0.99207,0.71705,0.91224,0.77689,0.83927,0.83159,0.77905,0.87673,0.69682,0.93838,0.61461,1,0.60723,1,0.47724,0.94862,0.41026,0.92214,0.2952,0.87666,0.18146,0.8317,0.07981,0.79152,0.06611,0.69933,0.0529,0.6105,0.04072,0.52853,0.02836,0.44542,0.01434,0.35107,0,0.25463,0,0.1488,0,0.06003,0.10638,0.013],"triangles":[1,29,0,27,28,29,26,27,29,2,29,1,3,29,2,4,29,3,4,26,29,5,25,26,6,24,25,6,23,24,26,4,5,6,25,5,7,22,23,7,21,22,7,23,6,8,11,7,10,8,9,7,11,21,21,19,20,11,8,10,21,18,19,11,18,21,11,17,18,12,17,11,12,16,17,13,16,12,15,16,13,14,15,13],"vertices":[2,32,-18.22,27.45,0.35143,31,-0.84,27.45,0.64857,3,33,-35.4,25.67,0.00016,32,-18.02,25.67,0.35152,31,-0.64,25.67,0.64832,3,33,-30.81,25.49,0.0045,32,-13.43,25.49,0.38577,31,3.95,25.49,0.60974,3,33,-24.37,25.25,0.0263,32,-6.99,25.25,0.49795,31,10.39,25.25,0.47575,3,33,-16.84,24.96,0.09481,32,0.54,24.96,0.64075,31,17.92,24.96,0.26445,4,34,-27.19,24.69,0.00248,33,-9.81,24.69,0.22499,32,7.57,24.69,0.6686,31,24.95,24.69,0.10392,4,34,-19.8,24.41,0.02426,33,-2.41,24.41,0.4253,32,14.97,24.41,0.52968,31,32.35,24.41,0.02076,4,34,-13.08,24.16,0.08569,33,4.3,24.16,0.58984,32,21.68,24.16,0.32333,31,39.07,24.16,0.00114,3,34,-6.44,23.91,0.2034,33,10.94,23.91,0.64457,32,28.32,23.91,0.15203,3,34,0.41,23.65,0.33689,33,17.79,23.65,0.59683,32,35.17,23.65,0.06627,3,34,4.51,18.69,0.49542,33,21.89,18.69,0.47851,32,39.27,18.69,0.02607,3,34,8.26,14.16,0.73218,33,25.64,14.16,0.26408,32,43.02,14.16,0.00374,3,34,11.35,10.42,0.9074,33,28.74,10.42,0.09259,32,46.12,10.42,0.00001,2,34,15.58,5.32,0.99713,33,32.96,5.32,0.00286,1,34,19.8,0.21,1,1,34,19.77,-0.21,1,2,34,15.18,-7.22,0.98568,33,32.57,-7.22,0.01432,3,34,12.82,-10.83,0.91998,33,30.21,-10.83,0.07808,32,47.59,-10.83,0.00194,3,34,8.77,-17.04,0.67906,33,26.15,-17.04,0.29734,32,43.53,-17.04,0.02359,4,34,4.76,-23.17,0.4518,33,22.14,-23.17,0.47471,32,39.53,-23.17,0.07335,31,56.91,-23.17,0.00014,4,34,1.18,-28.65,0.34624,33,18.56,-28.65,0.53531,32,35.94,-28.65,0.11591,31,53.33,-28.65,0.00253,4,34,-5.87,-28.78,0.24438,33,11.51,-28.78,0.55396,32,28.9,-28.78,0.18545,31,46.28,-28.78,0.01621,4,34,-12.66,-28.9,0.13125,33,4.72,-28.9,0.50588,32,22.1,-28.9,0.30475,31,39.49,-28.9,0.05812,4,34,-18.93,-29.01,0.05948,33,-1.55,-29.01,0.39103,32,15.84,-29.01,0.41265,31,33.22,-29.01,0.13684,4,34,-25.28,-29.12,0.02012,33,-7.9,-29.12,0.25187,32,9.48,-29.12,0.4619,31,26.86,-29.12,0.26611,4,34,-32.5,-29.24,0.00316,33,-15.11,-29.24,0.12353,32,2.27,-29.24,0.40798,31,19.65,-29.24,0.46533,4,34,-39.87,-29.37,0.00004,33,-22.49,-29.37,0.04778,32,-5.11,-29.37,0.27998,31,12.28,-29.37,0.67221,3,33,-30.5,-28.62,0.01064,32,-13.11,-28.62,0.14525,31,4.27,-28.62,0.84411,3,33,-37.21,-27.99,0.00154,32,-19.83,-27.99,0.08728,31,-2.45,-27.99,0.91119,2,32,-22.82,-21.62,0.0583,31,-5.44,-21.62,0.9417],"edges":[0,58,0,2,28,30,56,58,40,42,42,44,44,46,46,48,48,50,50,52,52,54,54,56,2,4,4,6,6,8,8,10,10,12,12,14,14,16,16,18,18,20,30,32,36,38,38,40,20,22,22,24,24,26,26,28,32,34,34,36]}},"effect/g2_0":{"effect/g2_0":{"x":-7.93,"y":-4.4,"width":350,"height":350}},"effect/g_0":{"effect/g_0":{"x":-6.51,"y":1.01,"width":350,"height":350}},"effect/g_1":{"effect/g_0":{"x":-6.51,"y":1.01,"width":350,"height":350}},"qunbaiYou":{"qunbaiYou":{"type":"mesh","hull":22,"width":40,"height":77,"uvs":[0.25216,0.00614,0.37281,0.12422,0.45308,0.20278,0.58731,0.33415,0.67769,0.45672,0.76097,0.56966,0.84921,0.68935,0.92158,0.78749,1,0.89385,1,0.89993,0.89755,0.94913,0.67833,0.98728,0.32966,0.98728,0.29494,0.90803,0.24157,0.78622,0.2089,0.6979,0.17144,0.59665,0.12759,0.4781,0.09074,0.37848,0.0624,0.30187,0.02388,0.19773,0.0247,0.02009],"triangles":[18,2,3,18,19,2,2,19,20,2,20,1,1,20,21,21,0,1,15,5,6,15,16,5,16,4,5,16,17,4,17,3,4,17,18,3,12,13,11,10,11,7,8,9,10,7,11,13,7,14,6,7,13,14,10,7,8,14,15,6],"vertices":[1,30,-2.84,4.86,1,1,30,7.26,6.83,1,2,39,-21.18,8.14,0.01634,30,13.98,8.14,0.98366,2,39,-9.94,10.33,0.4695,30,25.22,10.33,0.5305,2,39,0.14,11.04,0.92533,30,35.3,11.04,0.07467,3,40,-8.15,11.69,0.05652,39,9.43,11.69,0.94342,30,44.59,11.69,0.00006,2,40,1.69,12.39,0.62154,39,19.28,12.39,0.37846,2,40,9.77,12.96,0.96325,39,27.35,12.96,0.03675,2,40,18.52,13.57,1,39,36.1,13.57,0,2,40,18.96,13.44,1,39,36.54,13.44,0,1,40,21.39,8.41,1,1,40,21.65,-0.83,1,1,40,17.59,-14.17,1,2,40,11.35,-13.73,0.98382,39,28.93,-13.73,0.01618,2,40,1.75,-13.04,0.67228,39,19.33,-13.04,0.32772,2,40,-5.13,-12.31,0.22268,39,12.45,-12.31,0.77732,3,40,-13.03,-11.47,0.01127,39,4.55,-11.47,0.97841,30,39.71,-11.47,0.01032,2,39,-4.69,-10.49,0.76256,30,30.47,-10.49,0.23744,2,39,-12.46,-9.67,0.31347,30,22.7,-9.67,0.68653,2,39,-18.43,-9.03,0.06048,30,16.73,-9.03,0.93952,1,30,8.61,-8.17,1,1,30,-4.47,-4.16,1],"edges":[0,42,16,18,18,20,20,22,22,24,40,42,0,2,2,4,4,6,6,8,8,10,10,12,12,14,14,16,24,26,26,28,28,30,30,32,32,34,34,36,36,38,38,40]}},"qunbaihou":{"qunbaihou":{"type":"mesh","hull":23,"width":103,"height":62,"uvs":[0.24274,0.17717,0.35883,0.01468,0.74711,0.01457,0.84837,0.18275,0.90523,0.27719,0.95126,0.4758,0.99063,0.64567,0.99115,0.82263,0.99154,0.95107,0.91055,0.96375,0.86498,0.97089,0.78053,0.98411,0.63658,0.98409,0.25568,0.98405,0.16502,0.9695,0.09116,0.95765,0.04148,0.94968,0,0.93212,0.00969,0.85252,0.04323,0.7306,0.08867,0.56541,0.13318,0.40363,0.1659,0.28472],"triangles":[12,0,1,12,1,2,0,13,21,21,22,0,12,13,0,13,14,20,21,13,20,20,14,19,15,18,19,15,19,14,17,18,16,15,16,18,12,2,3,4,5,3,10,11,5,5,11,12,10,7,9,3,5,12,7,10,6,6,10,5,9,7,8],"vertices":[2,38,-18.8,-63.67,0.00114,35,-0.84,0.04,0.99886,2,38,-24.95,-49.3,0.15661,35,-15.14,6.36,0.84339,2,38,-13.31,-11.04,0.76895,35,-32.69,42.3,0.23105,3,38,-0.3,-4.09,0.91641,36,-46.98,56.25,0.00012,35,-27.9,56.25,0.08347,2,38,7.01,-0.2,0.99314,35,-25.21,64.08,0.00686,1,39,2.59,0.75,1,2,40,-3.74,1.57,0.00468,39,13.84,1.57,0.99532,6,40,6.77,-1.58,0.5594,39,24.35,-1.58,0.43796,38,41.93,-1.58,0.00004,37,-36.85,86.86,0.0002,36,-17.78,86.86,0.00162,35,1.3,86.86,0.00077,6,40,14.4,-3.86,0.52694,39,31.98,-3.86,0.46724,38,49.56,-3.86,0.00011,37,-29.71,90.39,0.00045,36,-10.64,90.39,0.00335,35,8.44,90.39,0.00191,6,40,12.73,-12.07,0.44258,39,30.31,-12.07,0.50067,38,47.89,-12.07,0.02834,37,-25.35,83.24,0.00218,36,-6.27,83.24,0.01123,35,12.81,83.24,0.015,6,40,11.78,-16.69,0.35782,39,29.36,-16.69,0.52148,38,46.94,-16.69,0.06305,37,-22.89,79.22,0.00453,36,-3.81,79.22,0.02119,35,15.26,79.22,0.03193,6,40,10.03,-25.25,0.22161,39,27.61,-25.25,0.50598,38,45.19,-25.25,0.13572,37,-18.34,71.76,0.01175,36,0.74,71.76,0.0482,35,19.82,71.76,0.07674,6,40,5.72,-39.43,0.09042,39,23.3,-39.43,0.36714,38,40.88,-39.43,0.20855,37,-11.84,58.44,0.03746,36,7.24,58.44,0.12183,35,26.32,58.44,0.17459,6,40,-5.71,-76.96,0.00457,39,11.87,-76.96,0.05082,38,29.45,-76.96,0.04683,37,5.37,23.18,0.4166,36,24.45,23.18,0.37179,35,43.53,23.18,0.10939,6,40,-9.29,-85.63,0.00137,39,8.29,-85.63,0.0185,38,25.87,-85.63,0.01579,37,8.66,14.39,0.70215,36,27.74,14.39,0.22888,35,46.81,14.39,0.03331,6,40,-12.21,-92.7,0.00025,39,5.37,-92.7,0.00404,38,22.95,-92.7,0.00307,37,11.34,7.23,0.9508,36,30.41,7.23,0.03797,35,49.49,7.23,0.00387,6,40,-14.17,-97.45,0.00002,39,3.41,-97.45,0.00039,38,20.99,-97.45,0.00027,37,13.14,2.42,0.99889,36,32.21,2.42,0.00034,35,51.29,2.42,0.00009,1,37,14.03,-1.9,1,1,37,9.16,-3.17,1,2,37,0.85,-3.38,0.60855,36,19.93,-3.38,0.39145,1,36,8.67,-3.67,1,2,36,-2.35,-3.95,0.05346,35,16.72,-3.95,0.94654,1,35,8.62,-4.15,1],"edges":[2,4,32,34,34,36,12,14,14,16,8,10,10,12,4,6,6,8,42,44,40,42,36,38,38,40,2,0,0,44,16,18,22,24,24,26,30,32,26,28,28,30,18,20,20,22]}},"qunbaoZuo":{"qunbaoZuo":{"type":"mesh","hull":28,"width":70,"height":78,"uvs":[0.87671,0.01162,1,0.07067,1,0.08886,0.97389,0.16194,0.94294,0.24856,0.9151,0.32646,0.8852,0.41013,0.8534,0.49913,0.81627,0.60303,0.77769,0.711,0.74138,0.81261,0.7045,0.91584,0.67782,0.9905,0.56426,0.98741,0.48634,0.98741,0.28822,0.98741,0.1839,0.96953,0.01294,0.94024,0.01378,0.8483,0.07721,0.71233,0.13669,0.5848,0.19446,0.46095,0.27857,0.35201,0.33567,0.27805,0.39393,0.20259,0.46241,0.1139,0.5181,0.0702,0.59101,0.013],"triangles":[0,1,2,3,0,2,4,0,3,4,27,0,4,5,27,27,6,26,5,6,27,6,25,26,6,24,25,7,24,6,23,24,7,7,22,23,8,22,7,8,21,22,9,21,8,20,21,9,10,20,9,16,19,20,20,10,16,10,15,16,18,19,16,17,18,16,10,14,15,10,13,14,11,13,10,12,13,11],"vertices":[2,35,-26.94,7.73,0.00005,29,-7.87,7.73,0.99995,2,35,-26.59,17.51,0.00928,29,-7.51,17.51,0.99072,2,35,-25.32,18.13,0.01106,29,-6.24,18.13,0.98894,3,36,-38.47,18.99,0.00038,35,-19.39,18.99,0.04989,29,-0.32,18.99,0.94973,3,36,-31.45,20.01,0.00862,35,-12.37,20.01,0.17856,29,6.71,20.01,0.81282,3,36,-25.13,20.92,0.03839,35,-6.05,20.92,0.37571,29,13.02,20.92,0.5859,3,36,-18.35,21.9,0.11513,35,0.73,21.9,0.57896,29,19.81,21.9,0.30591,4,37,-30.21,22.95,0.00335,36,-11.13,22.95,0.26838,35,7.94,22.95,0.6293,29,27.02,22.95,0.09897,4,37,-21.79,24.17,0.03574,36,-2.71,24.17,0.50486,35,16.37,24.17,0.44872,29,35.44,24.17,0.01068,3,37,-13.04,25.44,0.14792,36,6.04,25.44,0.6497,35,25.12,25.44,0.20239,3,37,-4.8,26.63,0.34861,36,14.28,26.63,0.5877,35,33.36,26.63,0.06369,3,37,3.57,27.84,0.56376,36,22.65,27.84,0.42647,35,41.72,27.84,0.00977,3,37,9.62,28.72,0.63869,36,28.7,28.72,0.36046,35,47.78,28.72,0.00085,3,37,12.89,21.47,0.73091,36,31.97,21.47,0.26909,35,51.05,21.47,0,2,37,15.29,16.57,0.84235,36,34.36,16.57,0.15765,2,37,21.37,4.1,0.99891,36,40.45,4.1,0.00109,1,37,23.32,-3.07,1,2,37,26.52,-14.83,0.99941,36,45.59,-14.83,0.00059,2,37,20.05,-17.92,0.9775,36,39.12,-17.92,0.0225,2,37,8.57,-18.58,0.76903,36,27.64,-18.58,0.23097,3,37,-2.2,-19.2,0.33419,36,16.88,-19.2,0.6585,35,35.96,-19.2,0.00731,4,37,-12.65,-19.81,0.06244,36,6.42,-19.81,0.80984,35,25.5,-19.81,0.12738,29,44.58,-19.81,0.00034,4,37,-22.87,-18.25,0.00157,36,-3.79,-18.25,0.49521,35,15.28,-18.25,0.46333,29,34.36,-18.25,0.03989,3,36,-10.73,-17.18,0.20934,35,8.34,-17.18,0.61329,29,27.42,-17.18,0.17737,3,36,-17.81,-16.1,0.04951,35,1.27,-16.1,0.45363,29,20.34,-16.1,0.49686,3,36,-26.13,-14.83,0.002,35,-7.05,-14.83,0.11046,29,12.02,-14.83,0.88755,2,35,-11.83,-12.82,0.01906,29,7.25,-12.82,0.98094,1,29,1,-10.19,1],"edges":[0,54,0,2,2,4,24,26,34,36,40,42,36,38,38,40,42,44,44,46,46,48,48,50,50,52,52,54,4,6,6,8,8,10,10,12,12,14,14,16,16,18,18,20,20,22,22,24,26,28,28,30,30,32,32,34]}},"shenti":{"shenti":{"type":"mesh","hull":18,"width":88,"height":74,"uvs":[0.85262,0.08102,0.95725,0.26824,0.89861,0.49278,0.89918,0.57548,0.92505,0.63052,0.9889,0.76637,0.98875,0.85238,0.71569,0.98583,0.43686,0.99199,0.23647,0.91729,0.13615,0.79759,0.12025,0.59584,0.11184,0.48929,0.09964,0.33455,0.10407,0.14563,0.17582,0.08926,0.46766,0.01299,0.73836,0.01265,0.23399,0.31519,0.44855,0.34749,0.67668,0.34103,0.26386,0.49283,0.59521,0.48314,0.42977,0.48798,0.29102,0.64785,0.49743,0.6963,0.7473,0.68338],"triangles":[7,26,6,6,26,5,7,25,26,5,26,4,26,3,4,26,2,3,26,22,2,8,9,25,8,25,7,25,9,24,9,10,24,10,11,24,24,23,25,25,22,26,25,23,22,11,21,24,24,21,23,11,12,21,12,18,21,23,21,19,22,20,2,12,13,18,23,19,22,19,21,18,22,19,20,2,20,1,20,19,16,19,18,16,20,0,1,20,17,0,20,16,17,13,14,18,14,15,18,18,15,16],"vertices":[3,5,20.97,-27.92,0.85854,4,47.75,-27.92,0.07591,2,27.51,47.8,0.06555,3,5,7.11,-37.12,0.6404,4,33.9,-37.12,0.18637,2,36.72,33.95,0.17323,3,5,-9.5,-31.96,0.27398,4,17.28,-31.96,0.25589,2,31.56,17.33,0.47013,3,5,-15.62,-32.01,0.12496,4,11.16,-32.01,0.18345,2,31.61,11.21,0.69159,3,5,-19.69,-34.29,0.05921,4,7.09,-34.29,0.10816,2,33.89,7.14,0.83263,3,5,-29.75,-39.91,0.00577,4,-2.96,-39.91,0.01564,2,39.5,-2.91,0.97859,3,5,-36.11,-39.9,0.00064,4,-9.33,-39.9,0.00408,2,39.49,-9.28,0.99528,2,4,-19.2,-15.87,0.00334,2,15.46,-19.15,0.99666,2,4,-19.66,8.67,0.6661,2,-9.07,-19.61,0.3339,3,5,-40.92,26.3,0.0034,4,-14.13,26.3,0.98695,2,-26.71,-14.08,0.00965,2,5,-32.06,35.13,0.02894,4,-5.27,35.13,0.97106,3,5,-17.13,36.53,0.14737,4,9.66,36.53,0.85263,2,-36.94,9.71,0,3,5,-9.24,37.27,0.27767,4,17.54,37.27,0.72233,2,-37.68,17.59,0,3,5,2.21,38.34,0.50658,4,28.99,38.34,0.49341,2,-38.75,29.04,0,3,5,16.19,37.95,0.69891,4,42.97,37.95,0.30109,2,-38.36,43.02,0,3,5,20.36,31.64,0.75404,4,47.14,31.64,0.24596,2,-32.05,47.19,0,3,5,26,5.96,0.99622,4,52.79,5.96,0.00378,2,-6.36,52.84,0.00001,3,5,26.03,-17.86,0.95533,4,52.81,-17.86,0.02041,2,17.46,52.86,0.02425,3,5,3.64,26.52,0.5487,4,30.42,26.52,0.4513,2,-26.93,30.47,0,3,5,1.25,7.64,0.54425,4,28.03,7.64,0.45575,2,-8.05,28.08,0,3,5,1.73,-12.44,0.57116,4,28.51,-12.44,0.33314,2,12.03,28.56,0.0957,3,5,-9.51,23.89,0.22545,4,17.28,23.89,0.77455,2,-24.3,17.33,0,3,5,-8.79,-5.27,0.01668,4,18,-5.27,0.9015,2,4.86,18.05,0.08183,3,5,-9.15,9.29,0.0791,4,17.64,9.29,0.9209,2,-9.7,17.69,0,2,5,-20.98,21.5,0.057,4,5.81,21.5,0.943,1,4,2.22,3.34,1,3,5,-23.61,-18.65,0.02341,4,3.18,-18.65,0.11946,2,18.24,3.23,0.85713],"edges":[0,34,0,2,2,4,4,6,10,12,12,14,14,16,16,18,18,20,26,28,28,30,30,32,32,34,26,36,36,38,38,40,40,2,24,26,24,42,4,44,42,46,46,44,20,22,22,24,22,48,48,50,50,52,6,8,8,10,52,8]}},"shuijiqiu":{"shuijiqiu":{"x":0.09,"y":0.88,"width":82,"height":81}},"tou1":{"tou1":{"x":66.45,"y":26.66,"rotation":-90.39,"width":183,"height":166}},"toufa1":{"toufa1":{"type":"mesh","hull":20,"width":39,"height":97,"uvs":[0.89774,0.0096,0.89786,0.19135,0.89793,0.29757,0.898,0.40842,0.89806,0.51003,0.89814,0.62751,0.93302,0.75706,0.9559,0.84201,0.97556,0.91505,0.99567,0.98974,0.68648,0.99084,0.50408,0.91532,0.38542,0.86619,0.22968,0.80172,0.11129,0.68488,0.0224,0.59715,0.02405,0.50544,0.02565,0.41688,0.43798,0.15373,0.79862,0.00838],"triangles":[1,18,19,1,19,0,2,17,18,1,2,18,3,17,2,4,16,17,4,17,3,5,15,4,4,15,16,5,14,15,13,14,5,6,13,5,12,13,6,6,11,12,7,11,6,11,7,8,10,11,8,10,8,9],"vertices":[1,7,-21.5,18.2,1,2,12,-19.6,21.27,0.00177,7,-3.87,18.09,0.99823,2,12,-9.42,19.66,0.07864,7,6.43,18.03,0.92136,3,13,-14.6,20.4,0.0113,12,1.2,17.98,0.45084,7,17.18,17.96,0.53786,3,13,-5.2,17.42,0.15656,12,10.94,16.45,0.72219,7,27.04,17.9,0.12125,4,14,-10.79,15.77,0.01158,13,5.66,13.98,0.68932,12,22.19,14.67,0.29766,7,38.44,17.83,0.00144,3,14,1.08,11.44,0.42465,13,18.05,11.48,0.57021,12,34.82,14.05,0.00514,2,14,8.87,8.6,0.90567,13,26.17,9.83,0.09433,2,14,15.57,6.16,0.99878,13,33.16,8.42,0.00122,1,14,22.41,3.66,1,1,14,17.18,-7.2,1,2,14,7.46,-10.35,0.87523,13,27.62,-9.11,0.12477,3,14,1.14,-12.39,0.47135,13,21.68,-12.08,0.52857,12,41.94,-8.7,0.00007,3,14,-7.15,-15.08,0.08341,13,13.88,-15.98,0.88245,12,34.81,-13.72,0.03414,2,13,1.68,-16.95,0.60369,12,22.9,-16.51,0.39631,3,13,-7.48,-17.68,0.2287,12,13.95,-18.6,0.75437,7,35.27,-16.3,0.01693,3,13,-15.94,-14.93,0.04298,12,5.17,-17.15,0.78922,7,26.38,-16.18,0.1678,3,13,-24.11,-12.28,0.00066,12,-3.3,-15.75,0.49118,7,17.79,-16.07,0.50816,1,7,-7.63,0.18,1,1,7,-21.64,14.33,1],"edges":[0,38,18,20,34,36,36,38,30,32,32,34,26,28,28,30,24,26,20,22,22,24,16,18,14,16,10,12,12,14,8,10,6,8,4,6,0,2,2,4]}},"toufa2":{"toufa2":{"type":"mesh","hull":23,"width":49,"height":109,"uvs":[0.88293,0.10872,0.94898,0.27234,0.97219,0.37812,1,0.50489,1,0.55535,0.93706,0.65205,0.88274,0.73553,0.81182,0.84449,0.75445,0.93265,0.63741,0.99241,0.5136,0.99266,0.45538,0.96707,0.38221,0.85752,0.32605,0.77343,0.26888,0.68784,0.20756,0.59603,0.13957,0.49423,0.07638,0.39961,0,0.2805,0,0.21204,0.07581,0.17289,0.72041,0.00737,0.77857,0.0069],"triangles":[1,17,0,21,0,20,21,22,0,18,20,17,0,17,20,18,19,20,14,15,5,5,15,4,4,15,3,1,2,17,16,3,15,3,16,2,16,17,2,10,11,9,9,11,8,11,12,8,8,12,7,12,13,7,7,13,6,13,14,6,6,14,5],"vertices":[2,9,-22.43,18.9,0.00345,8,2.88,21.43,0.99655,2,9,-4.33,19.81,0.32059,8,20.97,20.19,0.67941,2,9,7.25,19.45,0.79405,8,32.42,18.45,0.20595,3,11,-28.96,15.35,0.03678,9,21.13,19.02,0.9579,8,46.15,16.38,0.00532,3,11,-23.49,15.95,0.10233,9,26.59,18.31,0.89765,8,51.48,15.03,0.00002,2,11,-12.68,14.02,0.42919,9,36.64,13.9,0.57081,2,11,-3.34,12.36,0.82058,9,45.32,10.08,0.17942,2,11,8.84,10.19,0.99972,9,56.65,5.1,0.00028,1,11,18.7,8.44,1,1,11,25.79,3.44,1,1,11,26.48,-2.58,1,1,11,24.01,-5.72,1,2,11,12.53,-10.58,0.996,9,55.34,-15.95,0.004,2,11,3.72,-14.31,0.88824,9,45.9,-17.5,0.11176,2,11,-5.25,-18.1,0.57338,9,36.29,-19.08,0.42662,3,11,-14.88,-22.18,0.21845,9,25.98,-20.76,0.77572,8,46.24,-23.7,0.00583,3,11,-25.55,-26.69,0.03483,9,14.54,-22.64,0.85678,8,34.66,-24.2,0.1084,3,11,-35.46,-30.88,0.0009,9,3.92,-24.38,0.59342,8,23.91,-24.67,0.40569,2,9,-9.44,-26.41,0.19102,8,10.4,-25.11,0.80898,2,9,-16.84,-25.45,0.0928,8,3.17,-23.27,0.9072,2,9,-20.59,-21.22,0.05215,8,-0.06,-18.62,0.94785,1,8,-9.78,16.43,1,1,8,-9.13,19.2,1],"edges":[0,44,0,2,6,8,16,18,18,20,20,22,34,36,36,38,38,40,40,42,42,44,14,16,12,14,8,10,10,12,22,24,24,26,26,28,28,30,30,32,32,34,2,4,4,6]}},"yaodai":{"yaodai":{"x":1.01,"y":15.2,"rotation":-90.91,"width":78,"height":37}},"youjiao":{"youjiao":{"x":14.88,"y":1.98,"rotation":90,"width":26,"height":18}}}}],"animations":{"attack":{"slots":{"shuijiqiu":{"attachment":[{"time":0.3667,"name":null}]}},"bones":{"all2":{"rotate":[{"curve":0.25,"c3":0.75},{"time":0.1,"angle":-2.27,"curve":0.25,"c3":0.75},{"time":0.3,"angle":5.43,"curve":0.25,"c3":0.75},{"time":0.3667,"angle":-20.46,"curve":"stepped"},{"time":0.6667,"angle":-20.46,"curve":0.25,"c3":0.75},{"time":0.8333}],"translate":[{"curve":0.25,"c3":0.75},{"time":0.1,"x":-22.19,"y":-2.34,"curve":0.25,"c3":0.75},{"time":0.3,"x":-19.86,"y":1.75,"curve":0.25,"c3":0.75},{"time":0.3667,"x":19.31,"y":-7.59,"curve":0.25,"c3":0.75},{"time":0.5,"x":22.1,"y":-2.34,"curve":0.25,"c3":0.75},{"time":0.6667,"x":19.31,"y":-7.59,"curve":0.25,"c3":0.75},{"time":0.8333}]},"target1":{"rotate":[{"time":0.3,"curve":0.25,"c3":0.75},{"time":0.3667,"angle":-69.11,"curve":0.25,"c3":0.75},{"time":0.5,"angle":-56,"curve":0.25,"c3":0.75},{"time":0.6667,"angle":-62.75,"curve":0.25,"c3":0.75},{"time":0.8333}],"translate":[{"curve":0.25,"c3":0.75},{"time":0.1,"x":-25.7,"curve":"stepped"},{"time":0.3,"x":-25.7,"curve":0.25,"c3":0.75},{"time":0.3667,"x":4.09,"y":7.01,"curve":0.25,"c3":0.75},{"time":0.5,"x":4.09,"y":14.57,"curve":0.25,"c3":0.75},{"time":0.6667,"x":4.09,"y":7.01,"curve":0.25,"c3":0.75},{"time":0.8333}]},"shenti":{"rotate":[{"curve":0.25,"c3":0.75},{"time":0.1,"angle":12.08,"curve":0.25,"c3":0.75},{"time":0.3,"angle":4.27,"curve":0.25,"c3":0.75},{"time":0.3667,"angle":-2.79,"curve":0.25,"c3":0.75},{"time":0.5,"angle":-1.93,"curve":0.25,"c3":0.75},{"time":0.6667,"angle":-2.79,"curve":0.25,"c3":0.75},{"time":0.8333}],"translate":[{"curve":0.25,"c3":0.75},{"time":0.1,"x":2.75,"y":-0.29,"curve":0.25,"c3":0.75},{"time":0.3,"curve":0.25,"c3":0.75},{"time":0.3667,"x":2.06,"y":-0.94,"curve":0.25,"c3":0.75},{"time":0.5,"x":1.38,"y":0.88,"curve":0.25,"c3":0.75},{"time":0.6667,"x":2.06,"y":-0.94,"curve":0.25,"c3":0.75},{"time":0.8333}]},"tou1":{"rotate":[{"curve":0.25,"c3":0.75},{"time":0.1,"angle":5.1,"curve":0.25,"c3":0.75},{"time":0.3,"angle":4.27,"curve":0.25,"c3":0.75},{"time":0.3667,"angle":22.72,"curve":0.25,"c3":0.75},{"time":0.5,"angle":12.62,"curve":0.25,"c3":0.75},{"time":0.6667,"angle":22.72,"curve":0.25,"c3":0.75},{"time":0.8333}],"translate":[{"curve":0.25,"c3":0.75},{"time":0.1,"x":-4.75,"y":3.38,"curve":0.25,"c3":0.75},{"time":0.3,"curve":0.25,"c3":0.75},{"time":0.3667,"x":-1.94,"y":-3.32,"curve":0.25,"c3":0.75},{"time":0.5,"x":0.67,"y":-2.04,"curve":0.25,"c3":0.75},{"time":0.6667,"x":-1.94,"y":-3.32,"curve":0.25,"c3":0.75},{"time":0.8333}]},"shenti2":{"rotate":[{"curve":0.25,"c3":0.75},{"time":0.1,"angle":-5.28,"curve":0.25,"c3":0.75},{"time":0.3,"angle":4.27,"curve":0.25,"c3":0.75},{"time":0.3667,"angle":-2.79,"curve":0.25,"c3":0.75},{"time":0.5,"angle":-1.93,"curve":0.25,"c3":0.75},{"time":0.6667,"angle":-2.79,"curve":0.25,"c3":0.75},{"time":0.8333}],"translate":[{"curve":0.25,"c3":0.75},{"time":0.1,"x":-3.16,"y":3.01,"curve":0.25,"c3":0.75},{"time":0.3,"curve":0.25,"c3":0.75},{"time":0.3667,"x":-0.21,"y":-3.57,"curve":0.25,"c3":0.75},{"time":0.5,"x":2.17,"y":-2.55,"curve":0.25,"c3":0.75},{"time":0.6667,"x":-0.21,"y":-3.57,"curve":0.25,"c3":0.75},{"time":0.8333}]},"Youxiaobi":{"rotate":[{},{"time":0.1,"angle":-45.4},{"time":0.3,"angle":-42.98},{"time":0.3333,"angle":-116.05},{"time":0.3667,"angle":-130.23},{"time":0.5,"angle":141,"curve":"stepped"},{"time":0.5333,"angle":-58.19},{"time":0.6667,"angle":-62.39},{"time":0.8333}],"translate":[{},{"time":0.1,"x":7.71,"y":33.28},{"time":0.3,"x":19.84,"y":54.81},{"time":0.3667}],"scale":[{"time":0.3,"curve":"stepped"},{"time":0.3333,"x":-1,"curve":"stepped"},{"time":0.4333,"x":-1},{"time":0.5,"x":-0.921,"y":0.921,"curve":"stepped"},{"time":0.5333,"x":0.896,"y":0.896},{"time":0.6667}]},"Youdabi":{"rotate":[{},{"time":0.1,"angle":-8.93},{"time":0.3,"angle":-27.55},{"time":0.3667,"angle":-32.31},{"time":0.5,"angle":-27.75,"curve":"stepped"},{"time":0.5333,"angle":-18.13},{"time":0.6667,"angle":29.22},{"time":0.8333}],"scale":[{"time":0.4333},{"time":0.5,"x":0.921,"y":0.921},{"time":0.5333,"x":0.896,"y":0.896},{"time":0.6667}]},"Youdabi2":{"rotate":[{},{"time":0.1,"angle":21.69},{"time":0.3,"angle":7.19},{"time":0.3667,"angle":-29.98},{"time":0.5,"angle":-6.19,"curve":"stepped"},{"time":0.5333,"angle":-18.13},{"time":0.6667,"angle":29.22},{"time":0.8333}],"scale":[{"time":0.4333},{"time":0.5,"x":0.921,"y":0.921},{"time":0.5333}]},"Zuodabi":{"rotate":[{"curve":0.25,"c3":0.75},{"time":0.1,"angle":-10.13,"curve":0.25,"c3":0.75},{"time":0.3,"angle":-4.79,"curve":0.25,"c3":0.75},{"time":0.3667,"angle":-10.24,"curve":0.25,"c3":0.75},{"time":0.5,"angle":15.75,"curve":0.25,"c3":0.75},{"time":0.6667,"angle":9.62,"curve":0.25,"c3":0.75},{"time":0.8333}]},"Zuoxiaobi":{"rotate":[{"curve":0.25,"c3":0.75},{"time":0.1,"angle":-10.13,"curve":0.25,"c3":0.75},{"time":0.3,"angle":47.68,"curve":0.25,"c3":0.75},{"time":0.3667,"angle":-10.02,"curve":0.25,"c3":0.75},{"time":0.5,"angle":6.35,"curve":0.25,"c3":0.75},{"time":0.6667,"angle":-14.47,"curve":0.25,"c3":0.75},{"time":0.8333}]},"shuijiqiu":{"translate":[{},{"time":0.1,"x":-82.35,"y":-94.25},{"time":0.3,"x":-126.27,"y":-96.07},{"time":0.3667,"x":92.42,"y":-84.18},{"time":0.5}]},"qunbaoZuo":{"rotate":[{"curve":0.25,"c3":0.75},{"time":0.1,"angle":6.12,"curve":0.25,"c3":0.75},{"time":0.3,"angle":1.36,"curve":0.25,"c3":0.75},{"time":0.3667,"angle":-20.22,"curve":0.25,"c3":0.75},{"time":0.5,"angle":-25.55,"curve":0.25,"c3":0.75},{"time":0.6667}]},"qunbaoZuo2":{"rotate":[{"curve":0.25,"c3":0.75},{"time":0.1,"angle":6.12,"curve":0.25,"c3":0.75},{"time":0.3,"angle":-2.94,"curve":0.25,"c3":0.75},{"time":0.3667,"angle":11.9,"curve":0.25,"c3":0.75},{"time":0.5,"angle":-25.55,"curve":0.25,"c3":0.75},{"time":0.6667,"angle":-8.01,"curve":0.25,"c3":0.75},{"time":0.8333}]},"qunbaoZuo3":{"rotate":[{"curve":0.25,"c3":0.75},{"time":0.1,"angle":6.12,"curve":0.25,"c3":0.75},{"time":0.3,"angle":-2.94,"curve":0.25,"c3":0.75},{"time":0.3667,"angle":11.9,"curve":0.25,"c3":0.75},{"time":0.5,"angle":-25.55,"curve":0.25,"c3":0.75},{"time":0.6667,"angle":-8.01,"curve":0.25,"c3":0.75},{"time":0.8333}]},"qunbaoZuo4":{"rotate":[{"curve":0.25,"c3":0.75},{"time":0.1,"angle":6.12,"curve":0.25,"c3":0.75},{"time":0.3,"angle":-2.94,"curve":0.25,"c3":0.75},{"time":0.3667,"angle":11.9,"curve":0.25,"c3":0.75},{"time":0.5,"angle":-25.55,"curve":0.25,"c3":0.75},{"time":0.6667,"angle":-8.01,"curve":0.25,"c3":0.75},{"time":0.8333}]},"qunbaiYou":{"rotate":[{"curve":0.25,"c3":0.75},{"time":0.1,"angle":6.88,"curve":0.25,"c3":0.75},{"time":0.3,"angle":-3.28,"curve":0.25,"c3":0.75},{"time":0.4,"angle":12.62,"curve":0.25,"c3":0.75},{"time":0.5333,"angle":-6.65,"curve":0.25,"c3":0.75},{"time":0.7}]},"qunbaiYou2":{"rotate":[{"curve":0.25,"c3":0.75},{"time":0.1,"angle":6.88,"curve":0.25,"c3":0.75},{"time":0.3,"angle":-3.28,"curve":0.25,"c3":0.75},{"time":0.4,"angle":16.45,"curve":0.25,"c3":0.75},{"time":0.5333,"angle":-6.5,"curve":0.25,"c3":0.75},{"time":0.7,"angle":11.13,"curve":0.25,"c3":0.75},{"time":0.8333}]},"qunbaiYou3":{"rotate":[{"curve":0.25,"c3":0.75},{"time":0.1,"angle":6.88,"curve":0.25,"c3":0.75},{"time":0.3,"angle":-3.28,"curve":0.25,"c3":0.75},{"time":0.4,"angle":21.65,"curve":0.25,"c3":0.75},{"time":0.5333,"angle":-6.5,"curve":0.25,"c3":0.75},{"time":0.7,"angle":11.13,"curve":0.25,"c3":0.75},{"time":0.8333}]},"qunbaiYou4":{"rotate":[{"curve":0.25,"c3":0.75},{"time":0.1,"angle":6.88,"curve":0.25,"c3":0.75},{"time":0.3,"angle":-3.28,"curve":0.25,"c3":0.75},{"time":0.4,"angle":21.65,"curve":0.25,"c3":0.75},{"time":0.5333,"angle":-6.5,"curve":0.25,"c3":0.75},{"time":0.7,"angle":11.13,"curve":0.25,"c3":0.75},{"time":0.8333}]},"dangbu":{"rotate":[{"curve":0.25,"c3":0.75},{"time":0.1,"angle":16.83,"curve":0.25,"c3":0.75},{"time":0.3,"angle":7.11,"curve":0.25,"c3":0.75},{"time":0.3667,"angle":-17.23,"curve":0.25,"c3":0.75},{"time":0.5,"angle":17.33,"curve":0.25,"c3":0.75},{"time":0.6667}]},"dangbu2":{"rotate":[{"curve":0.25,"c3":0.75},{"time":0.1,"angle":16.83,"curve":0.25,"c3":0.75},{"time":0.3,"angle":7.11,"curve":0.25,"c3":0.75},{"time":0.3667,"angle":-19.86,"curve":0.25,"c3":0.75},{"time":0.5,"angle":17.33,"curve":0.25,"c3":0.75},{"time":0.6667,"angle":-6.01,"curve":0.25,"c3":0.75},{"time":0.8333}]},"dangbu3":{"rotate":[{"curve":0.25,"c3":0.75},{"time":0.1,"angle":16.83,"curve":0.25,"c3":0.75},{"time":0.3,"angle":7.11,"curve":0.25,"c3":0.75},{"time":0.3667,"angle":-23.52,"curve":0.25,"c3":0.75},{"time":0.5,"angle":17.33,"curve":0.25,"c3":0.75},{"time":0.6667,"angle":-6.01,"curve":0.25,"c3":0.75},{"time":0.8333}]},"dangbu4":{"rotate":[{"curve":0.25,"c3":0.75},{"time":0.1,"angle":16.83,"curve":0.25,"c3":0.75},{"time":0.3,"angle":7.11,"curve":0.25,"c3":0.75},{"time":0.3667,"angle":-25.22,"curve":0.25,"c3":0.75},{"time":0.5,"angle":17.33,"curve":0.25,"c3":0.75},{"time":0.6667,"angle":-6.01,"curve":0.25,"c3":0.75},{"time":0.8333}]},"toufa1b":{"rotate":[{"curve":0.25,"c3":0.75},{"time":0.1,"angle":14.57,"curve":0.25,"c3":0.75},{"time":0.3,"angle":-10.02,"curve":0.25,"c3":0.75},{"time":0.3667,"angle":6.49,"curve":0.25,"c3":0.75},{"time":0.5,"angle":-19.94,"curve":0.25,"c3":0.75},{"time":0.6667}]},"toufa1d":{"rotate":[{"curve":0.25,"c3":0.75},{"time":0.1,"angle":14.57,"curve":0.25,"c3":0.75},{"time":0.3,"angle":-10.02,"curve":0.25,"c3":0.75},{"time":0.3667,"angle":17.05,"curve":0.25,"c3":0.75},{"time":0.5,"angle":-19.94,"curve":0.25,"c3":0.75},{"time":0.6667,"angle":3.41,"curve":0.25,"c3":0.75},{"time":0.8333}]},"toufa1c":{"rotate":[{"curve":0.25,"c3":0.75},{"time":0.1,"angle":14.57,"curve":0.25,"c3":0.75},{"time":0.3,"angle":-10.02,"curve":0.25,"c3":0.75},{"time":0.3667,"angle":17.38,"curve":0.25,"c3":0.75},{"time":0.5,"angle":-19.94,"curve":0.25,"c3":0.75},{"time":0.6667,"angle":3.41,"curve":0.25,"c3":0.75},{"time":0.8333}]},"toufa2d":{"rotate":[{"curve":0.25,"c3":0.75},{"time":0.1,"angle":14.57,"curve":0.25,"c3":0.75},{"time":0.3,"angle":-3.41,"curve":0.25,"c3":0.75},{"time":0.3667,"angle":7.89,"curve":0.25,"c3":0.75},{"time":0.5,"angle":-13.47,"curve":0.25,"c3":0.75},{"time":0.6667,"angle":16.32,"curve":0.25,"c3":0.75},{"time":0.8333}]},"toufa2c":{"rotate":[{},{"time":0.1,"angle":14.57},{"time":0.3,"angle":-3.41},{"time":0.3667,"angle":26.62},{"time":0.5,"angle":-13.47},{"time":0.6667,"angle":11.12},{"time":0.8333}]},"toufa2b":{"rotate":[{},{"time":0.1,"angle":14.57},{"time":0.3,"angle":-3.41},{"time":0.3667,"angle":8.86},{"time":0.5,"angle":-13.47},{"time":0.6667,"angle":3.62},{"time":0.8333}]},"toufa2":{"rotate":[{"curve":0.25,"c3":0.75},{"time":0.1,"angle":14.57,"curve":0.25,"c3":0.75},{"time":0.3,"angle":-3.41,"curve":0.25,"c3":0.75},{"time":0.3667,"angle":0.94,"curve":0.25,"c3":0.75},{"time":0.5,"angle":-13.47,"curve":0.25,"c3":0.75},{"time":0.6667}]},"tou2":{"rotate":[{"time":0.3667,"curve":0.25,"c3":0.75},{"time":0.4333,"angle":9.19,"curve":0.25,"c3":0.75},{"time":0.5667,"angle":-10.73,"curve":0.25,"c3":0.75},{"time":0.7333}],"translate":[{"time":0.0667,"curve":0.25,"c3":0.75},{"time":0.1667,"x":-3.58,"y":0.63,"curve":0.25,"c3":0.75},{"time":0.3667,"x":0.85,"y":-0.86,"curve":0.25,"c3":0.75},{"time":0.4333,"x":-7.54,"y":-5.06,"curve":0.25,"c3":0.75},{"time":0.5667,"x":1.93,"y":3.56,"curve":0.25,"c3":0.75},{"time":0.7333}],"scale":[{"time":0.0667,"curve":0.25,"c3":0.75},{"time":0.1667,"x":1.086,"y":1.086,"curve":"stepped"},{"time":0.3667,"x":1.086,"y":1.086,"curve":0.25,"c3":0.75},{"time":0.4333,"x":1.173,"y":1.173,"curve":0.25,"c3":0.75},{"time":0.5667}]},"tou4":{"rotate":[{"time":0.3333,"curve":0.25,"c3":0.75},{"time":0.4,"angle":9.19,"curve":0.25,"c3":0.75},{"time":0.5333,"angle":-10.73,"curve":0.25,"c3":0.75},{"time":0.7}],"translate":[{"time":0.0333,"curve":0.25,"c3":0.75},{"time":0.1333,"x":-3.58,"y":0.63,"curve":0.25,"c3":0.75},{"time":0.3333,"x":0.85,"y":-0.86,"curve":0.25,"c3":0.75},{"time":0.4,"x":-7.54,"y":-5.06,"curve":0.25,"c3":0.75},{"time":0.5333,"x":1.93,"y":3.56,"curve":0.25,"c3":0.75},{"time":0.7}],"scale":[{"time":0.0333,"curve":0.25,"c3":0.75},{"time":0.1333,"x":1.086,"y":1.086,"curve":"stepped"},{"time":0.3333,"x":1.086,"y":1.086,"curve":0.25,"c3":0.75},{"time":0.4,"x":1.173,"y":1.173,"curve":0.25,"c3":0.75},{"time":0.5333}]},"tou3":{"rotate":[{"time":0.3,"curve":0.25,"c3":0.75},{"time":0.3667,"angle":9.19,"curve":0.25,"c3":0.75},{"time":0.5,"angle":-10.73,"curve":0.25,"c3":0.75},{"time":0.6667}],"translate":[{"curve":0.25,"c3":0.75},{"time":0.1,"x":-3.58,"y":0.63,"curve":0.25,"c3":0.75},{"time":0.3,"x":0.85,"y":-0.86,"curve":0.25,"c3":0.75},{"time":0.3667,"x":-7.54,"y":-5.06,"curve":0.25,"c3":0.75},{"time":0.5,"x":1.93,"y":3.56,"curve":0.25,"c3":0.75},{"time":0.6667}],"scale":[{"curve":0.25,"c3":0.75},{"time":0.1,"x":1.086,"y":1.086,"curve":"stepped"},{"time":0.3,"x":1.086,"y":1.086,"curve":0.25,"c3":0.75},{"time":0.3667,"x":1.173,"y":1.173,"curve":0.25,"c3":0.75},{"time":0.5}]},"effect/g2_0":{"scale":[{"x":0,"y":0}]},"effect/g_0":{"scale":[{"x":0,"y":0}]},"effect/g_1":{"scale":[{"x":0,"y":0}]}},"deform":{"default":{"qunbaihou":{"qunbaihou":[{"curve":0.25,"c3":0.75},{"time":0.1,"curve":0.25,"c3":0.75,"vertices":[-4.95066,2.67891,-5.40964,-1.55598,-4.95066,2.67891,-5.40964,-1.55598,-4.95066,2.67891,-5.40964,-1.55598,-4.95066,2.67891,-5.54476,-0.9701,-5.40964,-1.55598,-4.95066,2.67891,-5.40964,-1.55598,-4.59398,3.25282,-4.17109,3.77989,-4.59398,3.25282,-4.17109,3.77989,-4.59398,3.25282,-4.95066,2.67891,-5.61662,-0.37315,-5.54476,-0.9701,-5.40964,-1.55598,-4.17109,3.77989,-4.59398,3.25282,-4.95066,2.67891,-5.61662,-0.37315,-5.54476,-0.9701,-5.40964,-1.55598,-4.17109,3.77989,-4.59398,3.25282,-4.95066,2.67891,-5.61662,-0.37315,-5.54476,-0.9701,-5.40964,-1.55598,-4.17109,3.77989,-4.59398,3.25282,-4.95066,2.67891,-5.61662,-0.37315,-5.54476,-0.9701,-5.40964,-1.55598,-4.17109,3.77989,-4.59398,3.25282,-4.95066,2.67891,-5.61662,-0.37315,-5.54476,-0.9701,-5.40964,-1.55598,-4.17109,3.77989,-4.59398,3.25282,-4.95066,2.67891,-5.61662,-0.37315,-5.54476,-0.9701,-5.40964,-1.55598,-4.17109,3.77989,-4.59398,3.25282,-4.95066,2.67891,-5.61662,-0.37315,-5.54476,-0.9701,-5.40964,-1.55598,-4.17109,3.77989,-4.59398,3.25282,-4.95066,2.67891,-5.61662,-0.37315,-5.54476,-0.9701,-5.40964,-1.55598,-4.17109,3.77989,-4.59398,3.25282,-4.95066,2.67891,-5.61662,-0.37315,-5.54476,-0.9701,-5.40964,-1.55598,-4.17109,3.77989,-4.59398,3.25282,-4.95066,2.67891,-5.61662,-0.37315,-5.54476,-0.9701,-5.40964,-1.55598,-5.61662,-0.37315,-5.61662,-0.37315,-5.61662,-0.37315,-5.54476,-0.9701,-5.54476,-0.9701,-5.54476,-0.9701,-5.40964,-1.55598,-5.40964,-1.55598]},{"time":0.3,"curve":0.25,"c3":0.75},{"time":0.3667,"curve":0.25,"c3":0.75,"vertices":[-10.78541,7.67164,-10.79112,-7.66365,-11.51415,5.22287,-8.71806,-9.15691,-16.14064,-0.16356,-5.15201,-15.29707,-18.42788,-1.31956,-8.38665,-16.46166,-4.81221,-17.83722,-19.67453,-2.10325,-4.48194,-19.27222,-21.93649,1.39077,-23.26575,5.27847,-23.82394,1.25503,-24.93887,5.99829,-25.59489,1.68061,-25.50893,-2.68575,-15.42969,-20.49021,-10.87348,-23.23096,-5.84989,-24.97381,-26.16348,6.4996,-26.88683,1.96691,-26.8307,-2.62276,-16.37706,-21.4141,-11.61003,-24.33033,-6.34392,-26.20139,-25.62335,7.97755,-26.60521,3.51505,-26.8158,-1.04927,-17.51784,-20.33028,-12.94975,-23.50501,-7.82505,-25.67004,-25.17527,8.87434,-26.31576,4.47485,-26.69339,-0.05429,-18.16216,-19.56226,-13.73857,-22.88634,-8.72448,-25.22729,-24.08566,10.53883,-25.52429,6.3001,-26.223,1.87874,-19.25536,-17.90008,-15.15099,-21.48528,-10.39544,-24.14756,-21.36974,13.04042,-23.27214,9.22612,-24.49985,5.14443,-20.4691,-14.41285,-17.05767,-18.32323,-12.91308,-21.44658,-12.8642,17.23736,-15.60184,14.8051,-17.88713,11.94374,-20.93346,-4.93957,-19.46528,-9.14923,-17.1605,-12.96613,-11.21713,17.90923,-14.09263,15.74664,-16.55952,13.12767,-20.89417,-3.16117,-19.79351,-7.40097,-17.84214,-11.32309,-10.12254,18.59989,-13.13107,16.61298,-15.75885,14.14457,-21.09202,-1.88215,-20.25083,-6.19016,-18.53928,-10.23261,-9.46437,19.16966,-12.57905,17.28614,-15.32906,14.9016,-21.35273,-1.0515,-20.67717,-5.43119,-19.11296,-9.57782,-21.49947,-0.32314,-20.68238,-0.11046,-19.24211,-0.06831,-18.81462,-4.03393,-16.8577,-3.96067,-14.88787,-4.00411,-13.74226,-6.98777,-12.37563,-6.9568]},{"time":0.5,"curve":0.25,"c3":0.75,"vertices":[-11.15352,11.57405,-13.19098,-9.1843,-11.15352,11.57405,-13.19098,-9.1843,-11.15352,11.57405,-13.19098,-9.1843,-11.15352,11.57405,-7.93834,-13.97629,-13.19098,-9.1843,-11.15352,11.57405,-13.19098,-9.1843,-12.39192,10.23717,-13.47097,8.76884,-12.39192,10.23717,-13.47097,8.76884,-12.39192,10.23717,-11.15352,11.57405,-1.13274,-16.03348,-7.93834,-13.97629,-13.19098,-9.1843,-13.47097,8.76884,-12.39192,10.23717,-11.15352,11.57405,-1.13274,-16.03348,-7.93834,-13.97629,-13.19098,-9.1843,-13.47097,8.76884,-12.39192,10.23717,-11.15352,11.57405,-1.13274,-16.03348,-7.93834,-13.97629,-13.19098,-9.1843,-13.47097,8.76884,-12.39192,10.23717,-11.15352,11.57405,-1.13274,-16.03348,-7.93834,-13.97629,-13.19098,-9.1843,-13.47097,8.76884,-12.39192,10.23717,-11.15352,11.57405,-1.13274,-16.03348,-7.93834,-13.97629,-13.19098,-9.1843,-13.47097,8.76884,-12.39192,10.23717,-11.15352,11.57405,-1.13274,-16.03348,-7.93834,-13.97629,-13.19098,-9.1843,-13.47097,8.76884,-12.39192,10.23717,-11.15352,11.57405,-1.13274,-16.03348,-7.93834,-13.97629,-13.19098,-9.1843,-13.47097,8.76884,-12.39192,10.23717,-11.15352,11.57405,-1.13274,-16.03348,-7.93834,-13.97629,-13.19098,-9.1843,-13.47097,8.76884,-12.39192,10.23717,-11.15352,11.57405,-1.13274,-16.03348,-7.93834,-13.97629,-13.19098,-9.1843,-13.47097,8.76884,-12.39192,10.23717,-11.15352,11.57405,-1.13274,-16.03348,-7.93834,-13.97629,-13.19098,-9.1843,-1.13274,-16.03348,-1.13274,-16.03348,-1.13274,-16.03348,-7.93834,-13.97629,-7.93834,-13.97629,-7.93834,-13.97629,-13.19098,-9.1843,-13.19098,-9.1843]},{"time":0.6667,"curve":0.25,"c3":0.75,"vertices":[-10.14726,3.75058,-8.06441,-7.21119,-10.1404,1.88547,-6.41305,-8.07823,-12.5017,-2.33627,-3.78785,-12.14114,-14.07938,-3.16742,-1.81509,-14.31683,-3.79193,-13.92434,-14.94535,-3.70537,-3.72195,-14.94143,-17.02975,-0.61775,-18.25483,2.85736,-18.46307,-0.72078,-19.52149,3.42799,-19.81608,-0.40545,-19.36485,-4.22392,0.14103,-19.81985,-2.62119,-19.64626,-5.33261,-19.08949,-20.45291,3.82521,-20.80667,-0.19552,-20.37733,-4.20922,-0.08209,-20.80754,-2.97972,-20.59327,-5.81958,-19.97732,-20.07378,4.96689,-20.65511,0.99783,-20.45904,-3.00903,-1.27333,-20.64005,-4.13604,-20.26147,-6.91838,-19.48767,-19.77968,5.67297,-20.50288,1.74744,-20.4544,-2.24415,-2.02084,-20.47783,-4.85365,-19.99667,-7.59211,-19.12551,-19.08223,7.00078,-20.07491,3.18494,-20.31206,-0.75109,-3.45251,-20.03072,-6.20904,-19.3545,-8.84483,-18.30077,-17.36843,9.07528,-18.7939,5.55128,-19.51205,1.81808,-5.80155,-18.71827,-8.35236,-17.7276,-10.74061,-16.39114,-11.45712,13.13464,-13.77761,10.67559,-15.57954,7.81454,-10.85847,-13.63404,-12.65173,-11.98847,-14.19854,-10.10905,-9.95471,13.60175,-12.39367,11.42402,-14.36615,8.81606,-11.58833,-12.24023,-13.18031,-10.50658,-14.51552,-8.56797,-8.80941,13.8502,-11.31789,11.88893,-13.40036,9.47993,-12.03885,-11.15836,-13.4757,-9.37249,-14.65004,-7.40379,-8.11921,13.96812,-10.66343,12.13792,-12.8063,9.85058,-12.27908,-10.50063,-13.62196,-8.6877,-14.6995,-6.70531,-12.39336,-9.94683,-11.77285,-9.78532,-10.7378,-9.76597,-11.99338,-8.17493,-10.597,-8.1451,-9.26201,-8.07452,-10.29663,-6.70547,-9.26827,-6.67673]},{"time":0.8333}]}}},"drawOrder":[{"offsets":[{"slot":"shuijiqiu","offset":-15}]}]},"dead":{"bones":{"all2":{"rotate":[{},{"time":0.0667,"angle":-4.69},{"time":0.1333,"angle":6.1},{"time":0.2},{"time":0.3,"angle":-1.02},{"time":0.4333}],"translate":[{},{"time":0.1333,"x":0.75,"y":13.52},{"time":0.2},{"time":0.3,"x":5},{"time":0.4333}]},"all":{"rotate":[{"curve":0.25,"c3":0.75},{"time":0.1333,"angle":17.21,"curve":0.25,"c3":0.75},{"time":0.2,"angle":90}],"translate":[{"curve":0.25,"c3":0.75},{"time":0.1333,"y":44.02,"curve":0.25,"c3":0.75},{"time":0.2,"x":24.97,"y":36.14}]},"tou1":{"rotate":[{"time":0.0333},{"time":0.1,"angle":-4.69},{"time":0.1667,"angle":6.1},{"time":0.2333,"angle":-5.76},{"time":0.3333,"angle":5.13},{"time":0.4667}],"translate":[{},{"time":0.0667,"x":-2.62,"y":-0.25},{"time":0.1333,"x":5.96,"y":1.11},{"time":0.2},{"time":0.3,"x":0.07,"y":-1.31},{"time":0.4333}]},"shenti2":{"rotate":[{"time":0.0333},{"time":0.1,"angle":-4.69},{"time":0.1667,"angle":6.1},{"time":0.2333},{"time":0.3333,"angle":-1.02},{"time":0.4667}],"translate":[{},{"time":0.0667,"x":-3.28,"y":-0.04},{"time":0.1333,"x":8.22,"y":0.41},{"time":0.2},{"time":0.3,"x":0.05,"y":-1.31},{"time":0.4333}]},"shenti":{"rotate":[{"time":0.0333},{"time":0.1,"angle":-4.69},{"time":0.1667,"angle":6.1},{"time":0.2333},{"time":0.3333,"angle":-1.02},{"time":0.4667}],"translate":[{},{"time":0.0667,"x":-0.04,"y":-0.66},{"time":0.1333,"x":-2.13,"y":10.72},{"time":0.2}]},"target1":{"rotate":[{},{"time":0.0667,"angle":-7.29},{"time":0.1333,"angle":24.19},{"time":0.2}],"translate":[{},{"time":0.0667,"x":-2.12,"y":-14.01},{"time":0.1333,"x":22.86,"y":-1.01},{"time":0.2,"x":17.39},{"time":0.2667}]},"target2":{"rotate":[{},{"time":0.0667,"angle":-7.29},{"time":0.1333,"angle":-26.9},{"time":0.2,"angle":36.62},{"time":0.3}],"translate":[{},{"time":0.0667,"x":-2.12,"y":-14.01},{"time":0.1333,"x":2.56,"y":-18.45},{"time":0.2,"x":28.99},{"time":0.3,"x":-32.67},{"time":0.3667,"x":-27.93},{"time":0.4333,"x":-32.67}]},"Zuodabi":{"rotate":[{"curve":0.25,"c3":0.75},{"time":0.1333,"angle":25.39,"curve":0.25,"c3":0.75},{"time":0.2667,"angle":16.64,"curve":0.25,"c3":0.75},{"time":0.4,"angle":17.67}]},"Zuoxiaobi":{"rotate":[{"time":0.0333,"curve":0.25,"c3":0.75},{"time":0.1667,"angle":25.39,"curve":0.25,"c3":0.75},{"time":0.3,"angle":16.64,"curve":0.25,"c3":0.75},{"time":0.4333,"angle":17.67}]},"Youxiaobi":{"rotate":[{},{"time":0.1333,"angle":-37.57},{"time":0.2333},{"time":0.3667,"angle":-92.3}]},"Youdabi":{"rotate":[{"time":0.0333,"curve":0.25,"c3":0.75},{"time":0.1667,"angle":-19.43,"curve":0.25,"c3":0.75},{"time":0.2667,"curve":0.25,"c3":0.75},{"time":0.4,"angle":-11.81},{"time":0.5,"angle":-8.61}]},"Youdabi2":{"rotate":[{"time":0.0667,"curve":0.25,"c3":0.75},{"time":0.2,"angle":-19.43,"curve":0.25,"c3":0.75},{"time":0.3,"curve":0.25,"c3":0.75},{"time":0.4333,"angle":25.46},{"time":0.5333,"angle":37.44}]},"shuijiqiu":{"rotate":[{"time":0.0333},{"time":0.2,"angle":90},{"time":0.3667,"angle":180}],"translate":[{"time":0.0333},{"time":0.2,"x":-123.24,"y":111.92},{"time":0.3667,"x":-246.48,"y":-176.42}]},"effect/g2_0":{"scale":[{"x":0,"y":0}]},"effect/g_0":{"scale":[{"x":0,"y":0}]},"effect/g_1":{"scale":[{"x":0,"y":0}]}},"drawOrder":[{"offsets":[{"slot":"shuijiqiu","offset":-18}]}]},"idle":{"bones":{"all2":{"rotate":[{"angle":0.8,"curve":0.375,"c2":0.62,"c3":0.716},{"time":0.0667,"angle":1.1,"curve":0.25,"c3":0.75},{"time":0.4,"angle":-1.19,"curve":0.243,"c3":0.68,"c4":0.71},{"time":0.6667,"angle":0.8}],"translate":[{"y":1.51,"curve":0.25,"c3":0.75},{"time":0.3333,"y":-4.03,"curve":0.25,"c3":0.75},{"time":0.6667,"y":1.51}]},"shenti":{"translate":[{"y":1.18,"curve":0.375,"c2":0.62,"c3":0.716},{"time":0.0667,"y":1.51,"curve":0.25,"c3":0.75},{"time":0.4,"y":-1.01,"curve":0.243,"c3":0.68,"c4":0.71},{"time":0.6667,"y":1.18}]},"shenti2":{"rotate":[{"angle":-0.34,"curve":0.339,"c2":0.35,"c3":0.697,"c4":0.76},{"time":0.1333,"angle":0.8,"curve":0.375,"c2":0.62,"c3":0.716},{"time":0.2,"angle":1.1,"curve":0.25,"c3":0.75},{"time":0.5333,"angle":-1.19,"curve":0.258,"c3":0.619,"c4":0.45},{"time":0.6667,"angle":-0.34}]},"tou1":{"rotate":[{"angle":-0.89,"curve":0.306,"c2":0.24,"c3":0.694,"c4":0.76},{"time":0.2,"angle":0.8,"curve":0.375,"c2":0.62,"c3":0.716},{"time":0.2667,"angle":1.1,"curve":0.25,"c3":0.75},{"time":0.6,"angle":-1.19,"curve":0.284,"c3":0.625,"c4":0.38},{"time":0.6667,"angle":-0.89}],"translate":[{"x":-1.86,"curve":0.363,"c2":0.44,"c3":0.755},{"time":0.2,"x":1.01,"curve":0.25,"c3":0.75},{"time":0.5333,"x":-3.53,"curve":0.258,"c3":0.619,"c4":0.45},{"time":0.6667,"x":-1.86}]},"yaodai":{"rotate":[{"angle":0.55,"curve":0.345,"c2":0.38,"c3":0.68,"c4":0.71},{"time":0.0333,"angle":0.8,"curve":0.375,"c2":0.62,"c3":0.716},{"time":0.1,"angle":1.1,"curve":0.25,"c3":0.75},{"time":0.4333,"angle":-1.19,"curve":0.243,"c3":0.655,"c4":0.63},{"time":0.6667,"angle":0.55}],"translate":[{"y":1.28,"curve":0.36,"c2":0.64,"c3":0.695},{"time":0.0333,"y":1.51,"curve":0.25,"c3":0.75},{"time":0.3667,"y":-4.03,"curve":0.245,"c3":0.711,"c4":0.83},{"time":0.6667,"y":1.28}]},"qunbaoZuo":{"rotate":[{"angle":-0.4,"curve":0.339,"c2":0.35,"c3":0.697,"c4":0.76},{"time":0.1333,"angle":2.07,"curve":0.375,"c2":0.62,"c3":0.716},{"time":0.2,"angle":2.72,"curve":0.25,"c3":0.75},{"time":0.5333,"angle":-2.25,"curve":0.258,"c3":0.619,"c4":0.45},{"time":0.6667,"angle":-0.4}]},"qunbaoZuo2":{"rotate":[{"angle":-3.16,"curve":0.303,"c2":0.24,"c3":0.661,"c4":0.65},{"time":0.1333,"angle":0.77,"curve":0.381,"c2":0.55,"c3":0.742},{"time":0.2667,"angle":3.65,"curve":0.25,"c3":0.75},{"time":0.6,"angle":-4.17,"curve":0.284,"c3":0.625,"c4":0.38},{"time":0.6667,"angle":-3.16}]},"qunbaoZuo4":{"rotate":[{"angle":-10.24,"curve":0.375,"c2":0.62,"c3":0.716},{"time":0.0667,"angle":-13.38,"curve":0.284,"c3":0.625,"c4":0.38},{"time":0.1333,"angle":-10.24,"curve":0.32,"c2":0.29,"c3":0.757},{"time":0.4,"angle":10.73,"curve":0.243,"c3":0.68,"c4":0.71},{"time":0.6667,"angle":-10.24}]},"qunbaoZuo3":{"rotate":[{"angle":-8.95,"curve":0.258,"c3":0.619,"c4":0.45},{"time":0.1333,"angle":-3.83,"curve":0.363,"c2":0.44,"c3":0.755},{"time":0.3333,"angle":4.97,"curve":0.25,"c3":0.75},{"time":0.6667,"angle":-8.95}]},"qunbaiYou":{"rotate":[{"angle":-0.64,"curve":0.375,"c2":0.62,"c3":0.716},{"time":0.0667,"angle":-1.62,"curve":0.25,"c3":0.75},{"time":0.4,"angle":5.88,"curve":0.243,"c3":0.68,"c4":0.71},{"time":0.6667,"angle":-0.64}]},"qunbaiYou2":{"rotate":[{"angle":1.06,"curve":0.381,"c2":0.55,"c3":0.742},{"time":0.1333,"angle":-3.37,"curve":0.25,"c3":0.75},{"time":0.4667,"angle":8.67,"curve":0.245,"c3":0.637,"c4":0.56},{"time":0.6667,"angle":1.06}]},"qunbaiYou3":{"rotate":[{"angle":5.49,"curve":0.363,"c2":0.44,"c3":0.755},{"time":0.2,"angle":-4.71,"curve":0.25,"c3":0.75},{"time":0.5333,"angle":11.42,"curve":0.258,"c3":0.619,"c4":0.45},{"time":0.6667,"angle":5.49}]},"qunbaiYou4":{"rotate":[{"angle":9.32,"curve":0.32,"c2":0.29,"c3":0.757},{"time":0.2667,"angle":-4.71,"curve":0.25,"c3":0.75},{"time":0.6,"angle":11.42,"curve":0.284,"c3":0.625,"c4":0.38},{"time":0.6667,"angle":9.32}]},"dangbu":{"rotate":[{"angle":-1.28,"curve":0.349,"c2":0.39,"c3":0.689,"c4":0.74},{"time":0.0667,"angle":-3.12,"curve":0.375,"c2":0.62,"c3":0.716},{"time":0.1333,"angle":-4.14,"curve":0.25,"c3":0.75},{"time":0.4667,"angle":3.71,"curve":0.245,"c3":0.637,"c4":0.56},{"time":0.6667,"angle":-1.28}]},"dangbu2":{"rotate":[{"angle":2.16,"curve":0.321,"c2":0.3,"c3":0.661,"c4":0.65},{"time":0.0667,"angle":-0.15,"curve":0.375,"c2":0.5,"c3":0.75},{"time":0.2333,"angle":-4.64,"curve":0.25,"c3":0.75},{"time":0.5667,"angle":4.33,"curve":0.269,"c3":0.618,"c4":0.42},{"time":0.6667,"angle":2.16}]},"dangbu3":{"rotate":[{"angle":6.15,"curve":0.284,"c3":0.625,"c4":0.38},{"time":0.0667,"angle":4.31,"curve":0.32,"c2":0.29,"c3":0.757},{"time":0.3333,"angle":-8,"curve":0.25,"c3":0.75},{"time":0.6667,"angle":6.15}]},"dangbu4":{"rotate":[{"angle":2.79,"curve":0.36,"c2":0.45,"c3":0.701,"c4":0.81},{"time":0.0667,"angle":5.55,"curve":0.36,"c2":0.64,"c3":0.695},{"time":0.1,"angle":6.15,"curve":0.25,"c3":0.75},{"time":0.4333,"angle":-8,"curve":0.243,"c3":0.655,"c4":0.63},{"time":0.6667,"angle":2.79}]},"Zuodabi":{"rotate":[{"angle":5.18,"curve":0.25,"c3":0.75},{"time":0.3333,"angle":-1.72,"curve":0.25,"c3":0.75},{"time":0.6667,"angle":5.18}]},"Zuoxiaobi":{"rotate":[{"angle":4.28,"curve":0.375,"c2":0.62,"c3":0.716},{"time":0.0667,"angle":5.18,"curve":0.25,"c3":0.75},{"time":0.4,"angle":-1.72,"curve":0.243,"c3":0.68,"c4":0.71},{"time":0.6667,"angle":4.28}]},"Youxiaobi":{"rotate":[{"angle":-8.85,"curve":0.25,"c3":0.75},{"time":0.3333,"angle":5.06,"curve":0.25,"c3":0.75},{"time":0.6667,"angle":-8.85}]},"Youdabi":{"rotate":[{"angle":-5.52,"curve":0.375,"c2":0.62,"c3":0.716},{"time":0.0667,"angle":-6.93,"curve":0.25,"c3":0.75},{"time":0.4,"angle":-7.9,"curve":0.243,"c3":0.68,"c4":0.71},{"time":0.6667,"angle":-5.52}]},"Youdabi2":{"rotate":[{"angle":-2.96,"curve":0.381,"c2":0.55,"c3":0.742},{"time":0.1333,"angle":-6.93,"curve":0.25,"c3":0.75},{"time":0.4667,"angle":3.87,"curve":0.245,"c3":0.637,"c4":0.56},{"time":0.6667,"angle":-2.96}]},"toufa1b":{"rotate":[{"angle":-7.88,"curve":0.25,"c3":0.75},{"time":0.3333,"angle":9.46,"curve":0.25,"c3":0.75},{"time":0.6667,"angle":-7.88}]},"toufa1d":{"rotate":[{"angle":12.5,"curve":0.32,"c2":0.29,"c3":0.757},{"time":0.2667,"angle":-17.74,"curve":0.25,"c3":0.75},{"time":0.6,"angle":17.03,"curve":0.284,"c3":0.625,"c4":0.38},{"time":0.6667,"angle":12.5}]},"toufa1c":{"rotate":[{"angle":-4.57,"curve":0.381,"c2":0.55,"c3":0.742},{"time":0.1333,"angle":-14.19,"curve":0.25,"c3":0.75},{"time":0.4667,"angle":11.97,"curve":0.245,"c3":0.637,"c4":0.56},{"time":0.6667,"angle":-4.57}]},"toufa2":{"rotate":[{"angle":3.56,"curve":0.25,"c3":0.75},{"time":0.3333,"angle":-5.03,"curve":0.25,"c3":0.75},{"time":0.6667,"angle":3.56}]},"toufa2b":{"rotate":[{"angle":1.45,"curve":0.381,"c2":0.55,"c3":0.742},{"time":0.1333,"angle":5.93,"curve":0.25,"c3":0.75},{"time":0.4667,"angle":-6.23,"curve":0.245,"c3":0.637,"c4":0.56},{"time":0.6667,"angle":1.45}]},"toufa2c":{"rotate":[{"angle":-7.3,"curve":0.32,"c2":0.29,"c3":0.757},{"time":0.2667,"angle":9.26,"curve":0.25,"c3":0.75},{"time":0.6,"angle":-9.77,"curve":0.284,"c3":0.625,"c4":0.38},{"time":0.6667,"angle":-7.3}]},"toufa2d":{"rotate":[{"angle":-7.3,"curve":0.375,"c2":0.62,"c3":0.716},{"time":0.0667,"angle":-9.77,"curve":0.25,"c3":0.75},{"time":0.4,"angle":9.26,"curve":0.243,"c3":0.68,"c4":0.71},{"time":0.6667,"angle":-7.3}]},"tou2":{"rotate":[{"angle":-6.82,"curve":0.306,"c2":0.24,"c3":0.694,"c4":0.76},{"time":0.2,"angle":3.37,"curve":0.375,"c2":0.62,"c3":0.716},{"time":0.2667,"angle":5.16,"curve":0.25,"c3":0.75},{"time":0.6,"angle":-8.63,"curve":0.284,"c3":0.625,"c4":0.38},{"time":0.6667,"angle":-6.82}],"translate":[{"x":-2.05,"y":0.02,"curve":0.363,"c2":0.44,"c3":0.755},{"time":0.2,"curve":0.25,"c3":0.75},{"time":0.5333,"x":-3.25,"y":0.03,"curve":0.258,"c3":0.619,"c4":0.45},{"time":0.6667,"x":-2.05,"y":0.02}],"scale":[{"x":1.096,"y":1.096,"curve":0.245,"c3":0.637,"c4":0.56},{"time":0.2,"x":1.035,"y":1.035,"curve":0.381,"c2":0.55,"c3":0.742},{"time":0.3333,"curve":0.25,"c3":0.75},{"time":0.6667,"x":1.096,"y":1.096}]},"tou4":{"rotate":[{"angle":-1.68,"curve":0.347,"c2":0.38,"c3":0.694,"c4":0.76},{"time":0.1,"angle":3.37,"curve":0.375,"c2":0.62,"c3":0.716},{"time":0.1667,"angle":5.16,"curve":0.25,"c3":0.75},{"time":0.5,"angle":-8.63,"curve":0.258,"c3":0.619,"c4":0.45},{"time":0.6333,"angle":-3.49,"curve":0.33,"c2":0.32,"c3":0.665,"c4":0.66},{"time":0.6667,"angle":-1.68}],"translate":[{"x":-0.78,"y":0.01,"curve":0.382,"c2":0.58,"c3":0.731},{"time":0.1,"curve":0.25,"c3":0.75},{"time":0.4333,"x":-3.25,"y":0.03,"curve":0.245,"c3":0.637,"c4":0.56},{"time":0.6333,"x":-1.2,"y":0.01,"curve":0.339,"c2":0.35,"c3":0.674,"c4":0.69},{"time":0.6667,"x":-0.78,"y":0.01}],"scale":[{"x":1.073,"y":1.073,"curve":0.32,"c2":0.29,"c3":0.667,"c4":0.67},{"time":0.1,"x":1.035,"y":1.035,"curve":0.381,"c2":0.55,"c3":0.742},{"time":0.2333,"curve":0.25,"c3":0.75},{"time":0.5667,"x":1.096,"y":1.096,"curve":0.284,"c3":0.625,"c4":0.38},{"time":0.6333,"x":1.083,"y":1.083,"curve":0.32,"c2":0.29,"c3":0.655,"c4":0.62},{"time":0.6667,"x":1.073,"y":1.073}]},"tou3":{"rotate":[{"angle":-6.82,"curve":0.306,"c2":0.24,"c3":0.694,"c4":0.76},{"time":0.2,"angle":3.37,"curve":0.375,"c2":0.62,"c3":0.716},{"time":0.2667,"angle":5.16,"curve":0.25,"c3":0.75},{"time":0.6,"angle":-8.63,"curve":0.284,"c3":0.625,"c4":0.38},{"time":0.6667,"angle":-6.82}],"translate":[{"x":-2.05,"y":0.02,"curve":0.363,"c2":0.44,"c3":0.755},{"time":0.2,"curve":0.25,"c3":0.75},{"time":0.5333,"x":-3.25,"y":0.03,"curve":0.258,"c3":0.619,"c4":0.45},{"time":0.6667,"x":-2.05,"y":0.02}],"scale":[{"x":1.096,"y":1.096,"curve":0.245,"c3":0.637,"c4":0.56},{"time":0.2,"x":1.035,"y":1.035,"curve":0.381,"c2":0.55,"c3":0.742},{"time":0.3333,"curve":0.25,"c3":0.75},{"time":0.6667,"x":1.096,"y":1.096}]},"shuijiqiu":{"translate":[{"y":-1.19,"curve":0.363,"c2":0.44,"c3":0.755},{"time":0.2,"y":11.21,"curve":0.25,"c3":0.75},{"time":0.5333,"y":-8.41,"curve":0.258,"c3":0.619,"c4":0.45},{"time":0.6667,"y":-1.19}]},"effect/g2_0":{"scale":[{"x":0,"y":0}]},"effect/g_0":{"scale":[{"x":0,"y":0}]},"effect/g_1":{"scale":[{"x":0,"y":0}]}}},"move":{"bones":{"all2":{"rotate":[{"angle":-17.72}],"translate":[{"y":9.39},{"time":0.1,"y":-3.22},{"time":0.2667,"y":9.39},{"time":0.3667,"y":-3.22},{"time":0.5333,"y":9.39}]},"shenti":{"rotate":[{"angle":1.78,"curve":0.289,"c2":0.18,"c3":0.644,"c4":0.59},{"time":0.1,"angle":0.4,"curve":0.375,"c2":0.5,"c3":0.75},{"time":0.2333,"angle":-1.17,"curve":0.25,"c3":0.75},{"time":0.5,"angle":1.96,"curve":0.299,"c3":0.636,"c4":0.36},{"time":0.5333,"angle":1.78}],"translate":[{"x":-0.05,"y":0.17,"curve":0.382,"c2":0.56,"c3":0.74},{"time":0.1,"x":0.31,"y":-0.95,"curve":0.25,"c3":0.75},{"time":0.3667,"x":-0.76,"y":2.39,"curve":0.244,"c3":0.641,"c4":0.57},{"time":0.5333,"x":-0.05,"y":0.17}]},"shenti2":{"rotate":[{"angle":1.77,"curve":0.364,"c2":0.64,"c3":0.701},{"time":0.0333,"angle":1.96,"curve":0.25,"c3":0.625,"c4":0.5},{"time":0.1667,"angle":0.4,"curve":0.375,"c2":0.5,"c3":0.75},{"time":0.3,"angle":-1.17,"curve":0.244,"c3":0.702,"c4":0.8},{"time":0.5333,"angle":1.77}],"translate":[{"x":0.96,"y":0.25,"curve":0.359,"c2":0.43,"c3":0.756},{"time":0.1667,"x":-0.95,"y":-0.32,"curve":0.25,"c3":0.75},{"time":0.4333,"x":1.93,"y":0.54,"curve":0.26,"c3":0.618,"c4":0.44},{"time":0.5333,"x":0.96,"y":0.25}]},"tou1":{"rotate":[{"angle":0.91,"curve":0.382,"c2":0.56,"c3":0.74},{"time":0.1,"angle":1.96,"curve":0.25,"c3":0.625,"c4":0.5},{"time":0.2333,"angle":0.4,"curve":0.375,"c2":0.5,"c3":0.75},{"time":0.3667,"angle":-1.17,"curve":0.244,"c3":0.641,"c4":0.57},{"time":0.5333,"angle":0.91}],"translate":[{"x":1.22,"y":0.28,"curve":0.298,"c2":0.2,"c3":0.756},{"time":0.2333,"x":-2.35,"y":-0.86,"curve":0.25,"c3":0.75},{"time":0.5,"x":1.46,"y":0.36,"curve":0.299,"c3":0.636,"c4":0.36},{"time":0.5333,"x":1.22,"y":0.28}]},"target1":{"rotate":[{"angle":36.8},{"time":0.0333,"angle":1.33},{"time":0.1,"angle":-0.57},{"time":0.2,"angle":-15.68},{"time":0.2667,"angle":-85.46},{"time":0.3667,"angle":-80.66},{"time":0.4667,"angle":-0.31},{"time":0.5333,"angle":36.8}],"translate":[{"x":34.52,"y":8.41},{"time":0.0333,"x":25.64,"y":-7.36},{"time":0.1,"x":7.88,"y":-12.61},{"time":0.2,"x":-32.34,"y":-8.88},{"time":0.2667,"x":-34.85,"y":16.24},{"time":0.3667,"x":-3.22,"y":14.16},{"time":0.4667,"x":31.26,"y":15.64},{"time":0.5333,"x":34.52,"y":8.41}]},"target2":{"rotate":[{"angle":-95.91},{"time":0.2,"angle":-18.12},{"time":0.2667,"angle":31.62},{"time":0.3,"angle":-0.43},{"time":0.3667,"angle":2.74},{"time":0.4667,"angle":-38.77},{"time":0.5333,"angle":-95.91}],"translate":[{"x":-61.38,"y":15.44},{"time":0.1333,"x":-1.68,"y":5.69},{"time":0.2,"x":1.96,"y":18.12},{"time":0.2667,"x":12.96,"y":12.67},{"time":0.3,"x":4.04,"y":-4.06},{"time":0.3667,"x":-20.99,"y":-12.42},{"time":0.4667,"x":-53.74,"y":-5.69},{"time":0.5333,"x":-61.38,"y":15.44}]},"Zuodabi":{"rotate":[{"angle":-5.4,"curve":0.25,"c3":0.75},{"time":0.2667,"angle":30.42,"curve":0.25,"c3":0.75},{"time":0.5333,"angle":-5.4}]},"Zuoxiaobi":{"rotate":[{"angle":6.63,"curve":0.382,"c2":0.56,"c3":0.74},{"time":0.1,"angle":-5.4,"curve":0.25,"c3":0.75},{"time":0.3667,"angle":30.42,"curve":0.244,"c3":0.641,"c4":0.57},{"time":0.5333,"angle":6.63}]},"Youxiaobi":{"rotate":[{"angle":1.74,"curve":0.25,"c3":0.75},{"time":0.2667,"angle":-43.32,"curve":0.25,"c3":0.75},{"time":0.5333,"angle":1.74}],"translate":[{"curve":0.25,"c3":0.75},{"time":0.2667,"x":2.7,"y":12.98,"curve":0.25,"c3":0.75},{"time":0.5333}]},"Youdabi":{"rotate":[{"angle":4.97,"curve":0.379,"c2":0.6,"c3":0.724},{"time":0.0667,"angle":1.74,"curve":0.25,"c3":0.75},{"time":0.3333,"angle":19.27,"curve":0.242,"c3":0.667,"c4":0.67},{"time":0.5333,"angle":4.97}]},"Youdabi2":{"rotate":[{"angle":10.5,"curve":0.375,"c2":0.5,"c3":0.75},{"time":0.1333,"angle":1.74,"curve":0.25,"c3":0.75},{"time":0.4,"angle":19.27,"curve":0.25,"c3":0.625,"c4":0.5},{"time":0.5333,"angle":10.5}]},"qunbaoZuo":{"rotate":[{"angle":3.32,"curve":0.379,"c2":0.6,"c3":0.724},{"time":0.0667,"angle":6.43,"curve":0.25,"c3":0.75},{"time":0.3333,"angle":-10.43,"curve":0.242,"c3":0.667,"c4":0.67},{"time":0.5333,"angle":3.32}]},"qunbaoZuo2":{"rotate":[{"angle":-2.19,"curve":0.343,"c2":0.36,"c3":0.686,"c4":0.73},{"time":0.0667,"angle":4.01,"curve":0.379,"c2":0.6,"c3":0.724},{"time":0.1333,"angle":7.68,"curve":0.25,"c3":0.75},{"time":0.4,"angle":-12.2,"curve":0.25,"c3":0.625,"c4":0.5},{"time":0.5333,"angle":-2.19}]},"qunbaoZuo3":{"rotate":[{"angle":-10.64,"curve":0.314,"c2":0.27,"c3":0.657,"c4":0.64},{"time":0.0667,"angle":-3.24,"curve":0.375,"c2":0.5,"c3":0.75},{"time":0.2,"angle":8.41,"curve":0.25,"c3":0.75},{"time":0.4667,"angle":-14.9,"curve":0.276,"c3":0.621,"c4":0.4},{"time":0.5333,"angle":-10.64}]},"qunbaoZuo4":{"rotate":[{"angle":-16.54,"curve":0.276,"c3":0.621,"c4":0.4},{"time":0.0667,"angle":-11.94,"curve":0.333,"c2":0.33,"c3":0.758},{"time":0.2667,"angle":8.41,"curve":0.25,"c3":0.75},{"time":0.5333,"angle":-16.54}]},"qunbaiYou":{"rotate":[{"angle":3.03,"curve":0.379,"c2":0.6,"c3":0.724},{"time":0.0667,"angle":-4.02,"curve":0.25,"c3":0.75},{"time":0.3333,"angle":34.21,"curve":0.242,"c3":0.667,"c4":0.67},{"time":0.5333,"angle":3.03}]},"qunbaiYou2":{"rotate":[{"angle":4.78,"curve":0.343,"c2":0.36,"c3":0.686,"c4":0.73},{"time":0.0667,"angle":-1.65,"curve":0.379,"c2":0.6,"c3":0.724},{"time":0.1333,"angle":-5.44,"curve":0.25,"c3":0.75},{"time":0.4,"angle":15.13,"curve":0.25,"c3":0.625,"c4":0.5},{"time":0.5333,"angle":4.78}]},"qunbaiYou3":{"rotate":[{"angle":16.19,"curve":0.314,"c2":0.27,"c3":0.657,"c4":0.64},{"time":0.0667,"angle":6.94,"curve":0.375,"c2":0.5,"c3":0.75},{"time":0.2,"angle":-7.66,"curve":0.25,"c3":0.75},{"time":0.4667,"angle":21.53,"curve":0.276,"c3":0.621,"c4":0.4},{"time":0.5333,"angle":16.19}]},"qunbaiYou4":{"rotate":[{"angle":29.36,"curve":0.276,"c3":0.621,"c4":0.4},{"time":0.0667,"angle":22.01,"curve":0.333,"c2":0.33,"c3":0.758},{"time":0.2667,"angle":-10.52,"curve":0.25,"c3":0.75},{"time":0.5333,"angle":29.36}]},"yaodai":{"rotate":[{"angle":0.55,"curve":0.345,"c2":0.38,"c3":0.68,"c4":0.71},{"time":0.0333,"angle":0.8,"curve":0.375,"c2":0.62,"c3":0.716},{"time":0.0667,"angle":1.1,"curve":0.25,"c3":0.75},{"time":0.3333,"angle":-1.19,"curve":0.243,"c3":0.655,"c4":0.63},{"time":0.5333,"angle":0.55}],"translate":[{"y":1.28,"curve":0.36,"c2":0.64,"c3":0.695},{"time":0.0333,"y":1.51,"curve":0.25,"c3":0.75},{"time":0.3,"y":-4.03,"curve":0.245,"c3":0.711,"c4":0.83},{"time":0.5333,"y":1.28}]},"toufa1b":{"rotate":[{"angle":8.27,"curve":0.314,"c2":0.27,"c3":0.686,"c4":0.73},{"time":0.1333,"angle":-9.77,"curve":0.379,"c2":0.6,"c3":0.724},{"time":0.2,"angle":-15.06,"curve":0.25,"c3":0.75},{"time":0.4667,"angle":13.6,"curve":0.276,"c3":0.621,"c4":0.4},{"time":0.5333,"angle":8.27}]},"toufa1c":{"rotate":[{"angle":13.6,"curve":0.25,"c3":0.625,"c4":0.5},{"time":0.1333,"angle":-0.73,"curve":0.375,"c2":0.5,"c3":0.75},{"time":0.2667,"angle":-15.06,"curve":0.25,"c3":0.75},{"time":0.5333,"angle":13.6}]},"toufa1d":{"rotate":[{"angle":8.32,"curve":0.379,"c2":0.6,"c3":0.724},{"time":0.0667,"angle":13.6,"curve":0.276,"c3":0.621,"c4":0.4},{"time":0.1333,"angle":8.32,"curve":0.333,"c2":0.33,"c3":0.758},{"time":0.3333,"angle":-15.06,"curve":0.242,"c3":0.667,"c4":0.67},{"time":0.5333,"angle":8.32}]},"toufa2":{"rotate":[{"angle":-6.03,"curve":0.25,"c3":0.75},{"time":0.2667,"angle":12.7,"curve":0.25,"c3":0.75},{"time":0.5333,"angle":-6.03}]},"toufa2b":{"rotate":[{"angle":-2.57,"curve":0.379,"c2":0.6,"c3":0.724},{"time":0.0667,"angle":-6.03,"curve":0.25,"c3":0.75},{"time":0.3333,"angle":12.7,"curve":0.242,"c3":0.667,"c4":0.67},{"time":0.5333,"angle":-2.57}]},"toufa2c":{"rotate":[{"angle":3.34,"curve":0.375,"c2":0.5,"c3":0.75},{"time":0.1333,"angle":-6.03,"curve":0.25,"c3":0.75},{"time":0.4,"angle":12.7,"curve":0.25,"c3":0.625,"c4":0.5},{"time":0.5333,"angle":3.34}]},"toufa2d":{"rotate":[{"angle":9.25,"curve":0.333,"c2":0.33,"c3":0.758},{"time":0.2,"angle":-6.03,"curve":0.25,"c3":0.75},{"time":0.4667,"angle":12.7,"curve":0.276,"c3":0.621,"c4":0.4},{"time":0.5333,"angle":9.25}]},"toufa1":{"rotate":[{"angle":0.1,"curve":0.375,"c2":0.5,"c3":0.75},{"time":0.1333,"angle":-1.99,"curve":0.25,"c3":0.75},{"time":0.4,"angle":2.19,"curve":0.25,"c3":0.625,"c4":0.5},{"time":0.5333,"angle":0.1}]},"tou4":{"rotate":[{"angle":-1.68,"curve":0.347,"c2":0.38,"c3":0.694,"c4":0.76},{"time":0.0667,"angle":3.37,"curve":0.375,"c2":0.62,"c3":0.716},{"time":0.1333,"angle":5.16,"curve":0.25,"c3":0.75},{"time":0.4,"angle":-8.63,"curve":0.258,"c3":0.619,"c4":0.45},{"time":0.5,"angle":-3.49,"curve":0.33,"c2":0.32,"c3":0.665,"c4":0.66},{"time":0.5333,"angle":-1.68}],"translate":[{"x":-0.78,"y":0.01,"curve":0.382,"c2":0.58,"c3":0.731},{"time":0.0667,"curve":0.25,"c3":0.75},{"time":0.3333,"x":-3.25,"y":0.03,"curve":0.245,"c3":0.637,"c4":0.56},{"time":0.5,"x":-1.2,"y":0.01,"curve":0.339,"c2":0.35,"c3":0.674,"c4":0.69},{"time":0.5333,"x":-0.78,"y":0.01}],"scale":[{"x":1.073,"y":1.073,"curve":0.32,"c2":0.29,"c3":0.667,"c4":0.67},{"time":0.0667,"x":1.035,"y":1.035,"curve":0.381,"c2":0.55,"c3":0.742},{"time":0.2,"curve":0.25,"c3":0.75},{"time":0.4333,"x":1.096,"y":1.096,"curve":0.284,"c3":0.625,"c4":0.38},{"time":0.5,"x":1.083,"y":1.083,"curve":0.32,"c2":0.29,"c3":0.655,"c4":0.62},{"time":0.5333,"x":1.073,"y":1.073}]},"tou2":{"rotate":[{"angle":-6.82,"curve":0.306,"c2":0.24,"c3":0.694,"c4":0.76},{"time":0.1667,"angle":3.37,"curve":0.375,"c2":0.62,"c3":0.716},{"time":0.2,"angle":5.16,"curve":0.25,"c3":0.75},{"time":0.4667,"angle":-8.63,"curve":0.284,"c3":0.625,"c4":0.38},{"time":0.5333,"angle":-6.82}],"translate":[{"x":-2.05,"y":0.02,"curve":0.363,"c2":0.44,"c3":0.755},{"time":0.1667,"curve":0.25,"c3":0.75},{"time":0.4333,"x":-3.25,"y":0.03,"curve":0.258,"c3":0.619,"c4":0.45},{"time":0.5333,"x":-2.05,"y":0.02}],"scale":[{"x":1.096,"y":1.096,"curve":0.245,"c3":0.637,"c4":0.56},{"time":0.1667,"x":1.035,"y":1.035,"curve":0.381,"c2":0.55,"c3":0.742},{"time":0.2667,"curve":0.25,"c3":0.75},{"time":0.5333,"x":1.096,"y":1.096}]},"tou3":{"rotate":[{"angle":-6.82,"curve":0.306,"c2":0.24,"c3":0.694,"c4":0.76},{"time":0.1667,"angle":3.37,"curve":0.375,"c2":0.62,"c3":0.716},{"time":0.2,"angle":5.16,"curve":0.25,"c3":0.75},{"time":0.4667,"angle":-8.63,"curve":0.284,"c3":0.625,"c4":0.38},{"time":0.5333,"angle":-6.82}],"translate":[{"x":-2.05,"y":0.02,"curve":0.363,"c2":0.44,"c3":0.755},{"time":0.1667,"curve":0.25,"c3":0.75},{"time":0.4333,"x":-3.25,"y":0.03,"curve":0.258,"c3":0.619,"c4":0.45},{"time":0.5333,"x":-2.05,"y":0.02}],"scale":[{"x":1.096,"y":1.096,"curve":0.245,"c3":0.637,"c4":0.56},{"time":0.1667,"x":1.035,"y":1.035,"curve":0.381,"c2":0.55,"c3":0.742},{"time":0.2667,"curve":0.25,"c3":0.75},{"time":0.5333,"x":1.096,"y":1.096}]},"dangbu":{"rotate":[{"angle":-0.83,"curve":0.375,"c2":0.5,"c3":0.75},{"time":0.1333,"angle":-7.58,"curve":0.25,"c3":0.75},{"time":0.4,"angle":5.91,"curve":0.25,"c3":0.625,"c4":0.5},{"time":0.5333,"angle":-0.83}]},"dangbu2":{"rotate":[{"angle":6.48,"curve":0.314,"c2":0.27,"c3":0.686,"c4":0.73},{"time":0.1333,"angle":-5.82,"curve":0.379,"c2":0.6,"c3":0.724},{"time":0.2,"angle":-9.43,"curve":0.25,"c3":0.75},{"time":0.4667,"angle":10.11,"curve":0.276,"c3":0.621,"c4":0.4},{"time":0.5333,"angle":6.48}]},"dangbu3":{"rotate":[{"angle":12.78,"curve":0.25,"c3":0.625,"c4":0.5},{"time":0.1333,"angle":-1.13,"curve":0.375,"c2":0.5,"c3":0.75},{"time":0.2667,"angle":-15.05,"curve":0.25,"c3":0.75},{"time":0.5333,"angle":12.78}]},"dangbu4":{"rotate":[{"angle":11.91,"curve":0.379,"c2":0.6,"c3":0.724},{"time":0.0667,"angle":18.42,"curve":0.276,"c3":0.621,"c4":0.4},{"time":0.1333,"angle":11.91,"curve":0.333,"c2":0.33,"c3":0.758},{"time":0.3333,"angle":-16.85,"curve":0.242,"c3":0.667,"c4":0.67},{"time":0.5333,"angle":11.91}]},"shuijiqiu":{"rotate":[{"angle":-3.64,"curve":0.364,"c2":0.64,"c3":0.701},{"time":0.0333,"curve":0.25,"c3":0.75},{"time":0.3,"angle":-58.05,"curve":0.244,"c3":0.702,"c4":0.8},{"time":0.5333,"angle":-3.64}],"translate":[{"y":-4.27,"curve":0.379,"c2":0.6,"c3":0.724},{"time":0.0333,"curve":0.25,"c3":0.75},{"time":0.1667,"y":-23.14,"curve":0.25,"c3":0.75},{"time":0.3,"curve":0.25,"c3":0.75},{"time":0.4333,"y":-23.14,"curve":0.242,"c3":0.667,"c4":0.67},{"time":0.5333,"y":-4.27}]},"effect/g_0":{"scale":[{"x":0,"y":0}]},"effect/g2_0":{"scale":[{"x":0,"y":0}]},"effect/g_1":{"scale":[{"x":0,"y":0}]}}},"skill":{"slots":{"effect/g2_0":{"color":[{"color":"ffffff00"},{"time":0.3333,"color":"ffffffff","curve":"stepped"},{"time":0.6333,"color":"ffffffff"},{"time":0.8333,"color":"ffffff00"}]},"effect/g_0":{"color":[{"color":"ffffff00","curve":"stepped"},{"time":0.1667,"color":"ffffff00"},{"time":0.2,"color":"ffffffff","curve":"stepped"},{"time":0.3333,"color":"ffffffff"},{"time":0.5333,"color":"ffffff00"}]},"effect/g_1":{"color":[{"color":"ffffff00","curve":"stepped"},{"time":0.4333,"color":"ffffff00"},{"time":0.4667,"color":"ffffffff","curve":"stepped"},{"time":0.6,"color":"ffffffff"},{"time":0.8,"color":"ffffff00"}]}},"bones":{"all2":{"rotate":[{"curve":0.25,"c3":0.75},{"time":0.1333,"angle":-1.7,"curve":0.25,"c3":0.75},{"time":0.2667,"angle":0.95,"curve":0.25,"c3":0.75},{"time":0.4,"angle":-2.39,"curve":0.25,"c3":0.75},{"time":0.5333,"angle":0.63,"curve":0.25,"c3":0.75},{"time":0.6667,"angle":-2.43,"curve":0.25,"c3":0.75},{"time":0.8333}],"translate":[{"curve":0.25,"c3":0.75},{"time":0.0667,"y":-6.46,"curve":"stepped"},{"time":0.1333,"y":-6.46,"curve":0.25,"c3":0.75},{"time":0.2,"y":14.88,"curve":0.25,"c3":0.75},{"time":0.2667,"y":9.46,"curve":0.25,"c3":0.75},{"time":0.3333,"y":9.32,"curve":0.25,"c3":0.75},{"time":0.4,"y":9.46,"curve":0.25,"c3":0.75},{"time":0.4667,"y":9.32,"curve":0.25,"c3":0.75},{"time":0.5333,"y":9.46,"curve":0.25,"c3":0.75},{"time":0.6,"y":9.32,"curve":0.25,"c3":0.75},{"time":0.6667,"y":9.46,"curve":0.25,"c3":0.75},{"time":0.8333}]},"shenti":{"rotate":[{"curve":0.25,"c3":0.75},{"time":0.0667,"angle":-1.06,"curve":"stepped"},{"time":0.1333,"angle":-1.06,"curve":0.25,"c3":0.75},{"time":0.2,"angle":0.51,"curve":0.25,"c3":0.75},{"time":0.2667,"angle":-0.37,"curve":0.25,"c3":0.75},{"time":0.3333,"angle":0.51,"curve":0.25,"c3":0.75},{"time":0.4,"angle":-0.37,"curve":0.25,"c3":0.75},{"time":0.4667,"angle":0.51,"curve":0.25,"c3":0.75},{"time":0.5333,"angle":-0.37,"curve":0.25,"c3":0.75},{"time":0.6,"angle":0.51,"curve":0.25,"c3":0.75},{"time":0.6667,"angle":-1.06,"curve":0.25,"c3":0.75},{"time":0.8333}],"translate":[{"curve":0.25,"c3":0.75},{"time":0.0667,"y":-0.53,"curve":0.25,"c3":0.75},{"time":0.1333,"x":0.01,"y":-1.23,"curve":0.25,"c3":0.75},{"time":0.2,"y":3.2,"curve":0.25,"c3":0.75},{"time":0.2667,"y":1.81,"curve":0.25,"c3":0.75},{"time":0.3333,"y":4.6,"curve":0.25,"c3":0.75},{"time":0.4,"y":1.81,"curve":0.25,"c3":0.75},{"time":0.4667,"y":3.2,"curve":0.25,"c3":0.75},{"time":0.5333,"y":1.81,"curve":0.25,"c3":0.75},{"time":0.6,"y":3.2,"curve":"stepped"},{"time":0.6667,"y":3.2,"curve":0.25,"c3":0.75},{"time":0.8333}]},"shenti2":{"rotate":[{"curve":0.25,"c3":0.75},{"time":0.0667,"angle":-1.06,"curve":"stepped"},{"time":0.1333,"angle":-1.06,"curve":0.25,"c3":0.75},{"time":0.2,"angle":0.51,"curve":0.25,"c3":0.75},{"time":0.3,"angle":-0.37,"curve":0.25,"c3":0.75},{"time":0.3667,"angle":0.51,"curve":0.25,"c3":0.75},{"time":0.4333,"angle":-0.37,"curve":0.25,"c3":0.75},{"time":0.5,"angle":0.51,"curve":0.25,"c3":0.75},{"time":0.5667,"angle":-0.37,"curve":0.25,"c3":0.75},{"time":0.6333,"angle":0.51,"curve":0.25,"c3":0.75},{"time":0.7,"angle":-1.06,"curve":0.25,"c3":0.75},{"time":0.8333}],"translate":[{"curve":0.25,"c3":0.75},{"time":0.0667,"x":-2.67,"curve":0.25,"c3":0.75},{"time":0.1333,"x":-3.02,"y":-0.01,"curve":0.25,"c3":0.75},{"time":0.2,"x":1.6,"curve":0.25,"c3":0.75},{"time":0.3,"x":4.04,"curve":0.25,"c3":0.75},{"time":0.3667,"x":1.6,"curve":0.25,"c3":0.75},{"time":0.4333,"x":4.04,"curve":0.25,"c3":0.75},{"time":0.5,"x":1.6,"curve":0.25,"c3":0.75},{"time":0.5667,"x":4.04,"curve":0.25,"c3":0.75},{"time":0.6333,"x":0.56,"curve":0.25,"c3":0.75},{"time":0.7,"x":1.6,"curve":0.25,"c3":0.75},{"time":0.8333}]},"tou1":{"rotate":[{"curve":0.25,"c3":0.75},{"time":0.0667,"angle":-1.06,"curve":"stepped"},{"time":0.1333,"angle":-1.06,"curve":0.25,"c3":0.75},{"time":0.2333,"angle":0.51,"curve":0.25,"c3":0.75},{"time":0.3,"angle":-0.37,"curve":0.25,"c3":0.75},{"time":0.3667,"angle":0.51,"curve":0.25,"c3":0.75},{"time":0.4333,"angle":-0.37,"curve":0.25,"c3":0.75},{"time":0.5,"angle":0.51,"curve":0.25,"c3":0.75},{"time":0.5667,"angle":-0.37,"curve":0.25,"c3":0.75},{"time":0.6333,"angle":0.51,"curve":0.25,"c3":0.75},{"time":0.7,"angle":-1.06,"curve":0.25,"c3":0.75},{"time":0.8333}],"translate":[{"curve":0.25,"c3":0.75},{"time":0.0667,"x":-3.2,"curve":"stepped"},{"time":0.1333,"x":-3.2,"curve":0.25,"c3":0.75},{"time":0.2333,"x":2.14,"curve":0.25,"c3":0.75},{"time":0.3,"x":-1.69,"curve":0.25,"c3":0.75},{"time":0.3667,"x":2.14,"curve":0.25,"c3":0.75},{"time":0.4333,"x":-1.69,"curve":0.25,"c3":0.75},{"time":0.5,"x":2.14,"curve":0.25,"c3":0.75},{"time":0.5667,"x":-1.69,"curve":0.25,"c3":0.75},{"time":0.6333,"x":0.74,"curve":0.25,"c3":0.75},{"time":0.7,"x":2.14,"curve":0.25,"c3":0.75},{"time":0.8333}]},"Youxiaobi":{"rotate":[{"curve":0.25,"c3":0.75},{"time":0.1333,"angle":-50.36,"curve":0.25,"c3":0.75},{"time":0.2,"angle":20.62,"curve":"stepped"},{"time":0.6667,"angle":20.62,"curve":0.25,"c3":0.75},{"time":0.8333}],"translate":[{"curve":0.25,"c3":0.75},{"time":0.1333,"x":-0.39,"y":6.98,"curve":0.25,"c3":0.75},{"time":0.2,"x":9.92,"y":-18.26,"curve":"stepped"},{"time":0.6667,"x":9.92,"y":-18.26,"curve":0.25,"c3":0.75},{"time":0.8333}]},"Youdabi2":{"rotate":[{"curve":0.25,"c3":0.75},{"time":0.1333,"angle":37.05,"curve":0.25,"c3":0.75},{"time":0.2,"angle":-44.35,"curve":"stepped"},{"time":0.6667,"angle":-44.35,"curve":0.25,"c3":0.75},{"time":0.8333}]},"Youdabi":{"rotate":[{"curve":0.25,"c3":0.75},{"time":0.1333,"angle":8.56,"curve":0.25,"c3":0.75},{"time":0.2,"angle":2.42,"curve":"stepped"},{"time":0.6667,"angle":2.42,"curve":0.25,"c3":0.75},{"time":0.8333}]},"shuijiqiu":{"translate":[{"curve":0.25,"c3":0.75},{"time":0.1333,"x":-15.91,"y":-62.32,"curve":0.25,"c3":0.75},{"time":0.2,"x":5.3,"y":86.85,"curve":0.25,"c3":0.75},{"time":0.2667,"x":5.3,"y":76.24,"curve":0.25,"c3":0.75},{"time":0.3333,"x":5.3,"y":86.85,"curve":0.25,"c3":0.75},{"time":0.4,"x":5.3,"y":76.24,"curve":0.25,"c3":0.75},{"time":0.4667,"x":5.3,"y":86.85,"curve":0.25,"c3":0.75},{"time":0.5333,"x":5.3,"y":76.24,"curve":0.25,"c3":0.75},{"time":0.6,"x":5.3,"y":86.85,"curve":0.25,"c3":0.75},{"time":0.6667,"x":5.3,"y":76.24,"curve":0.25,"c3":0.75},{"time":0.8333}],"scale":[{"time":0.1333,"curve":0.25,"c3":0.75},{"time":0.2,"x":1.2,"y":1.2,"curve":0.25,"c3":0.75},{"time":0.3333,"x":1.1,"y":1.1,"curve":0.25,"c3":0.75},{"time":0.4667,"x":1.2,"y":1.2,"curve":0.25,"c3":0.75},{"time":0.6,"x":1.1,"y":1.1,"curve":0.25,"c3":0.75},{"time":0.6667,"x":1.2,"y":1.2,"curve":0.25,"c3":0.75},{"time":0.7333}]},"yaodai":{"rotate":[{"curve":0.25,"c3":0.75},{"time":0.0667,"angle":-4.5,"curve":0.25,"c3":0.75},{"time":0.1333,"angle":-4.59,"curve":0.25,"c3":0.75},{"time":0.2,"angle":4.09,"curve":0.25,"c3":0.75},{"time":0.2667,"angle":2.24,"curve":0.25,"c3":0.75},{"time":0.3333,"angle":2.04,"curve":0.25,"c3":0.75},{"time":0.4,"angle":0.44,"curve":0.25,"c3":0.75},{"time":0.4667,"angle":3.48,"curve":0.25,"c3":0.75},{"time":0.5333,"angle":3.35,"curve":0.25,"c3":0.75},{"time":0.6,"angle":3.23,"curve":0.25,"c3":0.75},{"time":0.6667,"angle":4.57,"curve":0.25,"c3":0.75},{"time":0.8333}],"translate":[{"curve":0.25,"c3":0.75},{"time":0.0667,"y":-0.53,"curve":0.25,"c3":0.75},{"time":0.1333,"x":0.01,"y":-1.23,"curve":0.25,"c3":0.75},{"time":0.2,"y":3.2,"curve":0.25,"c3":0.75},{"time":0.2667,"y":1.81,"curve":0.25,"c3":0.75},{"time":0.3333,"y":4.6,"curve":0.25,"c3":0.75},{"time":0.4,"y":1.81,"curve":0.25,"c3":0.75},{"time":0.4667,"y":3.2,"curve":0.25,"c3":0.75},{"time":0.5333,"y":1.81,"curve":0.25,"c3":0.75},{"time":0.6,"y":3.2,"curve":"stepped"},{"time":0.6667,"y":3.2,"curve":0.25,"c3":0.75},{"time":0.8333}]},"Zuodabi":{"rotate":[{"curve":0.25,"c3":0.75},{"time":0.1333,"angle":10.5,"curve":0.25,"c3":0.75},{"time":0.2,"angle":-12.78,"curve":0.25,"c3":0.75},{"time":0.3,"angle":-6.57,"curve":0.25,"c3":0.75},{"time":0.4333,"angle":-12.78,"curve":0.25,"c3":0.75},{"time":0.5333,"angle":-6.57,"curve":0.25,"c3":0.75},{"time":0.6667,"angle":-12.78,"curve":0.25,"c3":0.75},{"time":0.8333}]},"Zuoxiaobi":{"rotate":[{"curve":0.25,"c3":0.75},{"time":0.1333,"angle":10.5,"curve":0.25,"c3":0.75},{"time":0.2,"angle":-7.34,"curve":0.25,"c3":0.75},{"time":0.3333,"angle":-1.12,"curve":0.25,"c3":0.75},{"time":0.4667,"angle":-7.34,"curve":0.25,"c3":0.75},{"time":0.5667,"angle":-1.12,"curve":0.25,"c3":0.75},{"time":0.6667,"angle":-7.34,"curve":0.25,"c3":0.75},{"time":0.8333}]},"qunbaoZuo":{"rotate":[{"curve":0.25,"c3":0.75},{"time":0.1333,"angle":-6.48,"curve":0.25,"c3":0.75},{"time":0.2,"curve":0.25,"c3":0.75},{"time":0.2667,"angle":-15.77,"curve":0.25,"c3":0.75},{"time":0.4,"curve":0.25,"c3":0.75},{"time":0.5333,"angle":-15.77,"curve":0.25,"c3":0.75},{"time":0.6667}]},"qunbaoZuo2":{"rotate":[{"curve":0.25,"c3":0.75},{"time":0.1333,"angle":-6.48,"curve":0.25,"c3":0.75},{"time":0.2,"curve":0.25,"c3":0.75},{"time":0.3,"angle":-15.77,"curve":0.25,"c3":0.75},{"time":0.4333,"curve":0.25,"c3":0.75},{"time":0.5667,"angle":-15.77,"curve":0.25,"c3":0.75},{"time":0.7,"angle":4.25,"curve":0.25,"c3":0.75},{"time":0.8333}]},"qunbaoZuo3":{"rotate":[{"curve":0.25,"c3":0.75},{"time":0.1333,"angle":-6.48,"curve":0.25,"c3":0.75},{"time":0.2,"curve":0.25,"c3":0.75},{"time":0.3333,"angle":-15.77,"curve":0.25,"c3":0.75},{"time":0.4667,"curve":0.25,"c3":0.75},{"time":0.6,"angle":-15.77,"curve":0.25,"c3":0.75},{"time":0.7333,"angle":4.25,"curve":0.25,"c3":0.75},{"time":0.8333}]},"qunbaoZuo4":{"rotate":[{"curve":0.25,"c3":0.75},{"time":0.1333,"angle":-6.48,"curve":0.25,"c3":0.75},{"time":0.2,"curve":0.25,"c3":0.75},{"time":0.3667,"angle":-15.77,"curve":0.25,"c3":0.75},{"time":0.5,"curve":0.25,"c3":0.75},{"time":0.6333,"angle":-15.77,"curve":0.25,"c3":0.75},{"time":0.7667,"angle":4.25,"curve":0.25,"c3":0.75},{"time":0.8333}]},"qunbaiYou4":{"rotate":[{"curve":0.25,"c3":0.75},{"time":0.1333,"angle":7.56,"curve":0.25,"c3":0.75},{"time":0.2,"angle":-3.28,"curve":0.25,"c3":0.75},{"time":0.3333,"angle":9.34,"curve":0.25,"c3":0.75},{"time":0.4667,"angle":-3.28,"curve":0.25,"c3":0.75},{"time":0.6,"angle":9.34,"curve":0.25,"c3":0.75},{"time":0.7333,"angle":-5.39,"curve":0.25,"c3":0.75},{"time":0.8333}]},"qunbaiYou3":{"rotate":[{"curve":0.25,"c3":0.75},{"time":0.1333,"angle":7.56,"curve":0.25,"c3":0.75},{"time":0.2,"angle":-3.28,"curve":0.25,"c3":0.75},{"time":0.2667,"angle":9.34,"curve":0.25,"c3":0.75},{"time":0.4,"angle":-3.28,"curve":0.25,"c3":0.75},{"time":0.5333,"angle":9.34,"curve":0.25,"c3":0.75},{"time":0.6667,"angle":-5.39,"curve":0.25,"c3":0.75},{"time":0.8333}]},"qunbaiYou2":{"rotate":[{"curve":0.25,"c3":0.75},{"time":0.1333,"angle":7.56,"curve":0.25,"c3":0.75},{"time":0.2,"angle":-3.28,"curve":0.25,"c3":0.75},{"time":0.3,"angle":9.34,"curve":0.25,"c3":0.75},{"time":0.4333,"angle":-3.28,"curve":0.25,"c3":0.75},{"time":0.5667,"angle":9.34,"curve":0.25,"c3":0.75},{"time":0.7,"angle":-5.39,"curve":0.25,"c3":0.75},{"time":0.8333}]},"qunbaiYou":{"rotate":[{"curve":0.25,"c3":0.75},{"time":0.1333,"angle":7.56,"curve":0.25,"c3":0.75},{"time":0.2,"angle":-3.28,"curve":0.25,"c3":0.75},{"time":0.2667,"angle":9.34,"curve":0.25,"c3":0.75},{"time":0.4,"angle":-3.28,"curve":0.25,"c3":0.75},{"time":0.5333,"angle":9.34,"curve":0.25,"c3":0.75},{"time":0.6667}]},"dangbu4":{"rotate":[{"curve":0.25,"c3":0.75},{"time":0.1333,"angle":4.33,"curve":0.25,"c3":0.75},{"time":0.2,"angle":-6.32,"curve":0.25,"c3":0.75},{"time":0.3333,"angle":4.33,"curve":0.25,"c3":0.75},{"time":0.4667,"angle":-6.32,"curve":0.25,"c3":0.75},{"time":0.6,"angle":4.33,"curve":0.25,"c3":0.75},{"time":0.7333,"angle":-6.32,"curve":0.25,"c3":0.75},{"time":0.8333}]},"dangbu3":{"rotate":[{"curve":0.25,"c3":0.75},{"time":0.1333,"angle":4.33,"curve":0.25,"c3":0.75},{"time":0.2,"angle":-6.32,"curve":0.25,"c3":0.75},{"time":0.3333,"angle":4.33,"curve":0.25,"c3":0.75},{"time":0.4667,"angle":-6.32,"curve":0.25,"c3":0.75},{"time":0.6,"angle":4.33,"curve":0.25,"c3":0.75},{"time":0.7333,"angle":-6.32,"curve":0.25,"c3":0.75},{"time":0.8333}]},"dangbu2":{"rotate":[{"curve":0.25,"c3":0.75},{"time":0.1333,"angle":4.33,"curve":0.25,"c3":0.75},{"time":0.2333,"angle":-6.32,"curve":0.25,"c3":0.75},{"time":0.3667,"angle":4.33,"curve":0.25,"c3":0.75},{"time":0.5,"angle":-6.32,"curve":0.25,"c3":0.75},{"time":0.6333,"angle":4.33,"curve":0.25,"c3":0.75},{"time":0.7667,"angle":-6.32,"curve":0.25,"c3":0.75},{"time":0.8333}]},"dangbu":{"rotate":[{"curve":0.25,"c3":0.75},{"time":0.1333,"angle":4.33,"curve":0.25,"c3":0.75},{"time":0.2,"angle":-6.32,"curve":0.25,"c3":0.75},{"time":0.3333,"angle":4.33,"curve":0.25,"c3":0.75},{"time":0.4667,"angle":-6.32,"curve":0.25,"c3":0.75},{"time":0.6,"angle":4.33,"curve":0.25,"c3":0.75},{"time":0.7333,"angle":-6.32,"curve":0.25,"c3":0.75},{"time":0.8333}]},"toufa1b":{"rotate":[{"angle":-7.88,"curve":0.25,"c3":0.75},{"time":0.2,"angle":9.46,"curve":0.25,"c3":0.75},{"time":0.4333,"angle":-7.88,"curve":0.25,"c3":0.75},{"time":0.6333,"angle":9.46,"curve":0.25,"c3":0.75},{"time":0.8333,"angle":-7.88}]},"toufa1d":{"rotate":[{"angle":12.5,"curve":0.32,"c2":0.29,"c3":0.757},{"time":0.1667,"angle":-17.74,"curve":0.25,"c3":0.75},{"time":0.3667,"angle":17.03,"curve":0.284,"c3":0.625,"c4":0.38},{"time":0.4333,"angle":12.5,"curve":0.32,"c2":0.29,"c3":0.757},{"time":0.6,"angle":-17.74,"curve":0.25,"c3":0.75},{"time":0.8,"angle":17.03,"curve":0.284,"c3":0.625,"c4":0.38},{"time":0.8333,"angle":12.5}]},"toufa1c":{"rotate":[{"angle":-4.57,"curve":0.381,"c2":0.55,"c3":0.742},{"time":0.1,"angle":-14.19,"curve":0.25,"c3":0.75},{"time":0.3,"angle":11.97,"curve":0.245,"c3":0.637,"c4":0.56},{"time":0.4333,"angle":-4.57,"curve":0.381,"c2":0.55,"c3":0.742},{"time":0.5,"angle":-14.19,"curve":0.25,"c3":0.75},{"time":0.7,"angle":11.97,"curve":0.245,"c3":0.637,"c4":0.56},{"time":0.8333,"angle":-4.57}]},"toufa2":{"rotate":[{"angle":3.56,"curve":0.25,"c3":0.75},{"time":0.2,"angle":-5.03,"curve":0.25,"c3":0.75},{"time":0.4333,"angle":3.56,"curve":0.25,"c3":0.75},{"time":0.6333,"angle":-5.03,"curve":0.25,"c3":0.75},{"time":0.8333,"angle":3.56}]},"toufa2b":{"rotate":[{"angle":1.45,"curve":0.381,"c2":0.55,"c3":0.742},{"time":0.1,"angle":5.93,"curve":0.25,"c3":0.75},{"time":0.3,"angle":-6.23,"curve":0.245,"c3":0.637,"c4":0.56},{"time":0.4333,"angle":1.45,"curve":0.381,"c2":0.55,"c3":0.742},{"time":0.5,"angle":5.93,"curve":0.25,"c3":0.75},{"time":0.7,"angle":-6.23,"curve":0.245,"c3":0.637,"c4":0.56},{"time":0.8333,"angle":1.45}]},"toufa2c":{"rotate":[{"angle":-7.3,"curve":0.32,"c2":0.29,"c3":0.757},{"time":0.1667,"angle":9.26,"curve":0.25,"c3":0.75},{"time":0.3667,"angle":-9.77,"curve":0.284,"c3":0.625,"c4":0.38},{"time":0.4333,"angle":-7.3,"curve":0.32,"c2":0.29,"c3":0.757},{"time":0.6,"angle":9.26,"curve":0.25,"c3":0.75},{"time":0.8,"angle":-9.77,"curve":0.284,"c3":0.625,"c4":0.38},{"time":0.8333,"angle":-7.3}]},"toufa2d":{"rotate":[{"angle":-7.3,"curve":0.375,"c2":0.62,"c3":0.716},{"time":0.0333,"angle":-9.77,"curve":0.25,"c3":0.75},{"time":0.2667,"angle":9.26,"curve":0.243,"c3":0.68,"c4":0.71},{"time":0.4333,"angle":-7.3,"curve":0.375,"c2":0.62,"c3":0.716},{"time":0.4667,"angle":-9.77,"curve":0.25,"c3":0.75},{"time":0.6667,"angle":9.26,"curve":0.243,"c3":0.68,"c4":0.71},{"time":0.8333,"angle":-7.3}]},"effect/g_0":{"scale":[{"x":0.5,"y":0.5,"curve":"stepped"},{"time":0.2,"x":0.5,"y":0.5},{"time":0.5,"x":1.545,"y":1.545}]},"effect/g_1":{"scale":[{"x":0.5,"y":0.5,"curve":"stepped"},{"time":0.4667,"x":0.5,"y":0.5},{"time":0.7667,"x":1.545,"y":1.545}]}}}}},[0]]],0,0,[0],[-1],[0]]