[1,["ecpdLyjvZBwrvm+cedCcQy","f1AYb3szpNRqVd1exsjxyv","ffwxmh1r5NeZ0+GVRTjiKA","173NaCU0FG6oztERLDq4k6","6a90W7Xw9P2446e0kGvfbs","ebS/bAPsdDUp4RPubXYnmi","0e7R6/cRpA6qKo8ZICF160","81/KecGyVBLIynPNuEwEKR","e2/Vcd8/lGiI24Gt5yGA4C","a2MjXRFdtLlYQ5ouAFv/+R","7fIIhyppRNvLYvdlsPuxJq","8bjGlE+6JGIp/Fj3nUIfO7","53geBfcn5AsaX+bZ+NWPHP","b9jkkjrvVOnJxaxEfo1+IR","89CucvXeRG4o5AEufVPmKb","33Q6hdNWhGg6IIn9Jht+T1","2fm882nl5LS4tkP9Qn6PxI","09KiUz9x1JP7doP7FdYAYE","d6hRqnsWxJ7ZWqi57xDX5Z","332/Ypp/NGk4YUzVKUjwjp","07g2EmcqpIl5DaaTk2KY7H","57JJESq1RPF6gc54BloHJl","9e+CO9l3dI3a1thYBrVboL","092N/XvypHAKBi/yXT3Lkz","39mS74neZGp4Bx+JFdYG6O"],["node","_spriteFrame","root","_parent","_textureSetter","_prefab","_N$content","data"],[["cc.Node",["_name","_active","_opacity","_prefab","_contentSize","_trs","_parent","_components","_children","_color","_anchorPoint"],0,4,5,7,1,9,2,5,5],"cc.SpriteFrame",["cc.Widget",["_alignFlags","_originalWidth","_originalHeight","alignMode","_bottom","_top","node"],-3,1],["cc.Sprite",["_sizeMode","_type","node","_materials","_spriteFrame"],1,1,3,6],["cc.Label",["_string","_fontSize","_lineHeight","_styleFlags","_N$verticalAlign","_enableWrapText","_N$overflow","_N$horizontalAlign","node","_materials"],-5,1,3],["cc.PrefabInfo",["fileId","root"],2,1],["cc.Layout",["_N$layoutType","_N$spacingY","_resize","_N$spacingX","node","_layoutSize"],-1,1,5],["cc.Prefab",["_name"],2],["cc.ScrollView",["horizontal","brake","bounceDuration","_N$horizontalScrollBar","_N$verticalScrollBar","node","_N$content"],-2,1,1],["23c83NE4rdLkInMdn6tZDjW",["node"],3,1],["cc.Mask",["_N$alphaThreshold","node","_materials"],2,1,3],["cc.Button",["node"],3,1],["a326a9m5/1JeIcXBdJXIiLl",["_dataID","node"],2,1],["cc.LabelOutline",["_width","node","_color"],2,1,5],["cc.RichText",["_N$string","_N$fontSize","_N$maxWidth","_N$lineHeight","node"],-1,1],["bfc54kpI8JOI6yHYbZgXsaU",["node","_prefab"],3,1,6]],[[5,0,1,2],[0,0,6,7,3,4,5,2],[3,2,3,4,1],[3,1,0,2,3,4,3],[2,0,6,2],[4,0,1,2,3,4,8,9,6],[12,0,1,2],[0,0,6,7,3,9,4,5,2],[2,0,1,2,6,4],[0,0,8,7,3,4,5,2],[0,0,6,8,7,3,4,5,2],[0,0,8,7,3,4,2],[0,0,8,3,4,5,2],[0,0,7,3,9,4,5,2],[0,0,6,8,3,5,2],[0,0,6,7,3,9,4,10,5,2],[0,0,6,7,3,4,2],[11,0,1],[4,0,1,2,5,3,4,6,8,9,8],[13,0,1,2,2],[14,0,1,2,3,4,5],[15,0,1,1],[7,0,2],[0,0,8,3,5,2],[0,0,6,8,3,4,5,2],[0,0,2,6,7,3,9,4,3],[0,0,6,7,3,4,10,5,2],[0,0,6,8,7,3,4,10,5,2],[0,0,1,6,7,3,4,5,3],[0,0,1,6,8,3,5,3],[0,0,6,8,3,4,10,5,2],[8,0,1,2,3,4,5,6,6],[5,1,1],[2,3,0,6,3],[2,0,5,4,1,2,6,6],[2,3,0,1,2,6,5],[2,0,4,6,3],[9,0,1],[3,0,2,3,4,2],[10,0,1,2,2],[6,0,1,4,5,3],[6,2,0,3,1,4,5,5],[4,0,1,2,3,7,4,8,9,7]],[[[{"name":"hero_img6_3","rect":[0,0,44,40],"offset":[0,0],"originalSize":[44,40],"capInsets":[0,0,0,0]}],[1],0,[0],[4],[4]],[[{"name":"hero_img6_2","rect":[0,0,44,40],"offset":[0,0],"originalSize":[44,40],"capInsets":[0,0,0,0]}],[1],0,[0],[4],[5]],[[{"name":"hero_img6_1","rect":[0,0,44,40],"offset":[0,0],"originalSize":[44,40],"capInsets":[0,0,0,0]}],[1],0,[0],[4],[6]],[[{"name":"hero_img6_2up","rect":[0,0,44,40],"offset":[0,0],"originalSize":[44,40],"capInsets":[0,0,0,0]}],[1],0,[0],[4],[7]],[[{"name":"hero_img6_1up","rect":[0,0,44,40],"offset":[0,0],"originalSize":[44,40],"capInsets":[0,0,0,0]}],[1],0,[0],[4],[8]],[[[22,"GeneralSkillUI"],[9,"list_view",[-4],[[31,false,0.75,0.23,null,null,-3,-2]],[0,"ceLcHWtVJLqbTcJwv7VW2g",-1],[5,524,660],[0,-85.262,0,0,0,0,1,1,1,1]],[9,"GeneralSkillUI",[-8,-9],[[33,2,45,-6],[37,-7]],[32,-5],[5,750,1334],[375,667,0,0,0,0,1,1,1,1]],[10,"sp_bg",2,[-11,1,-12,-13],[[3,1,0,-10,[45],46]],[0,"41ilGeq0dMtIVS5UN4D7zX",2],[5,594,900],[0,49.293,0,0,0,0,1,1,1,1]],[10,"view",1,[-17,-18],[[39,0,-14,[38]],[34,45,3.1809999999999787,-3.1809999999999787,240,250,-15],[40,2,10,-16,[5,524,660]]],[0,"c1dc9Kk/CRJqaNnBOP4YGDS",1],[5,524,660],[0,-3.180999999999983,0,0,0,0,1,1,1,1]],[11,"node_unlock",[-21,-22,-23],[[3,1,0,-19,[16],17],[8,45,524,84,-20]],[0,"52Uu4GHJdBlab0c+3crx/A",1],[5,524,84]],[11,"node_lock",[-26,-27,-28],[[3,1,0,-24,[24],25],[8,45,524,84,-25]],[0,"4639NfXBVA0IEAc1BkwZBH",1],[5,524,84]],[23,"node_skillAutoLearningImg",[-29,-30,-31,-32,-33],[0,"5a9VxwaDZOmahyDEDmpdRd",1],[0,-145,0,0,0,0,1,1,1,1]],[24,"title",3,[-34,-35,-36,-37],[0,"6dM7bVck5JnLbsj8eRdM2t",2],[5,700,160],[0,351.12,0,0,0,0,1,1,1,1]],[12,"New Node",[5,6,-38,-39],[0,"fbK9eNg/RAQbeP2/PmDklS",1],[5,524,84],[0,-42,0,0,0,0,1,1,1,1]],[25,"btn_close",220,2,[[38,0,-40,[0],1],[35,2,45,750,1334,-41],[17,-42]],[0,"bcuFEACNxPuYg4rThwop3K",2],[4,4278190080],[5,750,1334]],[13,"lbl_type",[[5,"900600510",24,24,1,1,-44,[4]],[6,900600510,-45]],[0,"3dwLjONtdGj7/lwerSl/GC",-43],[4,4279122286],[5,120.13,30.24],[2.421,0.3,0,0,0,0,1,1,1,1]],[13,"lbl_type2",[[5,"被动技能",24,24,1,1,-47,[7]],[6,900600509,-48]],[0,"3dwLjONtdGj7/lwerSl/GC",-46],[4,4279463438],[5,96,30.24],[2.421,0.3,0,0,0,0,1,1,1,1]],[26,"lbl_name",8,[[5,"道具名字",32,32,1,1,-50,[9]],[19,3,-51,[4,4278190080]]],[0,"4dlqwRXitM/I3zu0japDbn",-49],[5,134,46.32],[0,0,0.5],[-112.7,33.059,0,0,0,0,1,1,1,1]],[27,"content",4,[9],[[41,1,3,19,10,-52,[5,524,84]]],[0,"036a4WKD5hBcbQJmMrbqoW8",1],[5,524,84],[0,0.5,1],[0,330,0,0,0,0,1,1,1,1]],[12,"New Node",[-53,-54,-55],[0,"6fFGerxepDnozWC7wdtua7",1],[5,524,180],[0,-90,0,0,0,0,1,1,1,1]],[7,"title",15,[[18,"900600912",24,24,false,1,1,2,-57,[29]],[6,900600912,-58]],[0,"3dvp3J2GZARa8maGy4dGZS",-56],[4,4282606479],[5,120,30.24],[-163.697,62.922,0,0,0,0,1,1,1,1]],[7,"type",7,[[5,"900600510",24,24,1,1,-60,[32]],[6,900600510,-61]],[0,"3dwLjONtdGj7/lwerSl/GC",-59],[4,4279122286],[5,120.13,30.24],[100,0,0,0,0,0,1,1,1,1]],[7,"type2",7,[[5,"900600710",24,24,1,1,-63,[37]],[6,900600710,-64]],[0,"05ZMZcZLlCULRISUjMz6+h",-62],[4,4279463438],[5,120.13,30.24],[-100,0,0,0,0,0,1,1,1,1]],[28,"btn_close",false,3,[[2,-65,[39],40],[36,4,-85.03500000000003,-66],[17,-67]],[0,"b7P9yHN8pBBLUu4puXdtUc",2],[5,92,88],[-230.585,-491.0350000000001,0,0,0,0,1,1,1,0]],[29,"node_general",false,3,[-68,-69,-70],[0,"63vJu4vhtBUaCtyR0UdMsX",2],[198.561,309.069,0,0,0,0,1,1,1,1]],[14,"node_passive",8,[-71,11],[0,"dd3Pg1IORO9oGOiPQDKP4T",2],[-39.981,-13.792,0,0,0,0,1,1,1,1]],[14,"node_active",8,[-72,12],[0,"e3xtxCvxZHXrjYT6SeDcUO",2],[-39.981,-13.792,0,0,0,0,1,1,1,1]],[1,"hero_img6_1up",5,[[2,-73,[10],11],[4,9,-74]],[0,"e4CsBRLEdJyqoY57iGRoWF",1],[5,44,40],[-240,22,0,0,0,0,1,1,1,1]],[1,"hero_img6_2up",5,[[2,-75,[12],13],[4,9,-76]],[0,"3eNu8XvYBKYqAz0THuDX93",1],[5,44,40],[-240,22,0,0,0,0,1,1,1,1]],[1,"hero_img6_3up",5,[[2,-77,[14],15],[4,9,-78]],[0,"83z7Q84OhK0YoI5LHIT4eL",1],[5,44,40],[-240,22,0,0,0,0,1,1,1,1]],[1,"hero_img6_1",6,[[2,-79,[18],19],[4,9,-80]],[0,"081Nee53BAdq3NS0W8cnqu",1],[5,44,40],[-240,22,0,0,0,0,1,1,1,1]],[1,"hero_img6_2",6,[[2,-81,[20],21],[4,9,-82]],[0,"f3DrgALbBBPbWHdq+ced8x",1],[5,44,40],[-240,22,0,0,0,0,1,1,1,1]],[1,"hero_img6_3",6,[[2,-83,[22],23],[4,9,-84]],[0,"e1W1gRQVVDSrUaa/ZEtFDf",1],[5,44,40],[-240,22,0,0,0,0,1,1,1,1]],[7,"lbl_lv",9,[[18,"1级：",24,24,false,1,1,2,-86,[26]]],[0,"3dvp3J2GZARa8maGy4dGZS",-85],[4,4284369740],[5,120,30.24],[-164.811,1.696,0,0,0,0,1,1,1,1]],[15,"rich_desc",9,[[20,"每5秒释放灵力飞袭：发射1枚灵力球，造成高额伤害。<color=#C54848>(1级解锁)</color>",24,360,26,-88]],[0,"123rlHrHBP64ZUTCFJoAGS",-87],[4,4284369740],[5,360,58.75999999999999],[0,0,0.5],[-158.664,1.362,0,0,0,0,1,1,1,1]],[30,"node_skillAutoLearningDesc",4,[15,7],[0,"1asTuFT+hP+6v+AouCHE+C",1],[5,524,180],[0,0.5,1],[0,236,0,0,0,0,1,1,1,1]],[16,"node_lock",15,[[3,1,0,-89,[27],28],[8,45,524,84,-90]],[0,"22yz6sozBPcYt6/TKZZrrY",1],[5,524,180]],[15,"rich_skillAutoLearningDesc",15,[[20,"将领达到60级XXXXXXXXX",24,420,26,-92]],[0,"123rlHrHBP64ZUTCFJoAGS",-91],[4,4284369740],[5,420,32.76],[0,0,0.5],[-223.024,19.203,0,0,0,0,1,1,1,1]],[1,"lbl_generalLv",20,[[42,"Lv.19/20",20,20,1,1,1,-93,[42]],[19,2,-94,[4,4278190080]]],[0,"f1BhYPYe5OAY9cnQVhQrZ1",2],[5,81.46,29.2],[0,-51.368,0,0,0,0,1,1,1,1]],[1,"hero_img7_1",21,[[3,1,0,-95,[2],3]],[0,"42FRlEYHVPcKwCE55wREJh",2],[5,155,42],[2.992,-0.242,0,0,0,0,1,1,1,1]],[1,"hero_img7_1",22,[[3,1,0,-96,[5],6]],[0,"3dPrT/rc9FLoy7vDSlPRbr",2],[5,155,42],[2.992,-0.242,0,0,0,0,1,1,1,1]],[1,"link_icon",8,[[21,-97,8]],[0,"b16xpAFKZBf5XmlowMBlhn",2],[5,140,140],[-197.396,4.145,0,0,0,0,1,0.8,0.8,0.85]],[1,"hero_img7_1",7,[[3,1,0,-98,[30],31]],[0,"f9YV5DdfBPj50LFnMz4qmZ",1],[5,155,42],[100,0,0,0,0,0,1,1,1,1]],[16,"common_icon1_6",7,[[2,-99,[33],34]],[0,"aa80JMfCxAVJxJaPreDKxP",1],[5,40,30]],[1,"hero_img7_1",7,[[3,1,0,-100,[35],36]],[0,"61PseVWBVA5Ky+86y+F8mt",1],[5,155,42],[-100,0,0,0,0,0,1,1,1,1]],[1,"link_generalIcon",20,[[21,-101,41]],[0,"82JZMVrT1JepLUiJtwvu7D",2],[5,140,140],[0,2.564,0,0,0,0,1,0.7,0.7,1]],[1,"common_btn2_3",20,[[2,-102,[43],44]],[0,"18Y6h5/1pJwZV2zbdKaQrZ",2],[5,41,40],[36.581,36.334,0,0,0,0,1,0.8,0.8,1]]],0,[0,2,1,0,6,14,0,0,1,0,-1,4,0,2,2,0,0,2,0,0,2,0,-1,10,0,-2,3,0,0,3,0,-1,8,0,-3,19,0,-4,20,0,0,4,0,0,4,0,0,4,0,-1,14,0,-2,31,0,0,5,0,0,5,0,-1,23,0,-2,24,0,-3,25,0,0,6,0,0,6,0,-1,26,0,-2,27,0,-3,28,0,-1,38,0,-2,17,0,-3,39,0,-4,40,0,-5,18,0,-1,21,0,-2,22,0,-3,37,0,-4,13,0,-3,29,0,-4,30,0,0,10,0,0,10,0,0,10,0,2,11,0,0,11,0,0,11,0,2,12,0,0,12,0,0,12,0,2,13,0,0,13,0,0,13,0,0,14,0,-1,32,0,-2,16,0,-3,33,0,2,16,0,0,16,0,0,16,0,2,17,0,0,17,0,0,17,0,2,18,0,0,18,0,0,18,0,0,19,0,0,19,0,0,19,0,-1,41,0,-2,34,0,-3,42,0,-1,35,0,-1,36,0,0,23,0,0,23,0,0,24,0,0,24,0,0,25,0,0,25,0,0,26,0,0,26,0,0,27,0,0,27,0,0,28,0,0,28,0,2,29,0,0,29,0,2,30,0,0,30,0,0,32,0,0,32,0,2,33,0,0,33,0,0,34,0,0,34,0,0,35,0,0,36,0,0,37,0,0,38,0,0,39,0,0,40,0,0,41,0,0,42,0,7,2,1,3,3,5,3,9,6,3,9,7,3,31,9,3,14,11,3,21,12,3,22,15,3,31,102],[0,0,0,0,0,0,0,0,0,0,0,0,0,0,0,0,0,0,0,0,0,0,0,0,0,0,0,0,0,0,0,0,0,0,0,0,0,0,0,0,0,0,0,0,0,0,0],[-1,1,-1,1,-1,-1,1,-1,5,-1,-1,1,-1,1,-1,1,-1,1,-1,1,-1,1,-1,1,-1,1,-1,-1,1,-1,-1,1,-1,-1,1,-1,1,-1,-1,-1,1,5,-1,-1,1,-1,1],[0,9,0,1,0,0,2,0,10,0,0,11,0,12,0,13,0,14,0,15,0,16,0,17,0,3,0,0,3,0,0,1,0,0,18,0,2,0,0,0,19,20,0,0,21,0,22]],[[{"name":"hero_img6_3up","rect":[0,0,44,40],"offset":[0,0],"originalSize":[44,40],"capInsets":[0,0,0,0]}],[1],0,[0],[4],[23]],[[{"name":"hero_img7_2","rect":[0,0,49,42],"offset":[0,0],"originalSize":[49,42],"capInsets":[21,19,21,21]}],[1],0,[0],[4],[24]]]]