[1,["ecpdLyjvZBwrvm+cedCcQy","44AxgnTM5OKY/gwFzT7lwp","07d6BI5UZADqNqcKJCCdZd","1fHn7mjx5KAo1qOGjHphUa","2c5G/wpbBHQa7rPm+V9WDe","3avBjVbyRBl7km6BWzek+r","a1J/1d/WVI64ezl/EfANIl","a2MjXRFdtLlYQ5ouAFv/+R","b1aAyN5GdIEazfvflw6iH+","a7R9BadbpDSqFfbxH4Ng0l","0avkKzhhxJro18MbeXW9lk","b9cshHfAZKtbyHgdluStFz","13kjLBG1NLS6RHDreNE7t3","89CucvXeRG4o5AEufVPmKb","332/Ypp/NGk4YUzVKUjwjp","46Xq7q8odLCLT6mrtcPZxR","ecRjibqo5EyphgLZ0WjxE4"],["node","_spriteFrame","_parent","_textureSetter","root","data"],[["cc.Node",["_name","_objFlags","_opacity","_prefab","_contentSize","_components","_parent","_trs","_children","_anchorPoint","_color"],0,4,5,9,1,7,2,5,5],"cc.SpriteFrame",["cc.Sprite",["_sizeMode","_type","_isTrimmedMode","node","_materials","_spriteFrame"],0,1,3,6],["cc.Widget",["_alignFlags","_top","_enabled","_originalWidth","_originalHeight","node"],-2,1],["cc.Layout",["_resize","_N$layoutType","_N$spacingY","_N$spacingX","_N$paddingTop","_N$paddingBottom","node","_layoutSize"],-3,1,5],["cc.Label",["_string","_fontSize","_styleFlags","_N$verticalAlign","_lineHeight","_N$horizontalAlign","node","_materials"],-3,1,3],["cc.PrefabInfo",["fileId","root"],2,1],["cc.Button",["zoomScale","node"],2,1],["cc.Prefab",["_name"],2],["e30981W+axNKbBurwpvgWam",["node"],3,1],["cc.BlockInputEvents",["node"],3,1],["cc.LabelOutline",["_width","node","_color"],2,1,5],["a326a9m5/1JeIcXBdJXIiLl",["_dataID","node"],2,1],["6e617Gf+5ZAi5ELzHSzBfzM",["_btnType","_colorType","node"],1,1],["cc.Mask",["_N$alphaThreshold","node","_materials"],2,1,3],["cc.ScrollView",["horizontal","brake","bounceDuration","_N$horizontalScrollBar","_N$verticalScrollBar","node","_N$content"],-2,1,1],["cc.RichText",["_N$string","_N$fontSize","_N$lineHeight","node"],0,1]],[[6,0,1,2],[5,0,1,4,2,5,3,6,7,7],[0,0,6,5,3,10,4,9,7,2],[2,0,2,3,4,5,3],[0,0,6,8,5,3,4,9,7,2],[0,0,6,5,3,4,7,2],[12,0,1,2],[0,0,8,5,3,4,7,2],[0,0,6,5,3,10,4,7,2],[2,1,0,3,4,5,3],[4,0,1,6,7,3],[7,0,1,2],[0,0,8,5,3,4,9,2],[2,3,4,5,1],[7,1,1],[5,0,1,2,5,3,6,7,6],[0,0,6,8,5,3,4,7,2],[0,0,6,5,3,10,4,9,2],[0,0,6,5,3,4,2],[3,0,3,4,5,4],[4,0,1,2,6,7,4],[11,0,1,2,2],[8,0,2],[0,0,6,8,5,3,4,2],[0,0,1,6,8,5,3,4,7,3],[0,0,5,3,4,9,2],[0,0,2,6,5,3,10,4,3],[0,0,8,3,4,9,7,2],[0,0,6,5,3,4,9,7,2],[0,0,6,5,3,10,4,2],[3,0,5,2],[3,0,1,5,3],[3,2,0,5,3],[9,0,1],[6,1,1],[2,0,3,4,2],[2,0,3,4,5,2],[10,0,1],[4,0,1,3,6,7,4],[4,0,1,4,5,3,2,6,7,7],[5,0,1,4,2,3,6,7,6],[13,0,1,2,3],[14,0,1,2,2],[15,0,1,2,3,4,5,6,6],[16,0,1,2,3,4]],[[[{"name":"common_box1_btn2up","rect":[0,15,100,106],"offset":[0,-7.5],"originalSize":[100,121],"capInsets":[0,0,0,0]}],[1],0,[0],[3],[3]],[[{"name":"outdoors_box1_btn1","rect":[0,0,44,44],"offset":[0,0],"originalSize":[44,44],"capInsets":[0,0,0,0]}],[1],0,[0],[3],[4]],[[{"name":"soldier1_1","rect":[8,1,93,109],"offset":[-0.5,-0.5],"originalSize":[110,110],"capInsets":[0,0,0,0]}],[1],0,[0],[3],[5]],[[{"name":"common_box1_btn2","rect":[0,28,100,93],"offset":[0,-14],"originalSize":[100,121],"capInsets":[0,0,0,0]}],[1],0,[0],[3],[6]],[[[22,"OuterCitySoliderInfoUI"],[7,"OuterCitySoliderInfoUI",[-4,-5],[[30,45,-2],[33,-3]],[34,-1],[5,750,1334],[375,667,0,0,0,0,1,1,1,1]],[23,"main",1,[-8,-9,-10,-11,-12,-13,-14],[[9,1,0,-6,[45],46],[37,-7]],[0,"1bGleA48hDnabTZTvkfzym",1],[5,725,1000]],[12,"group",[-17,-18,-19],[[9,1,0,-15,[25],26],[20,1,2,20,-16,[5,649,381]]],[0,"e3N0XMvn1CHrih1cs5zFs1",1],[5,649,381],[0,0.5,1]],[16,"info",3,[-21,-22,-23,-24],[[9,1,0,-20,[17],18]],[0,"12L3hY9/1ECZji6uBrTXIt",1],[5,649,131],[0,-65.5,0,0,0,0,1,1,1,1]],[7,"btn_out",[-27,-28,-29],[[3,2,false,-25,[36],37],[11,0.93,-26]],[0,"5aYCSmGspElpO7EVO0diC2",1],[5,100,121],[-160,0,0,0,0,0,1,1,1,0]],[7,"btn_in",[-32,-33,-34],[[3,2,false,-30,[43],44],[11,0.93,-31]],[0,"a7uKRbG39EFr1Fm9ByWITH",1],[5,100,121],[-50,0,0,0,0,0,1,1,1,0]],[24,"info",512,2,[-36,-37,-38],[[9,1,0,-35,[11],12]],[0,"f6cb1StRlNqYJVrYWjwDfo",1],[5,648,135],[0,325.843,0,0,0,0,1,1,1,1]],[25,"lbl",[[1,"900602075",24,30,1,1,1,-39,[5]],[31,1,-1.8999999999999986,-40],[21,3,-41,[4,4278190080]],[6,900602075,-42]],[0,"e5hxQgFplFjZSBxMqZyBK6",1],[5,126.13,43.8],[0,0,0.5]],[12,"content",[3],[[20,1,2,10,-43,[5,649,381]],[32,false,1,-44]],[0,"8dSIGP3mVCSo5FX141JBHB",1],[5,649,381],[0,0.5,1]],[7,"btn_hospital",[-48],[[35,0,-45,[24]],[41,"small","green",-46],[14,-47]],[0,"b9zO6y+mJKXJZcZGOzFJ9C",1],[5,175,76],[0,10,0,0,0,0,1,1,1,1]],[26,"btn_close",200,1,[[36,0,-49,[0],1],[19,45,100,100,-50],[14,-51]],[0,"37NgjBKd1FRZuWXkwac7Ph",1],[4,4278190080],[5,750,1334]],[4,"node_all",7,[8,-53],[[10,1,1,-52,[5,212.22,40]]],[0,"3fmdhcqfVE8Ywz6+GLTYsv",1],[5,212.22,40],[0,0,0.5],[-140.236,21.873,0,0,0,0,1,1,1,1]],[4,"node_hit",7,[-55,-56],[[10,1,1,-54,[5,166.85,40]]],[0,"be8+Va5YVJDbwK5DRihrg8",1],[5,166.85,40],[0,0,0.5],[-140.236,-20.19,0,0,0,0,1,1,1,1]],[4,"node_in",7,[-58,-59],[[10,1,1,-57,[5,166.85,40]]],[0,"a2CEYeiBtDgq6izQPI5E3B",1],[5,166.85,40],[0,0,0.5],[95.316,-20.19,0,0,0,0,1,1,1,1]],[12,"view",[9],[[42,0,-60,[27]],[19,45,240,250,-61]],[0,"a6QPoCiE9CA6Q7oW2spkHP",1],[5,669,704],[0,0.5,1]],[27,"item",[-62,-63,-64],[0,"7dujxQFuhBOa6diDj3qrMZ",1],[5,250,90],[0,0,0.5],[-290,-55,0,0,0,0,1,1,1,1]],[4,"node_pagebuttons",2,[5,6],[[38,1,1,10,-65,[5,210,121]]],[0,"8cUMqro+BIxYm6Uf7T4/u0",1],[5,210,121],[0,1,0.5],[308,-510.98,0,0,0,0,1,1,1,1]],[8,"lbl_title",2,[[15,"900602074",32,1,1,1,-66,[2]],[6,900602074,-67]],[0,"d4K4jtAmZBD6rFv41cvICy",1],[4,4288862715],[5,160.17,50.4],[0,455,0,0,0,0,1,1,1,1]],[5,"btn_rule",2,[[13,-68,[3],4],[14,-69]],[0,"b2kCnEDZhAnIO3T82vuyx+",1],[5,41,40],[146.451,455,0,0,0,0,1,1,1,0]],[28,"lbl_all_count",12,[[1,"999999",24,30,1,1,1,-70,[6]],[21,3,-71,[4,4278190080]]],[0,"53yw+Ra6hO86vNXEp7ePsO",1],[5,86.09,43.8],[0,0,0.5],[126.13,0,0,0,0,0,1,1,1,1]],[17,"lbl",13,[[1,"900602076",20,20,1,1,1,-72,[7]],[6,900602076,-73]],[0,"e27rQ2bj1PiIKXZ7Sss+fT",1],[4,4289153055],[5,100.11,25.2],[0,0,0.5]],[17,"lbl",14,[[1,"900602077",20,20,1,1,1,-74,[9]],[6,900602077,-75]],[0,"affFRp8YdPVL6dgKLjLDXE",1],[4,4289153055],[5,100.11,25.2],[0,0,0.5]],[4,"sv_list",2,[15],[[43,false,0.75,0.23,null,null,-76,9]],[0,"2fwVZFeb1CAr93kQC4fuIu",1],[5,669,704],[0,0.5,1],[0,250,0,0,0,0,1,1,1,1]],[5,"btn",4,[[13,-77,[13],14],[11,0.9,-78]],[0,"2a7egzd3hCvpfM7eOjdqD0",1],[5,44,44],[283.376,-27.664,0,0,0,0,1,1,1,0]],[4,"detail",3,[16],[[39,1,3,10,20,80,20,-79,[5,580,120]]],[0,"27JXClmQlCgIBySNgvXrk8",1],[5,580,120],[0,0.5,1],[0,-151,0,0,0,0,1,1,1,1]],[16,"btns",3,[10],[[10,1,1,-80,[5,175,90]]],[0,"91X46W8ExCBJyPbZQdiVyP",1],[5,175,90],[0,-336,0,0,0,0,1,1,1,1]],[29,"label",10,[[15,"900602078",28,1,1,1,-81,[23]],[6,900602078,-82]],[0,"b1cOxVxOdCBY0Wlm0OZVEl",1],[4,4278609666],[5,140.15,50.4]],[5,"btn_close",2,[[11,0.93,-83],[3,2,false,-84,[29],30]],[0,"67YtpAbE9KOJ+HLtZaRON3",1],[5,92,88],[-270,-520,0,0,0,0,1,1,1,0]],[2,"lbl_hit_count",13,[[1,"999999",20,20,1,1,1,-85,[8]]],[0,"acv6+X/nlLK5DrGetm++6U",1],[4,4289153055],[5,66.74,25.2],[0,0,0.5],[100.11,0,0,0,0,0,1,1,1,1]],[2,"lbl_in_count",14,[[1,"999999",20,20,1,1,1,-86,[10]]],[0,"dbPUoqadtCPbkiSGFRqPQl",1],[4,4289153055],[5,66.74,25.2],[0,0,0.5],[100.11,0,0,0,0,0,1,1,1,1]],[2,"name",4,[[40,"派遣部队1",24,24,1,1,-87,[15]]],[0,"cad99Awa9E2rNZCHCRa22G",1],[4,4284369740],[5,109.35,30.24],[0,0,0.5],[-297.754,34.192,0,0,0,0,1,1,1,1]],[2,"num",4,[[1,"使用士兵：8888888",24,24,1,1,1,-88,[16]]],[0,"bc4k5+tPZEP4UelU05/05a",1],[4,4287926936],[5,213.43,30.24],[0,1,0.5],[300.604,34.192,0,0,0,0,1,1,1,1]],[2,"desc",4,[[44,"正在进行",20,24,-89]],[0,"12m9aEVhJPQrOLAw9nWts8",1],[4,4287926936],[5,80,30.240000000000002],[0,0,0.5],[-297.754,-24.219,0,0,0,0,1,1,1,1]],[5,"icon",16,[[13,-90,[19],20]],[0,"8fXrUAOuFKArVWuqq2/0uh",1],[5,93,109],[33.88,0,0,0,0,0,1,0.8,0.8,1]],[2,"name",16,[[1,"探照灯",24,24,1,1,1,-91,[21]]],[0,"c2CFGXi+ZG1owernv/8zhT",1],[4,4284172363],[5,72,30.24],[0,0,0.5],[82,13,0,0,0,0,1,1,1,1]],[2,"count",16,[[1,"100",24,24,1,1,1,-92,[22]]],[0,"a0nuziUSpGF7atwtfAGezF",1],[4,4288904020],[5,40.04,30.24],[0,0,0.5],[82,-16,0,0,0,0,1,1,1,1]],[8,"lbl_empty",2,[[15,"当前没有外出部队",24,1,1,1,-93,[28]]],[0,"efGOujNA1HL7PYzxvSF2nY",1],[4,4287926936],[5,192,50.4],[0,-102.542,0,0,0,0,1,1,1,1]],[5,"img_off",5,[[3,2,false,-94,[31],32]],[0,"a3+iL/6H1ITpUSqjdQCUhA",1],[5,100,121],[0,2,0,0,0,0,1,1,1,1]],[18,"img_on",5,[[3,2,false,-95,[33],34]],[0,"43XIRdjGxMqrUGa45FxBwh",1],[5,100,121]],[8,"New Label",5,[[1,"忙碌",24,24,1,1,1,-96,[35]]],[0,"d5prV7hIhOzJlrtA28g1bG",1],[4,4282992977],[5,48,30.24],[0,-7.491,0,0,0,0,1,1,1,1]],[5,"img_off",6,[[3,2,false,-97,[38],39]],[0,"a0QRUPw11OlKiGqby2vOS1",1],[5,100,121],[0,2,0,0,0,0,1,1,1,1]],[18,"img_on",6,[[3,2,false,-98,[40],41]],[0,"0c/Igg101HzLeCJZGi82sv",1],[5,100,121]],[8,"New Label",6,[[1,"空闲",24,24,1,1,1,-99,[42]]],[0,"90dURNwDhG05/1hfFKvAGW",1],[4,4282992977],[5,48,30.24],[0,-7.491,0,0,0,0,1,1,1,1]]],0,[0,4,1,0,0,1,0,0,1,0,-1,11,0,-2,2,0,0,2,0,0,2,0,-1,18,0,-2,19,0,-3,7,0,-4,23,0,-5,37,0,-6,28,0,-7,17,0,0,3,0,0,3,0,-1,4,0,-2,25,0,-3,26,0,0,4,0,-1,24,0,-2,31,0,-3,32,0,-4,33,0,0,5,0,0,5,0,-1,38,0,-2,39,0,-3,40,0,0,6,0,0,6,0,-1,41,0,-2,42,0,-3,43,0,0,7,0,-1,12,0,-2,13,0,-3,14,0,0,8,0,0,8,0,0,8,0,0,8,0,0,9,0,0,9,0,0,10,0,0,10,0,0,10,0,-1,27,0,0,11,0,0,11,0,0,11,0,0,12,0,-2,20,0,0,13,0,-1,21,0,-2,29,0,0,14,0,-1,22,0,-2,30,0,0,15,0,0,15,0,-1,34,0,-2,35,0,-3,36,0,0,17,0,0,18,0,0,18,0,0,19,0,0,19,0,0,20,0,0,20,0,0,21,0,0,21,0,0,22,0,0,22,0,0,23,0,0,24,0,0,24,0,0,25,0,0,26,0,0,27,0,0,27,0,0,28,0,0,28,0,0,29,0,0,30,0,0,31,0,0,32,0,0,33,0,0,34,0,0,35,0,0,36,0,0,37,0,0,38,0,0,39,0,0,40,0,0,41,0,0,42,0,0,43,0,5,1,3,2,9,5,2,17,6,2,17,8,2,12,9,2,15,10,2,26,15,2,23,16,2,25,99],[0,0,0,0,0,0,0,0,0,0,0,0,0,0,0,0,0,0,0,0,0,0,0,0,0,0,0,0,0,0,0,0,0,0,0,0,0,0,0,0,0,0,0,0,0,0,0],[-1,1,-1,-1,1,-1,-1,-1,-1,-1,-1,-1,1,-1,1,-1,-1,-1,1,-1,1,-1,-1,-1,-1,-1,1,-1,-1,-1,1,-1,1,-1,1,-1,-1,1,-1,1,-1,1,-1,-1,1,-1,1],[0,7,0,0,8,0,0,0,0,0,0,0,9,0,10,0,0,0,11,0,12,0,0,0,0,0,13,0,0,0,14,0,1,0,2,0,0,1,0,1,0,2,0,0,1,0,15]],[[{"name":"hospital_img1_2","rect":[0,0,235,135],"offset":[0,0],"originalSize":[235,135],"capInsets":[173,0,47,0]}],[1],0,[0],[3],[16]]]]