[1,["98ghZsWwBEaJOf4HCE6xFj"],0,[["sp.SkeletonData",["_name","_atlasText","textureNames","_skeletonJson","textures"],-1,3]],[[0,0,1,2,3,4,5]],[[0,"cx","\r\ncx.png\r\nsize: 1163,1123\r\nformat: RGBA8888\r\nfilter: Linear,Linear\r\nrepeat: none\r\n10\r\n  rotate: false\r\n  xy: 317, 771\r\n  size: 289, 350\r\n  orig: 313, 373\r\n  offset: 13, 14\r\n  index: -1\r\n11\r\n  rotate: false\r\n  xy: 316, 27\r\n  size: 300, 359\r\n  orig: 313, 373\r\n  offset: 7, 11\r\n  index: -1\r\n12\r\n  rotate: false\r\n  xy: 2, 23\r\n  size: 312, 363\r\n  orig: 313, 373\r\n  offset: 1, 7\r\n  index: -1\r\n13\r\n  rotate: false\r\n  xy: 2, 755\r\n  size: 313, 366\r\n  orig: 313, 373\r\n  offset: 0, 5\r\n  index: -1\r\n14\r\n  rotate: false\r\n  xy: 2, 388\r\n  size: 313, 365\r\n  orig: 313, 373\r\n  offset: 0, 5\r\n  index: -1\r\n2\r\n  rotate: true\r\n  xy: 890, 826\r\n  size: 295, 221\r\n  orig: 313, 373\r\n  offset: 9, 9\r\n  index: -1\r\n3\r\n  rotate: false\r\n  xy: 881, 39\r\n  size: 280, 209\r\n  orig: 313, 373\r\n  offset: 18, 32\r\n  index: -1\r\n4\r\n  rotate: false\r\n  xy: 618, 230\r\n  size: 261, 230\r\n  orig: 313, 373\r\n  offset: 27, 48\r\n  index: -1\r\n5\r\n  rotate: true\r\n  xy: 888, 250\r\n  size: 249, 255\r\n  orig: 313, 373\r\n  offset: 32, 43\r\n  index: -1\r\n6\r\n  rotate: false\r\n  xy: 591, 462\r\n  size: 295, 307\r\n  orig: 313, 373\r\n  offset: 9, 9\r\n  index: -1\r\n7\r\n  rotate: false\r\n  xy: 608, 820\r\n  size: 280, 301\r\n  orig: 313, 373\r\n  offset: 18, 30\r\n  index: -1\r\n8\r\n  rotate: false\r\n  xy: 888, 501\r\n  size: 264, 317\r\n  orig: 313, 373\r\n  offset: 25, 25\r\n  index: -1\r\n9\r\n  rotate: false\r\n  xy: 317, 431\r\n  size: 272, 338\r\n  orig: 313, 373\r\n  offset: 21, 19\r\n  index: -1\r\ndiguang_0\r\n  rotate: true\r\n  xy: 618, 2\r\n  size: 226, 255\r\n  orig: 266, 317\r\n  offset: 19, 33\r\n  index: -1\r\n",["cx.png"],{"skeleton":{"hash":"E1il1EqSZYchCu/aLlc7yWTDL+s","spine":"3.8.99","x":-318.38,"y":-320.88,"width":647.51,"height":771.46,"images":"./image/","audio":""},"bones":[{"name":"root"},{"name":"0","parent":"root","x":-1.84,"y":9},{"name":"diguang_0","parent":"root","x":2.29,"y":49.88,"scaleX":1.4583,"scaleY":1.4583}],"slots":[{"name":"0","bone":"0","attachment":"7"},{"name":"diguang_0","bone":"diguang_0","attachment":"diguang_0","blend":"additive"}],"skins":[{"name":"default","attachments":{"0":{"2":{"x":-0.66,"y":104.5,"width":521,"height":621},"3":{"x":-0.66,"y":104.5,"width":521,"height":621},"4":{"x":-0.66,"y":104.5,"width":521,"height":621},"5":{"x":-0.66,"y":104.5,"width":521,"height":621},"6":{"x":-0.66,"y":104.5,"width":521,"height":621},"7":{"x":-0.66,"y":104.5,"width":521,"height":621},"8":{"x":-0.66,"y":104.5,"width":521,"height":621},"9":{"x":-0.66,"y":104.5,"width":521,"height":621},"10":{"x":-0.66,"y":104.5,"width":521,"height":621},"11":{"x":-0.66,"y":104.5,"width":521,"height":621},"12":{"x":-0.66,"y":104.5,"width":521,"height":621},"13":{"x":-0.66,"y":104.5,"width":521,"height":621},"14":{"x":-0.66,"y":104.5,"width":521,"height":621}},"diguang_0":{"diguang_0":{"x":2.11,"y":10.26,"width":444,"height":529}}}}],"animations":{"animation":{"slots":{"0":{"color":[{"color":"ffffff00"},{"time":0.0333,"color":"ffffffff","curve":"stepped"},{"time":0.4333,"color":"ffffffff"},{"time":0.4667,"color":"ffffff00"}],"attachment":[{"name":"2"},{"time":0.0667,"name":"3"},{"time":0.1,"name":"4"},{"time":0.1333,"name":"5"},{"time":0.1667,"name":"6"},{"time":0.2,"name":"7"},{"time":0.2333,"name":"8"},{"time":0.2667,"name":"9"},{"time":0.3,"name":"10"},{"time":0.3333,"name":"11"},{"time":0.3667,"name":"12"},{"time":0.4,"name":"13"},{"time":0.4333,"name":"14"}]},"diguang_0":{"color":[{"color":"ffffff00"},{"time":0.0333,"color":"ffffffff","curve":"stepped"},{"time":0.2,"color":"ffffffff"},{"time":0.4667,"color":"ffffff00"}]}}}}},[0]]],0,0,[0],[-1],[0]]