{"paths":{"0":["spine/gezi/guangtianshi",2],"1":["spine/cai/skeleton",4],"2":["ui/summer_bg7",4],"3":["spine/niudanji/niudanji",2],"4":["ui/national_img4_1",4],"5":["ui/halloween_bg4",4],"6":["ui/zhuanKuai-2",4],"7":["ui/national_bg1",4],"8":["spine/rk/rk",2],"9":["ui/national_bg3_1",4],"10":["ui/national_btn2_1",4],"11":["spine/dj/dj",2],"12":["ui/halloween_txt2_1",4],"13":["spine/gx/gx",2],"14":["spine/cai/skeleton",2],"15":["ui/national_gift3",4],"16":["ui/zhuanKuai-1",4],"17":["ui/national_bar1_icon2",4],"18":["ui/map1",4],"19":["ui/national_btn1_1",4],"20":["spine/gezi/guangtianshi",3],"21":["spine/dizuo/dizuo",2],"22":["ui/zhuanKuai-4",4],"23":["ui/halloween_txt4_1",4],"24":["spine/wansehn/wansehn",2],"25":["spine/cai.atlaseton",3],"26":["spine/shengdianxunbao/shengdianxunbao",4],"27":["spine/zhuanPan/zhuanPan",4],"28":["spine/guangtianshi/guangtianshi",2],"29":["ui/common_btn3_26",4],"30":["ui/map2",4],"31":["spine/wansehn/wansehn",4],"32":["ui/national_btn1_3",4],"33":["spine/zhuanPan/zhuanPan",2],"34":["spine/cx/cx",2],"35":["ui/halloween_btn3_2",4],"36":["ui/national_bar1_1up",4],"37":["spine/gezi/guangtianshi",4],"38":["ui/national_btn1_4",4],"39":["ui/halloween_gift2",4],"40":["ui/national_gift2",4],"41":["ui/halloween_bg2",4],"42":["ui/summer_img8_1",4],"43":["ui/summer_txt6_2",4],"44":["spine/gx/gx",4],"45":["ui/national_bg2",4],"46":["spine/yh/yh",2],"47":["spine/niudanji/niudanji",4],"48":["ui/national_img3_2",4],"49":["spine/gx/gx",3],"50":["spine/guangtianshi/guangtianshi",4],"51":["ui/national_txt2_1",4],"52":["spine/rk/rk",3],"53":["ui/national_bg3",4],"54":["ui/zhuanKuai-3",4],"55":["spine/beijing/beijin",2],"56":["spine/rk/rk",4],"57":["spine/beijing/beijin",3],"58":["spine/dizuo/dizuo",4],"59":["spine/beijing/beijin",4],"60":["spine/yh/yh",4],"61":["ui/national_bg2_2",4],"62":["spine/guangtianshi/guangtianshi",3],"63":["ui/halloween_bar1_icon1",4],"64":["ui/national_btn1_2",4],"65":["ui/national_img1_1",4],"66":["spine/cai/skeleton",3],"67":["ui/national_bg4",4],"68":["ui/national_gift1",4],"69":["spine/wansehn/wansehn",3],"70":["spine/dizuo/dizuo",3],"71":["ui/national_txt1_2",4],"72":["ui/halloween_txt1_2",4],"73":["spine/dj/dj",4],"74":["spine/shengdianxunbao/shengdianxunbao",2],"75":["spine/dizuo2/dizuo2",4],"76":["spine/cx/cx",4],"77":["ui/halloween_bg3_1",4],"78":["ui/national_bar1_icon1up",4],"79":["spine/yh/yh",3],"80":["spine/dj/dj",3],"81":["ui/national_btn3_1",4],"82":["spine/shengdianxunbao/shengdianxunbao",3],"83":["ui/national_txt4_1",4],"84":["ui/national_txt3_1",4],"85":["ui/national_bar1_icon1",4],"86":["ui/halloween_txt3_1",4],"87":["spine/zhuanPan/zhuanPan",3],"88":["ui/national_btn3_2",4],"89":["ui/halloween_gift1",4],"90":["ui/summer_txt7_1",4],"91":["ui/national_bar1_1",4],"92":["ui/national_img3_1",4],"93":["ui/national_btn3_1up",4],"94":["ui/halloween_bar1_icon1up",4],"95":["ui/halloween_bar1_icon2",4],"96":["spine/cx/cx",3],"97":["spine/dizuo2/dizuo2",3],"98":["ui/national_img2_1",4],"99":["ui/BG",4],"100":["spine/niudanji/niudanji",3],"101":["ui/national_btn2_2",4],"102":["ui/halloween_img4_1",4],"103":["spine/dizuo2/dizuo2",2],"104":["ui/national_bg3",1,1],"106":["ui/national_btn1_2",1,1],"108":["spine/gx/gx",1,1],"112":["ui/national_bg2",1,1],"116":["item/HalloweenExchangeItem",0],"120":["ui/common_btn3_26",1,1],"122":["item/HalloweenTaskItem",0],"123":["ui/national_gift3",1,1],"124":["ui/national_gift2",1,1],"126":["ui/national_btn3_1",1,1],"127":["ui/national_bg2_2",1,1],"133":["ui/halloween_bg3_1",1,1],"135":["spine/zhuanPan/zhuanPan",1,1],"137":["ui/halloween_gift1",1,1],"138":["prefab/HalloweenTurnTaskUI",0],"139":["ui/halloween_bg4",1,1],"140":["ui/national_btn1_4",1,1],"144":["ui/national_gift1",1,1],"148":["spine/dizuo/dizuo",1,1],"150":["spine/rk/rk",1,1],"151":["spine/yh/yh",1,1],"153":["ui/halloween_txt3_1",1,1],"156":["ui/BG",1,1],"157":["prefab/HalloweenExchangeUI",0],"160":["ui/national_btn3_1up",1,1],"163":["prefab/HalloweenTurnGiftUI",0],"164":["ui/map2",1,1],"166":["ui/zhuanKuai-1",1,1],"167":["ui/national_bar1_1up",1,1],"169":["ui/national_txt2_1",1,1],"172":["ui/national_btn2_1",1,1],"173":["ui/national_btn1_3",1,1],"175":["ui/national_img1_1",5],"178":["ui/national_bar1_icon1up",1,1],"180":["spine/beijing/beijin",1,1],"182":["ui/national_img3_1",1,1],"183":["prefab/HalloweenMainUI",0],"184":["ui/national_bg3_1",1,1],"187":["spine/shengdianxunbao/shengdianxunbao",1,1],"188":["ui/national_txt3_1",1,1],"190":["spine/guangtianshi/guangtianshi",1,1],"194":["ui/national_bg1",1,1],"195":["ui/halloween_img4_1",1,1],"198":["ui/summer_bg7",1,1],"200":["item/HalloweenTurnItem",0],"201":["ui/zhuanKuai-4",1,1],"204":["spine/cai/skeleton",1,1],"211":["ui/national_bg4",1,1],"213":["ui/national_img3_2",1,1],"214":["ui/halloween_txt1_2",1,1],"216":["prefab/HalloweenBuyBpLevelUI",0],"218":["item/HalloweenTreasureItem",0],"221":["spine/cx/cx",1,1],"228":["spine/dizuo2/dizuo2",1,1],"230":["ui/national_img4_1",1,1],"231":["ui/summer_txt7_1",1,1],"232":["ui/halloween_bar1_icon1",1,1],"233":["ui/summer_txt6_2",1,1],"234":["spine/wansehn/wansehn",1,1],"235":["prefab/HalloweenTurnUI",0],"238":["ui/halloween_btn3_2",1,1],"239":["item/HalloweenGiftItem",0],"240":["ui/map1",1,1],"241":["ui/national_bar1_1",1,1],"243":["ui/national_img2_1",1,1],"246":["ui/summer_img8_1",1,1],"247":["prefab/HalloweenTreasureUI",0],"249":["spine/dj/dj",1,1],"250":["ui/national_txt1_2",1,1],"251":["ui/national_bar1_icon1",1,1],"253":["ui/national_bar1_icon2",1,1],"254":["ui/halloween_bar1_icon2",1,1],"255":["ui/halloween_gift2",1,1],"258":["ui/zhuanKuai-2",1,1],"260":["ui/halloween_bar1_icon1up",1,1],"265":["ui/halloween_txt4_1",1,1],"266":["spine/gezi/guangtianshi",1,1],"272":["ui/halloween_txt2_1",1,1],"273":["prefab/HalloweenFaceUI",0],"274":["ui/halloween_bg2",1,1],"275":["spine/niudanji/niudanji",1,1],"278":["ui/national_btn1_1",1,1],"280":["ui/national_btn2_2",1,1],"281":["ui/zhuanKuai-3",1,1],"283":["ui/national_btn3_2",1,1],"284":["prefab/HalloweenSignUI",0],"285":["ui/national_txt4_1",1,1]},"types":["cc.Prefab","cc.SpriteFrame","sp.SkeletonData","cc.Asset","cc.Texture2D","cc.SpriteAtlas"],"uuids":["07hojzd+dHVo4kg2/jUmY1","09OCDKFk9GmKJrsVWF3MR/","0ah3DH+6NDmJheVOM4+woB","0cbC8TbSdBT7t8jFx18Drz","19wBRAJaVPxKPurAJ+IC7O","1aMws5suxLgotIVtLnzSmL","1bKAv/1KdNS4vuKKu5gM1F","1bicNlef1OmaliWKv4lXnq","1c5k4Gx29Ck5kMC0OguCqb","1ff95yetRLgJ9kAB9xcX9r","21WNqji0lE8IZQfcJmkLJM","211XuQTK1E05YhG/uSGxSy","24YMzHOA9J5qUhJ9JN8qUK","25ec1wwwpOipNdeC73taE3","27p464CchLC7Nmc76xIRec","272t96qxFMkLTYfYlqJzDP","28XuzVzipMaq0/EhOe/8Q6","29WJBoU8ZESKLZTiqAwCGT","2a2Z2/Pr1ClpIquSLx8+51","2bEhxUuhdFRpdVwvyBZhEu","2eVi57J4VLOpA5rlBceNDP","2ezyh1wEFHMJcxI5UeTyy3","2fBoVvfdhAmJOZaVkanKwr","30wpaFMWJAfZYr/HO/04lY","32TOxOWvhJeLB0/86+G7z3","34p4ZXmb9DqqE8P0F0tdFz","36WWb5fbdGqrzjmpjGYg1K","3ajDKXzPZNNJxUXez/dWKz","3bKbCwa05DZ6p9PmZXqkeH","3eA3DAeFBLK5HKu4aBWNGB","48GOJVTsZItJEjhd9+tgSA","49HJrb0ClIK6S4rrTlZcBn","49ai66/VNIcILXTX+70jt+","4btsO7Q+BDe6ZAYXXkNyoG","54ghfVssNKAZ0PypLE0Zll","56zOlRDHFGapc2BJWVekMu","62MAnn3B9Oebri/5TrQEVq","65lyn6geNGsqHrfAOFat4R","66NXfIY+FAH4l0V5QQWhHA","66fK9cz19Ps5VWiWTf+abe","6a803UL55OQZDUy2ERCJHM","6cDqBWQPtO8rQ77u/A2RYP","6crdcbsD1HTqAmZxzarb98","6ddbX4KPNEkKUaO4kdV5Uv","75LflqvY5NxJv0GehYWOfL","79+DNm/YRFJr0K3JF/PJmR","7cJaCMHs1MY4xJjbUXiMr5","81pZfKdstIOY/PC25y2fs1","824jVBmOVGv5lgDUx39SDI","85Vyw4lDhBWYgpn7umqe3W","867ciPSctLEqWed87YgoE9","8ewglT2tpOP5VvgcfcIv1Q","91dqZLHmRMkqLjnk4+jVt0","94qYamwxRHhaf3j9TJhLUZ","95M1o+zOBBcYrDVawWrKim","95UNzy7kFE0bM9M+TB69/7","950eBsKTVBhpE86uplVB9J","97xgMmkiFPeaat8PqXOWXg","98IXU66C1ImYiQv+1ulzPV","9bhxQpn6JIrJomb8zTLqu3","9ctrRBEldJm4v5/m9e6zwq","a0GbUtfjlGeZV/qYwnNnM3","a3nKyMA8NM1brgqspNcT2D","a8T8QxRulPt5MOggotusrg","acjjGAiSpH47Bi3o0cehy0","afflLDc8RG0pMzI579qnen","b0MDzfcMJLgqi67VH3fQ3p","b15XnbztBN0rxtvCo8rD9t","b25NvC4ehE7L/I7HD51cig","b5FYJkZldJFY8tpRfY+HAp","b6NldDMx9MoIYocEolqq9a","b7ab7PJyFHMaAYkxlEtzKS","bd8IuR3IlPg5cmyaf3i7nz","c030vpBkNIlJajQ+f9ScCm","c6dXSmThNFQLZ6L/Z+6gpI","c7eXZ1GCZOZpjrmoWiOH00","caVSELk/NKXqi284vA3yTr","caagGAzoRH4L+cZ8zuaFaI","cdK9qrCW9J2LCPRD7LqJ+p","cfb9VETo9OjZlLFN6QiBIC","d1k+MEKlZIJqBvOhSF3pvA","d3w2GGtyJAQJQJw5bDxlMx","d4TQ63HtBEFpifCHVdomxH","dbgrtE4X9KirlFnwm0k0gb","ddWRAgqIVMTYIHRQNHk9TM","e2UOJ2T71LKIUvOxQXFDIb","e55l+2zSVBlqfI/+aPYGa5","eaEECuMXlJ2IJqTQhGeRCH","eaJCc+HRBL672BfoqS2+Lq","eay8gBQ7NNsbZbiwnN9Han","ebBMQ65LdJ6auShz7Kszs/","ebNLQrxDJGzoqPKRANQMOu","ecPDWzJFpHE70fmKO4BXnj","edBemm4ahCWJkcPTQFTK19","edqU0m051LnIGW5o6FFWkf","eeie9rLkdNK5EbXmwCdR1W","f0zCYLSadJhLRYqqFvG22H","f48n2iu/dNHpWGq43QHejP","f8fkfeQyJMiLzQjzDmeK5t","f9RltP2CFN544bOR27szvc","faAK+dbJ1JeI6xAMorLNaw","fcyG9tKSBIRIDK98jhnE8Y","fdYvxxVlZN5IAV+Oh/DXY+","ff2yhAjTdDl7dwe8TWg4kn","00t2jRdZZChaCWwkxHwf6H","01RuRVbtBDBrOfEVx7g6fC","01kDuUlFVKO7A1XSrMOOrv","01xwehLRVBkby+WkQ9hKfL","02G7fyDtRNPJcxDo1A7ZTY","05x5nywlFMnLX3ai+1DKFP","08bmYXn75Ly7gDNJjLrXYa","08c4Fa4FZBVI541mEZ0C1d","09SLSyH71KhrNX3AJe+w/l","0a946UwElO9p1YEFURxlnh","0d/uup0OpH4IbyllU3ZcSt","0eQs5OTQ1Kx6rMlEbuBbqI","0fInwem9RLr6hJU/h3Dh/2","0fbDXfUz1INqVcLJUNuVGB","0ffyQmuK5BjYVZ69Hh5uXo","11d9L6CfdPwJ/rCuI3REQE","13iumZuR1CVa3DvAp+iVhP","13y5dEd9dBj7Dr4/mQ8ns8","14RpGKa4VAgZ2tD2oyZmlw","19anfvfVRBa4pmHzjaDiVV","1aaBzLvSVEhJJNCz8amg9p","1a1Y1f/zpE3rQ3GtH0fkVO","1bZIQ2df1JbqMO5x71BKSm","1fvRJTNl5EjJWEWbl6xYXq","20x0vuf9ZB1IEp+B8Sqe+W","21x1x0smdI5Y91ru78kjTz","23Ay6oe5FFbKRIM6I2XG0B","23qh2GKgFIv7K5RrKzPlvt","23tUfhoPNIZoFmQBBe7tMN","24HETZhnpIwKVZDeuztuwK","24iiDu4etAZI/bK0f13faU","24sYkmP0JPcIoTLFGaNlyS","248N7Q/kpCpp07P8XjShFr","29AqLZWzZPk5IjE48rtx4q","29llKLiJVL/pMAUkkcEPi8","298oerm8lJiYUHPUhgJwWB","2aHKNBOuxKnaURQXZw/wqJ","2aRqn/RVlHI5k6DXjIs5FG","2fSlnavU5JU44qy7x2NFvn","304U0EwRBNaZ27lue9XO3L","32tL3FdP9HPLv2f+KPa1mx","34goYJECBK9YwXrrhCWzBo","35P072XvdKGoJ+tSkW3QHF","35Y2atPnFOS6QC7H/pLjyD","35h1ljkd9N4pBb7pYlnPBO","35zXQTkihHTY4iZSAuyvgP","36IFszt8ZC0aoZ9/NoOYNd","36aGh0xJpEzpN0xrM3dwWi","36o7qGFOxI9a+PE1Yrupby","37A7x/WhFH6bo8o+eFPl6f","38IUe8jmlLYa9HwGj8guWu","38IhasOwFJFZ/zK3cViGxW","38vHL6IYNA7L3DnbijbcL2","39CYzGH9xB4I7yr0pA4OGv","39KKmWP5lN6b5uC6aioYMW","3b1Baz1hxOXo9cSlb7xFr6","3b49UIHRxF7JQQylXVAC+y","3catrUeCJMFIT1JZRA6/mh","3fQA7X4rlJSJ7UzcaNyr6j","3fSyfw0UdBt5cKh2x8WTZk","3fW+4JqXRL5IqHiUIsy9MI","40mshVSphLJ5taGWR1kBod","42KAkrxVdM15P8C45DBuQR","43+13lMcRA4ag2bqZ+zDbC","44QhkBerRL+7COznXTQHD7","45A2gCzLtGZoNeIfZQ1aW4","4dJl9i3+pHjLUddqwiObsL","4eb2gTXodNjaw6rEykWIL+","4fPPNyQLJObqoRO2KpOlfh","4fyby70wlJPaTU6b/61w1W","50tnN48AFNxoSdN6Naiz3L","5228aZ03xGjbCKkBKbK5v8","53O1DO5bZCw52xeU4PuxKr","56zYmhX25GQpTT+BMexlSx","5bH8grLJ9FpKefM0Ructyv","5bZN8fSHBMlZUXNCdrQHLb","5cGYYsgkhFMqcQQiX1ltFY","5cHuqDQrJE3qI9ibvX0h6h","5d49M+iSZE0aqsRF+wuSax","60oB3PI+pLUbrtZWTpfMm/","62u5K1u1NFbJp7TjTs7VOm","63APgePGxGkpcnOQ2PUbhQ","63UgGJTXdNm5m689goLd83","65C5GD5ktFhbKy6LsywSu3","66fQOFjU5AXoHKAaVXxYKG","67UpNLJjBJ8KZH4P+lfVmC","6cY3HjkrlHUrG0N95ZF3iH","70aiFZhARKWqEBR3ZHwfgi","7076M1e8JMIYw2E17ECNOm","71OM05jGtMoqtPkNu/18rI","74IJVNHE9G07SUjE7F9dOc","75RB5NVCxKrIjRD86hMM1j","75bw3nilNGxLaFt8rlwE3w","79vRZq17ZOB5dumDltM35k","7aIX7ZyKhCFYE/L3e9DYze","7asbPq0ktCPJB3IoliD9VP","7eKV8XKIFMIbM9JhPEFOQl","7eSrsJ88hAWpLtSqxCRZUL","80F5L2TpBDIovmyY7traEn","80KgS62uxM3aEgxIUe3wYm","81eMOc2MhDBavngeNKTHc7","84evsRRjxMq422kk7+p4/f","84sngFKMtBDbMOyM78cENg","8b1vpPE4xMm7Z0WfpD6cAr","8dwgdof5NN8Z75cI6N1IGF","8ezBdgCo5MEaQNoAC8aoqb","8fWf0nx15ImoKBz39z8R/m","8fy0Y63ZJEP5TMVkcCZyYE","90L0KqK6tOIahWdONHslJR","90oL4PkaJHU7AWQhKh04D0","91aud4zN1DFJoVWoLp+kXW","93uPCdCshEGL7aoZiDYFDZ","94+zk552dNiKhHIrFGQaqx","959F5O975E0oFkeC/tD7d4","974PN6UQpO0KSE1CJpCYtI","9bFdO8eGNEuI/wM+8J5stx","9eKVTVq8BME701clReFQpq","9ei4+vi99Gpr+H2u5V8boW","a0BuQNKvtLo5XPIOBVz80Z","a2WPmpEa5F56iPWDZ+esYM","a2t1KDZYJM75Osk2FuXzmV","a2vts1eZFH0KSshBBC6D5H","a4yPFxBnNGaIdeSpwTU1td","a41MxElhNBzbJrUFRzr5nN","a5GrgYTitBQYyNTszb58zP","a5YV16V0tDXrBeAvKY6SJo","a6iuwYRVdBeJKa6t+e7VLG","acEHmfHuxFqp/ua3NDP6n7","adHaVGH7hBG7hVyptUZp5R","afoKlUdXJAcbE5+B7cpYV7","b0/sfs5PtAVZCa5Dy2eTYk","b2KO1NRSVF0r+QnFOrHRrp","b5jqNDLUZHrKVzN+EW7Qla","b6XpmOblJAU7aEomCR9Io+","bagprzi9BORqXEqODkxUqV","bayb8m3PtIeL9/2wGYJ/Yg","bbxNTY4MpN67oHYmIIsqvJ","beEkHlnR5I46xZiUmCjjLO","be7Dp9G2FCR69tqS/UpShn","c0M1/HhotP7JrcQBpadYrL","c2yI9SziRCrIZiOMnpVNFw","c3J4kui/xA84YQ7xJSmd4+","c4kDQKteVFVr48u8VarVGm","c6dVpfa5JMkIpAJh8Q4pOr","c7Qas0/lNOnY+O1HlfTXV0","c8GV3iErJNKIy7rVlVWQKO","c8VoEmNEVBhbF4oc1UVTiB","c8y7cRWzVEna7ASC5WoC2X","c9tcio+M1LepUAtLn6hN8A","cdU05E5lJKhasiysIhugp2","d1x0MB2/JBTbYKsmww62ga","d2+fOLwb5KQYtHDaqjPXIh","d3yQjKp1xFcYq6ES/X4ydl","d9VYk/toxN9IZv0lornC//","db7gBj17pD5JwtAYiiWxZs","e1BENf7sBLJ5UIREdSKXkZ","e3jAWBhChAtaCMQ4xOkZgy","e4lK6BQyVB9qEMpv58Qa6r","e5H+/r9ydN2rZVyR8wGIdo","e6y8W7rUJBnqDS5lZlB7Ow","e8QFcDyWtJ1qEHqOGYI6ki","e9boAvSPZIe5cNPKX4ywsA","e9dbQC9aFLAq6qVuSvHJCm","eam1aVSW5E6puZ0MjBKk6v","ebTSKpoZ5CMZ1bos148xjV","ebWuwB5DxGgLejFWuTdJmc","eeSdMyWSJCCIo0y9Cd96a/","efLBnoxzxIkZVevSMkjLj/","ef0AB6wJZCYaQ7N/5yzBvq","f1Z9h0PEdNQY9PlWuGGAsB","f1o/qTaGhDLZEckzqQZv7u","f3t1FQRTFIBb9+WobM23Bz","f33MNrt0VCSq1mLvMCfrSe","f50aXiCLhO2qFG1VEX5AwC","f6q8eZhjxAoYbMTot3hFKs","f68SBvKqhJKYhrp2jD3j9/","f7A3FEV5hE8YKE8nFdgTLl","f70SbB69FAbpl2M8u63Zuj","f7/hLOQKtC6qExH8J7qtBF","faH7ZDd+BKCLGGvq07rPVH","fcZst4Em1JUIZVHcocUuyH","fevvAQdKBFDK52CB9lcGEY","fewJYQKAtBvKS6/giou/cj","02m6lgMTNIwa5nPzIIKQuE","03frwY/FtNeZ6FbP35g21q","05gaUXeRNA+6ZS5SI/8xqp","07N1cg0mRLqIR8XKFfqTI/","07g2EmcqpIl5DaaTk2KY7H","0aA2B/109MQ5wQjocA0hko","0a3tbvz5VHq7RPZqvubxD1","0a4Ax9vkZMs5x7z6k7HLOf","0b0xHdOVdPG4+c931kVynm","0cNx4AR0JJ0boBHOnrtZUw","0eej4Aau5IUL8SHV5BGZCL","10oX0EDD1Bt7Px2J+jjNDg","13R/Z0AGhNgIbrCho+JHBv","136H2TVzhPvLSsIN+qG1Ge","14sjeSakZEa4TxXsIlVOYB","18HSFrho5Bw70h61jN4TK3","19I7kxUdBAdofIQy6jQ/bx","19og+xLbBIk4PERd7HiU6E","1aTHu/MyhNJrHw5US/1x/c","1eJ3mFMnNOxLVuGH+M3AzA","1fLh5PSypNaYFW+Tnf1AgB","20XIC8Yy5Lh6fHf9FqzoXO","20uJdGAPlAPbkbInb7Y0Fe","29FYIk+N1GYaeWH/q1NxQO","30cWf+VIZIJpOMq9Rfk8Qk","30ryEMNRtNsLXoenr1gGj3","31IDHP431PmpPIMhU7aoqj","32MvyQTDRAK59s6+qBVxsK","32REVTkb1ObYo+JvRK+O2h","332/Ypp/NGk4YUzVKUjwjp","34IDyjszBJxqvnRjrGDOqB","34eVw3BQNMUaS9lHerje3b","35yojXjVBAboHTsrfJP16R","3eJrQTZgdHK792eU2IuGzx","3eYKTMEdRH5LhraMA6wVXK","41g7z75VJNEpie2zC/aT/Q","46Xq7q8odLCLT6mrtcPZxR","47IC7z8AhAGoGF2GqF4txq","48m2CIY95MerzvrWkozQ9i","4aAmef63hPdZS8HUmYyTZW","4aRmgwzZtHlbPt5r6dxGjb","4ah09iLMFFKrBKdpc3jbR5","4cKHINjSVKP4sZkNBVph92","4c4g7wReZGmpFmp21KYkU5","4dT2acsOFMcaJbqxp7N5Hw","50HY+4aHRMTa2AKNupH7cD","543EolVd5Feq0ZXjxyQwIZ","57JJESq1RPF6gc54BloHJl","59Xuzgr5hMUavQcWL9OkxB","59jLUEBVROGJr2xJA2b/CJ","5aNBw+DAtG9oPzbcuTuv1v","5fyQaCJO5O9aWD9HKagTjX","60yikTuhJBn5TAcMYzmQ1R","61URN8+l1JDbV8xFE97+s0","64fgpL0jBEJ5W91fG/+4wX","6eVDfw46FC6KeaKL67mh7D","72FBGT1tRNg4Ptm82ALNi3","72lAD64YJJRaDyKfrCiipM","738mkEHzlFIbGjG/eBAvcL","79y05ShDhHUK9g2azujLuL","7a/QZLET9IDreTiBfRn2PD","7bKPN4SgdMsIu3oY3QdOYj","81oU2lFWdPNZV8Md8ZZciw","82JouQY4xDaI8RdjkAuVZX","82Q6sHYo5KsrdK9M/2zDOk","85qEsKzRNMNKHRoQp04onR","89CucvXeRG4o5AEufVPmKb","8bKXNc8VhOpKxKNf3xtzMH","8dk4r9dL5PkKKxNPcSjX8h","8dzaEnnh1CgrBDlRP15Sqr","8eGhrgW/JBdqF+V7UhGCGK","9bBV4q2zFP7rOfODGeno2h","a18MYo+NJFBKD9gv7wsBAa","a2MjXRFdtLlYQ5ouAFv/+R","a6LVbNoupIirIDrApqMG8A","a9IId3O1tNuqr02flV62jO","b2aeYWU0NHK7JBdGp0G4xx","b48qYx5cpK5KKgda9AI68i","b9cshHfAZKtbyHgdluStFz","c1n+SOSGNA37J97kSFiVOo","c7KdCM5+9ExYUhjGTU578I","c8Qu3qHcBCM6Mvi7slJ0Bi","c9gcuVRWJIE750gmJ3EXhv","ccBMhAU1RGpbuCVq29NdXy","d6/34sArxFEqTHYbTANRRc","d9dQQpFstMNZaj6+NbaIc0","daMrKIsOVLdLiAXooNjxZO","e1UdWnb1JKdr2hvBc1hnor","e691lQ9MFABYTWVufOgA2U","e8JJbnC2dC/5TNxZIJnFjD","e9oKCsroFLGrOBcsFeWF3B","e92N5oH5lBwbhLBKGsJV+T","eaeYQ+3YFHBo+K5JioESUZ","eanPCOFGtFOr5WXSfJpy6o","ecpdLyjvZBwrvm+cedCcQy","eeJSKlIglNfZduPqWcaZYt","eevz9gFFFCoLKGR8cd31UI","f0BIwQ8D5Ml7nTNQbh1YlS","f0l9otAl9NRrgRHVHAJ49L","f2MjClZp5AA4fsu3/VVJ9K","f7G+6+x3FMc58Fr0u/S7zy","f89amjTF9BFrb9tY4+LjKD","feUmkr3U1PtL5XW3uSvuM7","fed1+7gABHAoZQQ49VrX+R"],"scenes":{},"redirect":[310,0,316,0,343,0,347,1,360,0,361,0,381,1,384,0],"deps":["resources","internal"],"packs":{"01c4b7a86":[292,293,296,298,314,336,338,339,346,198,348,349,355,356,231,363,364,366,246,372,377,379,385,284],"044d7466f":[106,140,156,173,183,269,278],"05cd2512b":[299,303,305,133,153,161,320,164,327,335,342,345,354,224,235,238,240,254,371,387,390],"064c61b76":[287,300,321],"075771f25":[307,175],"0891e6aea":[171,174,244],"09a462a96":[288,218,358],"0a37e343d":[289,297,312,313,172,247,368,272],"0aef19ba9":[138,323,344,195],"0b288652f":[116,341,367],"0b465efaf":[304,309,317,319,322,324,353,357,216,370,382],"0bef564f5":[337,383,273],"0da9af9ad":[137,163,255,374],"0db4f3ccb":[105,107,109,110,111,1,2,113,114,115,117,118,119,121,4,5,125,6,7,9,128,10,129,130,131,132,12,134,136,15,16,17,141,18,19,22,142,23,143,145,146,147,149,26,152,154,155,158,27,159,29,162,165,168,30,31,32,170,176,35,179,181,36,185,186,37,38,39,189,40,41,42,43,191,192,193,44,196,197,45,199,202,203,47,48,205,206,50,207,208,51,209,210,212,215,53,54,56,217,58,219,59,60,220,222,61,223,225,226,227,229,63,64,65,67,68,236,237,71,72,242,73,245,248,75,252,76,77,78,81,256,257,83,84,259,85,261,262,86,263,264,88,267,89,90,91,268,92,93,94,270,95,271,276,277,279,282,98,99,101,102,286],"0dffe13c2":[290,291,294,295,301,302,306,308,311,315,318,325,326,329,330,333,177,340,350,351,352,362,369,376,378,380,386,388,389],"0f8b30691":[139,157,373,265],"0fac07e12":[123,239]},"name":"net_activity_halloween","importBase":"import","nativeBase":"native","debug":false,"isZip":false,"encrypted":false,"versions":{"import":[104,"849b4","01c4b7a86","41478",108,"a9843","044d7466f","733ee","05cd2512b","31551","064c61b76","b6df7","075771f25","2f94f",0,"6598a","0891e6aea","3e357",112,"ea458","09a462a96","17d03","0a37e343d","d74ee","0aef19ba9","c0c31","0b288652f","0148d","0b465efaf","17410","0bef564f5","4ec2d",3,"334bf","0da9af9ad","1e91e","0db4f3ccb","363ee","0dffe13c2","232d7","0f8b30691","aedfb","0fac07e12","4ae21",120,"792e1",122,"5631a",124,"e8e65",126,"062f4",8,"f49b2",127,"a5298",11,"bef29",135,"b896e",13,"a1ce9",14,"7da77",20,"ad470",21,"e8459",24,"c51d9",144,"7608a",25,"0b044",148,"272b1",150,"f13ef",151,"b9e4a",28,"71ddf",160,"23e40",166,"4e7ee",167,"19b5f",169,"4d403",328,"bbfd1",33,"2b0eb",331,"72795",332,"92bb6",34,"b282a",334,"9e500",178,"08877",180,"9cb46",182,"00740",184,"af34b",187,"b843d",188,"c24eb",190,"7ca12",194,"c24cf",46,"49496",200,"d3d8f",201,"fddfe",204,"02abe",49,"20618",211,"b9ede",213,"5edf5",214,"69af6",52,"356de",55,"665cb",57,"6dbae",221,"2aa3d",359,"d4c59",62,"ad470",228,"53870",230,"52b81",232,"9198c",233,"ab7d8",66,"08689",234,"a3831",69,"9758b",70,"55425",365,"357b7",241,"66c86",243,"28d1c",74,"bab60",249,"b875b",250,"49c8c",251,"280b0",253,"108eb",79,"9bbaa",80,"6775e",82,"94a38",258,"ee69f",260,"9d212",375,"a6b16",266,"4a259",87,"360bf",96,"abb4c",274,"e6ff4",275,"1b4f3",97,"315f3",280,"262bf",281,"0bb09",100,"edf5b",283,"71071",285,"73c95",103,"9965f"],"native":[105,"de1e3",107,"e1cf6",109,"98df1",0,"52e85",110,"d770d",111,"3b356",1,"0feaf",2,"672e2",113,"2547c",3,"01ba0",114,"88a9a",115,"48caf",117,"0663f",118,"af434",119,"4749e",121,"b46f9",4,"b2851",5,"6a3f1",125,"df463",6,"4ddc0",7,"89013",8,"fc755",9,"8e220",128,"2f9f4",10,"2083c",129,"b2047",11,"4f40b",130,"6f216",131,"049ea",132,"e7620",12,"cffcf",134,"156bc",136,"acb74",13,"552f6",14,"f6e5e",15,"7c779",16,"242f6",17,"f73d6",141,"64fc8",18,"54554",19,"371e5",20,"4a167",21,"3934c",22,"080ff",142,"9eb93",23,"98352",143,"7c779",24,"fb194",145,"daaf6",25,"92f3e",146,"802ce",147,"7b75b",149,"7395c",26,"06683",152,"226ce",154,"41696",155,"ce306",158,"4ca32",27,"23575",28,"e9f67",159,"00039",161,"52e85",29,"cc068",162,"ded0c",165,"c38f3",168,"6bec0",30,"5a334",31,"0f093",32,"1c51d",33,"394a8",170,"ce3be",171,"f6e5e",174,"4f40b",176,"86e9c",34,"0c043",35,"ab345",177,"3092d",179,"65c12",181,"c82fb",36,"1f793",185,"e6267",186,"d47a9",37,"65c12",38,"50eb0",39,"d679b",189,"1f793",40,"f4bbf",41,"f4748",42,"abb0c",43,"b5e75",191,"90375",192,"6b5ad",193,"83ce0",44,"ad9aa",196,"9bb23",197,"b1a24",45,"a2778",199,"2a4f4",46,"cf588",202,"55c40",203,"f67f3",47,"fd78b",48,"4d564",205,"65090",206,"b9599",49,"c321b",50,"20591",207,"843b3",208,"47a82",51,"2329e",209,"91266",210,"2a3ed",212,"3c7fc",52,"2e286",215,"4fbba",53,"40d60",54,"3ba74",55,"b4a1b",56,"2a3ed",217,"8dd7f",57,"4c289",58,"27f6b",219,"ec69c",59,"e69be",60,"e46fe",220,"018ed",222,"58f34",61,"eeb35",223,"0feaf",224,"cf588",225,"1a887",62,"0d9da",226,"94a4d",227,"1b226",229,"14f29",63,"513a6",64,"1fe9c",65,"c74ca",66,"92f3e",67,"0ec11",68,"0a308",69,"18e41",236,"e46fe",70,"31df5",237,"e96f5",71,"84f4c",72,"2f05d",242,"f1556",73,"86e9c",244,"0c043",245,"cc068",74,"48190",248,"00c25",75,"ef24c",252,"b7362",76,"f1556",77,"0d9e6",78,"d47a9",79,"44329",80,"102f2",81,"d6d51",256,"3ce62",82,"9391b",257,"cc0d7",83,"55912",84,"dd238",259,"c164f",85,"47a82",261,"27e34",262,"2083c",86,"26a9e",263,"c1e8e",264,"6ef06",87,"6fbbe",88,"4e109",267,"61fdc",89,"59f97",90,"46f4d",91,"98df1",268,"5bd06",269,"fc755",92,"66fcb",93,"e1cf6",94,"0f629",270,"84d0d",95,"07e93",271,"fd39b",96,"3ff00",276,"364b5",97,"4b15e",277,"66d18",279,"d6d51",282,"1f7a8",98,"10e51",99,"d0885",100,"795dd",101,"ded0c",102,"20c3d",286,"10e51",103,"270a2"]}}